Workbook

Sheet Settings
A1: CLOUDIT AUTOMATION & ACCOUNTING SERVICES LLC
A2: System Settings — Change yellow cells to update all calculations
A4: GENERAL SETTINGS
A5: Parameter | B5: Value | C5: Unit | D5: Notes
A6: Standard Working Hours/Month | B6: 160 | C6: Hours | D6: 22 days × 8 hrs
A7: Working Days/Month | B7: 20 | C7: Days
A8: INR to USD Conversion Rate | B8: 85 | C8: INR/USD | D8: Change this when rate changes
A9: Period | B9: Jan 2026 | D9: Update each month
A11: UTILIZATION THRESHOLDS
A12: Parameter | B12: Value | C12: Unit | D12: Notes
A13: High Utilization (Green) | B13: 0.85 | C13: % | D13: Above this = overloaded/optimal
A14: Medium Utilization (Yellow) | B14: 0.65 | C14: % | D14: Between this and High = review
A15: Low Utilization (Red) | B15: 0.5 | C15: % | D15: Below this = underutilized
A17: INCREMENT SCORING WEIGHTS
A18: Dimension | B18: Weight | C18: Max Score | D18: Notes
A19: Utilization Score | B19: 0.25 | C19: 25 | D19: Billable hours / standard hours
A20: Client Profitability | B20: 0.2 | C20: 20 | D20: Revenue vs cost of clients served
A21: Efficiency Score | B21: 0.15 | C21: 15 | D21: Work Composer accuracy
A22: Tenure & Loyalty | B22: 0.15 | C22: 15 | D22: Years of service
A23: Designation & Responsibility | B23: 0.15 | C23: 15 | D23: Role complexity
A24: Revenue per Head | B24: 0.1 | C24: 10 | D24: Billing / employee cost
A25: Total | B25: =SUM(B19:B24) -> 1 | C25: =SUM(C19:C24) -> 100 | D25: Must equal 100% / 100
A27: INCREMENT SLAB PERCENTAGES (v2)
A28: Slab | B28: Increment % | C28: Score Range
A29: Scoring Model | B29: Historical 60% + Future 40%
A31: Exceptional | B31: 0.175 | C31: Score 85-100 → 17.5%
A32: High Performer | B32: 0.12 | C32: Score 70-84 → 12%
A33: Meets Expectations | B33: 0.075 | C33: Score 50-69 → 7.5%
A34: Below Expectations | B34: 0.03 | C34: Score 30-49 → 3%
A35: Underperformer | B35: 0 | C35: Score 0-29 → 0%

Sheet ① Timelog Input
A1: PASTE YOUR TIMELOG DATA HERE
A2: Instructions: Copy-paste from your timelog export. Keep headers in Row 3. Max 200 employees.
A3: ID | B3: Employee Name | C3: Employee ID | D3: Reporting Manager | E3: Controller | F3: Employment Type | G3: Designation | H3: Department | I3: Total Hours | J3: Billable Hours | K3: Approved Hours | L3: Efficiency Score | M3: Work Composer Time | N3: WC Diff Hours | O3: WC Percentage | P3: Last Updated | Q3: 406 CONSULTING LLC | R3: 4P TAXES LLC | S3: AB CAPSTONE GROUP | T3: ABACUS BUSINESS SOLUTIONS, LLC | U3: ACE CPA | V3: ACT NOW FINANCIAL SERVICES, LLC | W3: ACTION ACCOUNTING | X3: AMI US HOLDING INC. | Y3: ANCIENT CITY ACCOUNTING LLC | Z3: BEAM ACCOUNTING INC | AA3: BORISTAX INC | AB3: BRADLEY FINANCIAL SERVICES LLC | AC3: BRIGHTSKIES BUSINESS SERVICES, LLC | AD3: BUSINESS NAVIGATORS LLC | AE3: CASCFO Advisory- United States | AF3: CENTURION TAX AND ACCOUNTING | AG3: CHRIS WHALEN CPA, LLC | AH3: CLARK FINANCIALS | AI3: CLOUDIT | AJ3: COHEN AND ASSOCIATES | AK3: DOR BUSINESS GROUP LLC | AL3: EVERMORE FINANCIAL SERVICES LLC | AM3: Fleming Accounting Solutions | AN3: FULL COMPLIANCE, LLC | AO3: H J EDWARDS | AP3: HELLO ACCOUNTAX | AQ3: HIA TAX | AR3: IAM ACCOUNTING LLC | AS3: INNOVATIVE CONSULTING & SOLUTIONS, LLC | AT3: INVENT WEALTH, CPA | AU3: jmWILLIAMS, CPA, LLP | AV3: JOHNSON & ROBINSON LLC | AW3: LEANCORP ACCOUNTING | AX3: LIFETIME FUNDING, LLC | AY3: MAINSPRING SOLUTIONS | AZ3: MARTIN D. EISENSTEIN, CPA | BA3: MATHESON & ASSOCIATES | BB3: MCFADDEN ACCOUNTING | BC3: MEJIA & ASSOCIATES, INC. | BD3: MERAKI ACCOUNTING & TAX LLC | BE3: NATIONAL TAX CENTERS, LLC | BF3: NEW AGE IRON WORKS, INC. | BG3: NEWELL TAYLOR CPA | BH3: NUMBER NUTTZ CONSULTING | BI3: ONE KOSMOS, INC. | BJ3: PORCHEA & LOTT ACCOUNTING | BK3: PROVISION ACCOUNTING SOLUTIONS | BL3: PW ADVISORS LLC | BM3: RATHEL’S ACCOUNTING SERVICE, INC | BN3: ROSEN KUSLANSKY CPA PC | BO3: RRAW CPA LLP | BP3: RTW XXACT ENTERPRISES, LLC | BQ3: SFSG BILLING PROJECT | BR3: SMALLHOLD INC | BS3: SOUTH FLORIDA SECURITY GROUP | BT3: TAX GEEK LLC | BU3: THE PROFIT SCALE THRIVE | BV3: THE TAX CUTTERY | BW3: THINKING MAPS, INC. | BX3: TREE OF LIFE FUNDING INC | BY3: TRI SCAPES | BZ3: WB MORROW | CA3: WE ARE QUADRANT | CB3: WIGGS CPA TAX & ACCOUNTING | CC3: XPERT BOOKKEEPING LLC | CD3: Total Firms Hours
A4: 1 | B4: Ankit | C4: CAS-IH_1070 | D4: Jasleen.D | E4: Jasleen.D | F4: In-house | G4: Associate | H4: Accounting | I4: 113.42 | J4: 113.42 | K4: 113.42 | L4: 100% | M4: 111.38333 | N4: 2.0366667 | O4: 1.83% | P4: 03/03/2026 | R4: 21.5 | AI4: 5.84 | AR4: 86.08 | CD4: 113.42
A5: 2 | B5: Astha.D | C5: CAS-IH_1092 | D5: Anshul Ohri | E5: Jasleen.D | F5: In-house | G5: Associate | H5: Accounting | I5: 156.75 | J5: 156.75 | K5: 156.75 | L5: 100% | M5: 152.16667 | N5: 4.5833333 | O5: 3.01% | P5: 03/03/2026 | AT5: 156.75 | CD5: 156.75
A6: 3 | B6: Pragati.S | C6: CAS-IH_1105 | D6: Anshul Ohri | E6: Jasleen.D | F6: In-house | G6: Asst. Team Lead | H6: Accounting | I6: 125.58 | J6: 125.58 | K6: 125.58 | L6: 100% | O6: -- | P6: 03/03/2026 | AC6: 69.58 | AI6: 16.61 | AT6: 3.82 | AY6: 27.4 | BA6: 8.17 | CD6: 125.58
A7: 4 | B7: Anshul.O | C7: CAS-IH_1109 | D7: Jasleen.D | E7: Jasleen.D | F7: In-house | G7: Team Lead | H7: Accounting | I7: 157.42 | J7: 157.42 | K7: 157.42 | L7: 100% | M7: 130.46667 | N7: 26.953333 | O7: 20.66% | P7: 03/03/2026 | Y7: 4.5 | AC7: 31.67 | AD7: 9.5 | AI7: 19.5 | AQ7: 6 | AT7: 19.5 | AY7: 6 | BA7: 0.5 | BG7: 2 | BO7: 5 | BZ7: 53.25 | CD7: 157.42
A8: 5 | B8: Shefali.B | C8: CAS-IH_1122 | D8: Anshul Ohri | E8: Jasleen.D | F8: In-house | G8: Associate | H8: Accounting | I8: 147.41 | J8: 147.41 | K8: 147.41 | L8: 100% | O8: -- | P8: 03/03/2026 | AI8: 5.92 | BA8: 141.49 | CD8: 147.41
A9: 6 | B9: Sandesh.H | C9: CAS-IH_1149 | D9: Anshul Ohri | E9: Jasleen.D | F9: In-house | G9: Associate | H9: Accounting | I9: 166 | J9: 166 | K9: 166 | L9: 100% | O9: -- | P9: 03/03/2026 | AB9: 43.5 | AC9: 122.5 | CD9: 166
A10: 7 | B10: Robin.S | C10: CAS-IH_1162 | D10: Anshul Ohri | E10: Jasleen.D | F10: Remote | G10: Associate | H10: Accounting | I10: 141.24 | J10: 141.24 | K10: 141.24 | L10: 100% | O10: -- | P10: 03/02/2026 | AI10: 1 | AT10: 140.24 | CD10: 141.24
A11: 8 | B11: Vijet.B | C11: CAS-RR_2371 | D11: Anshul Ohri | E11: Jasleen.D | F11: Remote | G11: Associate | H11: Accounting | I11: 157.75 | J11: 157.75 | K11: 157.75 | L11: 100% | O11: -- | P11: 03/03/2026 | AI11: 2 | AQ11: 73 | BG11: 82.75 | CD11: 157.75
A12: 9 | B12: Somya.B | C12: CAS-IH_1169 | D12: Anshul Ohri | E12: Jasleen.D | F12: Retainer | G12: Sr. Associate | H12: Accounting | I12: 146.75 | J12: 146.75 | K12: 146.75 | L12: 100% | O12: -- | P12: 03/03/2026 | Y12: 139.75 | AI12: 7 | CD12: 146.75
A13: 10 | B13: Jasleen.D | C13: CAS-IH_1069 | D13: Andrew Jindal | E13: -- | F13: In-house | G13: Controller | H13: Accounting | I13: 107 | J13: 107 | K13: 107 | L13: 100% | O13: -- | P13: 03/03/2026 | R13: 2 | T13: 6 | Y13: 2 | AB13: 2 | AC13: 2 | AD13: 2 | AE13: 20 | AI13: 54 | AL13: 2 | AQ13: 2 | AR13: 2 | AT13: 2 | AY13: 3 | BA13: 2 | BG13: 2 | BO13: 2 | CD13: 107
A14: 11 | B14: Jyoti | C14: CAS-IH_1037 | D14: Andrew Jindal | E14: -- | F14: In-house | G14: Controller | H14: Accounting, Business Tax, VA | I14: 151.9 | J14: 151.9 | K14: 151.9 | L14: 100% | O14: -- | P14: 03/03/2026 | Q14: 3.75 | AI14: 40.16 | AM14: 0.5 | AN14: 2 | AT14: 89.16 | AZ14: 9.75 | BE14: 3.33 | BK14: 0.75 | BL14: 2.5 | CD14: 151.9
A15: 12 | B15: Vini | C15: CAS-IH_1018 | D15: Andrew Jindal | E15: -- | F15: In-house | G15: Controller | H15: HR | I15: 10.42 | J15: 10.42 | K15: 10.42 | L15: 100% | O15: -- | P15: 03/03/2026 | AI15: 10.42 | CD15: 10.42
A16: 13 | B16: Asmita | C16: CAS-IH_1049 | D16: Jyoti | E16: Jyoti | F16: In-house | G16: Sr. Associate | H16: Accounting, Business Tax | I16: 115.67 | J16: 115.67 | K16: 115.67 | L16: 100% | M16: 132.81667 | N16: -17.146667 | O16: 12.91% | P16: 03/02/2026 | AI16: 1 | AM16: 14.5 | AT16: 18.92 | AU16: 22.75 | AZ16: 23.5 | BE16: 4.75 | BK16: 11.75 | BL16: 7.5 | BT16: 11 | CD16: 115.67
A17: 14 | B17: Nikita | C17: CAS-IH_1041 | D17: Andrew Jindal | E17: -- | F17: In-house | G17: Controller | H17: Accounting, Business Tax, VA, L&D | I17: 101 | J17: 101 | K17: 101 | L17: 100% | O17: -- | P17: 02/26/2026 | U17: 4 | AI17: 72 | BM17: 9 | CA17: 14 | CB17: 2 | CD17: 101
A18: 15 | B18: Ayushi | C18: CAS-IH_1051 | D18: Andrew Jindal | E18: -- | F18: In-house | G18: Asst. Controller | H18: Accounting, Business Tax | L18: -- | O18: --
A19: 16 | B19: Shefali | C19: CAS-IH_1065 | D19: Nikita Shah | E19: Nikita Shah | F19: In-house | G19: Team Lead | H19: Accounting | I19: 144.35 | J19: 144.35 | K19: 144.35 | L19: 100% | O19: -- | P19: 03/03/2026 | U19: 29.5 | W19: 2 | AI19: 16.59 | BB19: 2 | BL19: 33.84 | BM19: 2 | BV19: 0.5 | BW19: 6.92 | CA19: 49 | CC19: 2 | CD19: 144.35
A20: 17 | B20: Rashi | C20: CAS-IH_1077 | D20: Vinita Dagar | E20: Vinita Dagar | F20: In-house | G20: Asst. Manager | H20: HR | L20: -- | O20: --
A21: 18 | B21: Gaganjot | C21: CAS-IH_1159 | D21: Shefali | E21: Nikita Shah | F21: In-house | G21: Asst. Team Lead | H21: Accounting, Business Tax | L21: -- | O21: --
A22: 19 | B22: Robin | C22: CAS-IH_1005 | D22: Jyoti | E22: Jyoti | F22: In-house | G22: Sr. Associate | H22: Accounting | I22: 165.25 | J22: 162.25 | K22: 162.25 | L22: 98.18% | O22: -- | P22: 03/03/2026 | AI22: 1.5 | AN22: 130.25 | AZ22: 5 | BC22: 1 | BK22: 6 | BS22: 18.5 | CD22: 162.25
A23: 20 | B23: Nishu | C23: CAS-IH_1038 | D23: Robin | E23: Jyoti | F23: In-house | G23: Associate | H23: Accounting, Business Tax, VA | I23: 132.67 | J23: 132.67 | K23: 132.67 | L23: 100% | O23: -- | P23: 03/03/2026 | AN23: 132.67 | CD23: 132.67
A24: 21 | B24: Pinky | C24: CAS-RT_2045 | D24: Nikita Shah | E24: Nikita Shah | F24: Remote | G24: Manager | H24: Accounting | I24: 64.27 | J24: 64.27 | K24: 64.27 | L24: 100% | O24: -- | P24: 03/03/2026 | S24: 64.27 | CD24: 64.27
A25: 22 | B25: Preety | C25: CAS-IH_1056 | D25: Nikita Shah | E25: Nikita Shah | F25: In-house | G25: Team Lead | H25: Accounting, Business Tax | I25: 81 | J25: 81 | K25: 81 | L25: 100% | O25: -- | P25: 03/03/2026 | V25: 2.75 | AG25: 10 | AI25: 15.5 | AV25: 4.5 | AW25: 1 | BL25: 39.75 | BN25: 3 | CB25: 4.5 | CD25: 81
A26: 23 | B26: Urvashi | C26: CAS-RT_2063 | D26: Pinky | E26: Nikita Shah | F26: Remote | G26: Associate | H26: Accounting | I26: 104.09 | J26: 104.09 | K26: 104.09 | L26: 100% | O26: -- | P26: 03/03/2026 | S26: 104.09 | CD26: 104.09
A27: 24 | B27: Melita | C27: CAS-IH_1046 | D27: Smriti Shah | E27: Smriti Shah | F27: In-house | G27: Team Lead | H27: Individual Tax | I27: 178.09 | J27: 178.09 | K27: 178.09 | L27: 100% | O27: -- | P27: 03/03/2026 | AI27: 98.5 | AM27: 4.34 | AN27: 31.75 | AT27: 6 | AU27: 35.41 | AZ27: 1.75 | BC27: 0.17 | BK27: 0.17 | CD27: 178.09
A28: 25 | B28: Bhawna | C28: CAS-RR_2077 | D28: Jyoti | E28: Jyoti | F28: Retainer | G28: Manager | H28: Accounting | I28: 189.58 | J28: 189.58 | K28: 189.58 | L28: 100% | N28: 189.58 | O28: -- | P28: 03/02/2026 | BR28: 68.01 | BY28: 121.57 | CD28: 189.58
A29: 26 | B29: Anand | C29: CAS-RT_2078 | D29: Nikita Shah | E29: Nikita Shah | F29: Remote | G29: Associate | H29: Accounting | I29: 159.38 | J29: 159.38 | K29: 159.38 | L29: 100% | M29: 158.06667 | N29: 1.3133333 | O29: 0.83% | P29: 03/03/2026 | AX29: 88.78 | BX29: 70.6 | CD29: 159.38
A30: 27 | B30: Shivani | C30: CAS-RT_2102 | D30: Preety | E30: Nikita Shah | F30: Remote | G30: Associate | H30: Accounting | I30: 55.11 | J30: 55.11 | K30: 55.11 | L30: 100% | O30: -- | P30: 02/27/2026 | AG30: 49.1 | BN30: 6.01 | CD30: 55.11
A31: 28 | B31: Sreeja | C31: CAS-RT_2108 | D31: Pinky | E31: Nikita Shah | F31: Remote | G31: Manager | H31: Accounting | I31: 90.58 | J31: 90.58 | K31: 90.58 | L31: 100% | O31: -- | P31: 03/03/2026 | S31: 90.58 | CD31: 90.58
A32: 29 | B32: Divya.M | C32: CAS-RT_2113 | D32: Preety | E32: Nikita Shah | F32: Remote | G32: Manager | H32: Accounting | I32: 82.67 | J32: 82.67 | K32: 82.67 | L32: 100% | M32: 83.25 | N32: -0.58 | O32: 0.7% | P32: 02/25/2026 | V32: 23.25 | AG32: 44.42 | AZ32: 5 | BN32: 10 | CD32: 82.67
A33: 30 | B33: Kritika | C33: CAS-IH_1102 | D33: Sachi Mazumdar | E33: Sachi Mazumdar | F33: In-house | G33: Manager | H33: FP&A | I33: 163 | J33: 139 | K33: 139 | L33: 85.28% | O33: -- | P33: 03/03/2026 | X33: 139 | CD33: 139
A34: 31 | B34: Abhilash | C34: CAS-IH_1061 | D34: Smriti Shah | E34: Smriti Shah | F34: In-house | G34: Sr. Associate | H34: Individual Tax | I34: 99.34 | J34: 99.34 | K34: 99.34 | L34: 100% | M34: 186.15 | N34: -86.81 | O34: 46.63% | P34: 03/03/2026 | Q34: 2.5 | AG34: 54.84 | AI34: 37.5 | AM34: 1.5 | BL34: 3 | CD34: 99.34
A35: 32 | B35: Kavita | C35: CAS-IH_1108 | D35: Sachi Mazumdar | E35: Sachi Mazumdar | F35: In-house | G35: Manager | H35: FP&A | I35: 132 | J35: 132 | K35: 132 | L35: 100% | O35: -- | P35: 02/25/2026 | X35: 132 | CD35: 132
A36: 33 | B36: Sakshi | C36: CAS-IH_1078 | D36: Nikita Shah | E36: Nikita Shah | F36: In-house | G36: Associate | H36: Accounting | I36: 114.48 | J36: 114.48 | K36: 114.48 | L36: 100% | O36: -- | P36: 03/03/2026 | AI36: 2.08 | BQ36: 112.4 | CD36: 114.48
A37: 34 | B37: Suhani | C37: CAS-RR_2370 | D37: Ayushi | E37: Ayushi | F37: Retainer | G37: Team Lead | H37: Accounting | I37: 136.75 | J37: 136.75 | K37: 136.75 | L37: 100% | O37: -- | P37: 03/03/2026 | AA37: 25.5 | AI37: 32.5 | AK37: 3 | AP37: 6.75 | BD37: 6 | BF37: 5 | BK37: 8 | BP37: 10 | BT37: 10 | CA37: 30 | CD37: 136.75
A38: 35 | B38: Shradha | C38: CAS-IH_1082 | D38: Jyoti | E38: Jyoti | F38: In-house | G38: Sr. Associate | H38: Accounting | I38: 158.67 | J38: 154.17 | K38: 154.17 | L38: 97.16% | O38: -- | P38: 03/03/2026 | AI38: 3 | AN38: 144.17 | BS38: 7 | CD38: 154.17
A39: 36 | B39: Ridhi.G | C39: CAS-IH_1146 | D39: Shefali | E39: Nikita Shah | F39: In-house | G39: Asst. Team Lead | H39: Accounting, Business Tax | I39: 115.74 | J39: 115.74 | K39: 115.74 | L39: 100% | O39: -- | P39: 03/03/2026 | U39: 33.16 | AI39: 3.5 | BB39: 16.42 | BL39: 20.74 | CA39: 41.92 | CD39: 115.74
A40: 37 | B40: Bhairavi.M | C40: CAS-IH_1160 | D40: Suhani | E40: Ayushi | F40: In-house | G40: Associate | H40: Accounting | I40: 165 | J40: 149 | K40: 149 | L40: 90.3% | M40: 165.43333 | N40: -16.433333 | O40: 9.93% | P40: 03/03/2026 | AA40: 135.75 | BF40: 13.25 | CD40: 149
A41: 38 | B41: Ujjwal.J | C41: CAS-IH_1150 | D41: Preety | E41: Nikita Shah | F41: In-house | G41: Associate | H41: Accounting, Business Tax | I41: 127.16 | J41: 125.91 | K41: 125.91 | L41: 99.02% | O41: -- | P41: 03/03/2026 | AI41: 25.67 | AV41: 2.75 | AW41: 3.5 | BL41: 80.33 | CB41: 13.66 | CD41: 125.91
A42: 39 | B42: Sukhmeen.K | C42: CAS-RR_2253 | D42: Ayushi | E42: Ayushi | F42: Retainer | G42: Manager | H42: Accounting | I42: 168.92 | J42: 168.92 | K42: 168.92 | L42: 100% | O42: -- | P42: 03/03/2026 | AA42: 41 | AH42: 4.5 | AI42: 43.42 | AJ42: 28 | AS42: 1 | BE42: 31 | BH42: 17 | BU42: 2 | BY42: 1 | CD42: 168.92
A43: 40 | B43: Tanisha.J | C43: CAS-IH_1111 | D43: Rashi | E43: Vinita Dagar | F43: In-house | G43: Associate | H43: HR | I43: 109 | J43: 109 | K43: 109 | L43: 100% | O43: -- | P43: 03/03/2026 | AI43: 109 | CD43: 109
A44: 41 | B44: Disha.M | C44: CAS-IH_1113 | D44: Rashi | E44: Vinita Dagar | F44: In-house | G44: Associate | H44: HR | I44: 51 | J44: 51 | K44: 51 | L44: 100% | O44: -- | P44: 03/03/2026 | AI44: 51 | CD44: 51
A45: 42 | B45: Smriti.S | C45: CAS-IH_1114 | D45: Ammie | E45: -- | F45: In-house | G45: Controller | H45: Individual Tax | I45: 42.75 | J45: 42.75 | K45: 42.75 | L45: 100% | O45: -- | P45: 03/03/2026 | Q45: 1.83 | AB45: 6 | AM45: 16.25 | AN45: 2.09 | AT45: 6.67 | BL45: 9.25 | BT45: 0.66 | CD45: 42.75
A46: 43 | B46: Muhammad.S | C46: CAS-RT_2283 | D46: Suhani | E46: Ayushi | F46: Remote | G46: Associate | H46: Accounting | I46: 160.25 | J46: 132.5 | K46: 132.5 | L46: 82.68% | O46: -- | P46: 03/03/2026 | AA46: 25.5 | BS46: 35 | BT46: 37.75 | CA46: 34.25 | CD46: 132.5
A47: 44 | B47: Farheen.K | C47: CAS-RT_2296 | D47: Sukhmeen.K | E47: Sukhmeen.K | F47: Remote | G47: Asst. Team Lead | H47: Accounting | I47: 166.37 | J47: 142.02 | K47: 142.02 | L47: 85.36% | M47: 164.65 | N47: -22.63 | O47: 13.74% | P47: 03/03/2026 | AA47: 7 | AH47: 18.57 | AI47: 49.57 | BE47: 22.48 | BH47: 0.75 | BU47: 43.65 | CD47: 142.02
A48: 45 | B48: Vaibhav.A | C48: CAS-IH_1120 | D48: Sachi Mazumdar | E48: Sachi Mazumdar | F48: In-house | G48: Manager | H48: FP&A | I48: 200 | J48: 180 | K48: 180 | L48: 90% | O48: -- | P48: 03/03/2026 | X48: 180 | CD48: 180
A49: 46 | B49: Shikha.A | C49: CAS-IH_1123 | D49: Smriti Shah | E49: Smriti Shah | F49: In-house | G49: Asst. Team Lead | H49: Individual Tax | I49: 160.5 | J49: 160.5 | K49: 160.5 | L49: 100% | O49: -- | P49: 03/03/2026 | Q49: 20.25 | AB49: 1 | AI49: 105.25 | AM49: 1.5 | AN49: 5 | AT49: 1.75 | AZ49: 9.75 | BK49: 0.5 | BL49: 15.5 | CD49: 160.5
A50: 47 | B50: Rupesh.A | C50: CAS-IH_1124 | D50: Sachi Mazumdar | E50: Sachi Mazumdar | F50: In-house | G50: Sr. Manager | H50: FP&A | L50: -- | O50: --
A51: 48 | B51: Deepika.B | C51: CAS-IH_1126 | D51: Smriti Shah | E51: Smriti Shah | F51: In-house | G51: Associate | H51: Individual Tax | I51: 153.6 | J51: 153.6 | K51: 153.6 | L51: 100% | M51: 212.93333 | N51: -59.333333 | O51: 27.86% | P51: 03/03/2026 | Q51: 2.33 | AB51: 0.75 | AI51: 77.09 | AM51: 25.84 | AT51: 12.5 | AZ51: 14 | BE51: 3.75 | BK51: 1.42 | BL51: 15.92 | CD51: 153.6
A52: 49 | B52: Vandana.M | C52: CAS-IH_1127 | D52: Smriti Shah | E52: Smriti Shah | F52: In-house | G52: Associate | H52: Individual Tax | I52: 119.16 | J52: 119.16 | K52: 119.16 | L52: 100% | O52: -- | P52: 03/03/2026 | AG52: 8.83 | AI52: 53.91 | AN52: 52.09 | BL52: 4.33 | CD52: 119.16
A53: 50 | B53: Shikha.AG | C53: CAS-RT_2319 | D53: Suhani | E53: Ayushi | F53: Remote | G53: Asst. Team Lead | H53: Accounting | I53: 55.91 | J53: 55.91 | K53: 55.91 | L53: 100% | O53: -- | P53: 02/27/2026 | AA53: 8.75 | AI53: 2.08 | BT53: 45.08 | CD53: 55.91
A54: 51 | B54: Falguni.M | C54: CAS-RT_2324 | D54: Jyoti | E54: Jyoti | F54: Remote | G54: Manager | H54: Business Tax | I54: 150.5 | J54: 150.5 | K54: 150.5 | L54: 100% | M54: 185.03333 | N54: -34.533333 | O54: 18.66% | P54: 03/03/2026 | Q54: 25 | AI54: 27.25 | AM54: 11.25 | AT54: 35.75 | AZ54: 4.25 | BE54: 26 | BL54: 13.5 | BT54: 7.5 | CD54: 150.5
A55: 52 | B55: Saumil.M | C55: CAS-RT_2332 | D55: Suhani | E55: Ayushi | F55: Remote | G55: Associate | H55: Accounting | I55: 102.39 | J55: 92.31 | K55: 92.31 | L55: 90.16% | O55: -- | P55: 03/03/2026 | AX55: 3.32 | CA55: 88.99 | CD55: 92.31
A56: 53 | B56: Seemu.A | C56: CAS-RT_2335 | D56: Preety | E56: Nikita Shah | F56: Remote | G56: Associate | H56: Accounting | I56: 103.38 | J56: 103.38 | K56: 103.38 | L56: 100% | O56: -- | P56: 03/03/2026 | V56: 2.34 | AG56: 20.08 | AI56: 1.67 | AZ56: 33.07 | BN56: 31.99 | BW56: 14.23 | CD56: 103.38
A57: 54 | B57: Kanica.P | C57: CAS-RT_2340 | D57: Shefali | E57: Nikita Shah | F57: Remote | G57: Sr. Associate | H57: Accounting | I57: 160 | J57: 160 | K57: 160 | L57: 100% | O57: -- | P57: 03/03/2026 | AI57: 3.67 | BL57: 29.75 | CA57: 126.58 | CD57: 160
A58: 55 | B58: Ammie | C58: CAS-IH_1137 | D58: Andrew Jindal | E58: -- | F58: In-house | G58: Sr. Controller | H58: Individual Tax, Business Tax | I58: 177.82 | J58: 177.82 | K58: 177.82 | L58: 100% | M58: 77.116667 | N58: 100.70333 | O58: 130.59% | P58: 03/03/2026 | AI58: 115 | AM58: 3.25 | AT58: 15 | AU58: 1.16 | BE58: 40.16 | BL58: 0.5 | BT58: 2.75 | CD58: 177.82
A59: 56 | B59: Pranjali.M | C59: CAS-RT_2349 | D59: Sukhmeen.K | E59: Ayushi | F59: Remote | G59: Associate | H59: Accounting | I59: 80.09 | J59: 78.17 | K59: 78.17 | L59: 97.6% | O59: -- | P59: 03/03/2026 | AI59: 2.42 | BE59: 72.17 | BH59: 3.58 | CD59: 78.17
A60: 57 | B60: Shikha.S | C60: CAS-RT_2351 | D60: Shefali | E60: Nikita Shah | F60: Remote | G60: Associate | H60: Accounting | I60: 177.89 | J60: 177.89 | K60: 177.89 | L60: 100% | O60: -- | P60: 03/02/2026 | U60: 10.74 | AI60: 3.41 | BB60: 87.67 | BL60: 65.4 | BM60: 10.67 | CD60: 177.89
A61: 58 | B61: Rutu.G | C61: CAS-RT_2359 | D61: Preety | E61: Nikita Shah | F61: Remote | G61: Associate | H61: Accounting | I61: 117.87 | J61: 112.78 | K61: 112.78 | L61: 95.68% | O61: -- | P61: 03/03/2026 | AI61: 3.92 | AV61: 2.5 | AW61: 0.67 | BL61: 37.34 | CB61: 68.35 | CD61: 112.78
A62: 59 | B62: Sachi | C62: CAS-IH_1003 | D62: Sam | E62: -- | F62: In-house | G62: Coo | H62: FP&A | L62: -- | O62: --
A63: 60 | B63: Aishwarya.V | C63: CAS-RR_2374 | D63: Anshul Ohri | E63: Jasleen.D | F63: Remote | G63: Asst. Team Lead | H63: Accounting | I63: 132.13 | J63: 131.78 | K63: 131.78 | L63: 99.74% | M63: 115.18333 | N63: 16.596667 | O63: 14.41% | P63: 02/26/2026 | T63: 128.66 | AI63: 3.12 | CD63: 131.78
A64: 61 | B64: Tejas.P | C64: CAS-RT_2367 | D64: Anshul Ohri | E64: Jasleen.D | F64: Remote | G64: Sr. Associate | H64: Accounting | I64: 185.75 | J64: 185.75 | K64: 185.75 | L64: 100% | O64: -- | P64: 03/03/2026 | AC64: 137 | AI64: 7.75 | AY64: 41 | CD64: 185.75
A65: 62 | B65: Priyam.B | C65: CAS-RT_2361 | D65: Shefali | E65: Nikita Shah | F65: Remote | G65: Asst. Team Lead | H65: Accounting | L65: -- | O65: --
A66: 63 | B66: Jaya.L | C66: CAS-IH_1151 | D66: Sarah | E66: Sarah | F66: In-house | G66: Asst. Team Lead | H66: Accounting, L&D | I66: 167.77 | J66: 150.27 | K66: 150.27 | L66: 89.57% | O66: -- | P66: 03/03/2026 | AI66: 150.27 | CD66: 150.27
A67: 64 | B67: Ayushi.B | C67: CAS-RT_2369 | D67: Jyoti | E67: Jyoti | F67: Remote | G67: Associate | H67: Accounting | I67: 145.74 | J67: 136.24 | K67: 136.24 | L67: 93.48% | M67: 144.2 | N67: -7.96 | O67: 5.52% | P67: 03/03/2026 | AN67: 124.74 | BS67: 11.5 | CD67: 136.24
A68: 65 | B68: Akanksha.V | C68: CAS-IH_1144 | D68: Rashi | E68: Vinita Dagar | F68: In-house | G68: Associate | H68: HR | I68: 96 | J68: 96 | K68: 96 | L68: 100% | M68: 57 | N68: 39 | O68: 68.42% | P68: 02/23/2026 | AI68: 96 | CD68: 96
A69: 66 | B69: Teja.R | C69: CAS-RT_2372 | D69: Shefali | E69: Nikita Shah | F69: Remote | G69: Associate | H69: Accounting | I69: 122.85 | J69: 122.85 | K69: 122.85 | L69: 100% | O69: -- | P69: 03/03/2026 | AI69: 12.01 | CC69: 110.84 | CD69: 122.85
A70: 67 | B70: Upasana | C70: CAS-RT_2373 | D70: Jyoti | E70: Jyoti | F70: Remote | G70: Sr. Associate | H70: Accounting | I70: 179.39 | J70: 179.39 | K70: 179.39 | L70: 100% | O70: -- | P70: 03/03/2026 | AI70: 33.82 | AT70: 119.99 | AU70: 25.58 | CD70: 179.39
A71: 68 | B71: Scarlett.C | C71: CAS-RT_2374 | D71: Namya.S | E71: Jasleen.D | F71: Remote | G71: Sr. Associate | H71: Accounting | I71: 178.012 | J71: 178 | K71: 178 | L71: 99.99% | O71: -- | P71: 03/03/2026 | AI71: 2.66 | AL71: 175.34 | CD71: 178
A72: 69 | B72: Alan | C72: CAS-IH_1148 | D72: Andrew Jindal | E72: -- | F72: In-house | G72: Project Manager (S/W) | H72: IT | L72: -- | M72: 0.38333333 | N72: -0.38333333 | O72: 100%
A73: 70 | B73: Farheen.F | C73: CAS-RT_2375 | D73: Anshul Ohri | E73: Jasleen.D | F73: Remote | G73: Associate | H73: Accounting | I73: 158 | J73: 158 | K73: 158 | L73: 100% | M73: 155.8 | N73: 2.2 | O73: 1.41% | P73: 03/03/2026 | AD73: 145.75 | AI73: 12.25 | CD73: 158
A74: 71 | B74: Megha.J | C74: CAS-RT_2376 | D74: Anshul Ohri | E74: Jasleen.D | F74: Remote | G74: Associate | H74: Accounting | I74: 97.16 | J74: 97.16 | K74: 97.16 | L74: 100% | O74: -- | P74: 02/16/2026 | T74: 94.35 | AI74: 2.81 | CD74: 97.16
A75: 72 | B75: Prachi.G | C75: CAS-IH_1161 | D75: -- | E75: Sachi Mazumdar | F75: In-house | G75: Sr. Manager | H75: FP&A | I75: 146 | J75: 146 | K75: 146 | L75: 100% | O75: -- | P75: 02/26/2026 | BY75: 146 | CD75: 146
A76: 73 | B76: Itee.S | C76: CAS-RT_2382 | D76: Sukhmeen.K | E76: Ayushi | F76: Remote | G76: Associate | H76: Accounting | I76: 174.65 | J76: 155.29 | K76: 155.29 | L76: 88.91% | O76: -- | P76: 03/03/2026 | AA76: 9.42 | AI76: 1.32 | AS76: 40.84 | BE76: 103.29 | BH76: 0.42 | CD76: 155.29
A77: 74 | B77: Anushka.G | C77: CAS-RT_2383 | D77: Nikita Shah | E77: Nikita Shah | F77: Remote | G77: Associate | H77: L&D | I77: 162 | J77: 162 | K77: 162 | L77: 100% | M77: 148.86667 | N77: 13.133333 | O77: 8.82% | P77: 03/03/2026 | AI77: 162 | CD77: 162
A78: 75 | B78: Priyanka.M | C78: CAS-RT_2384 | D78: Sukhmeen.K | E78: Ayushi | F78: Remote | G78: Asst. Team Lead | H78: Accounting | I78: 163.3 | J78: 137.18 | K78: 137.18 | L78: 84% | O78: -- | P78: 03/03/2026 | AA78: 11.5 | AI78: 3 | AS78: 26.32 | BE78: 96.36 | CD78: 137.18
A79: 76 | B79: Raj.B | C79: CAS-RT_2385 | D79: Shefali | E79: Nikita Shah | F79: Remote | G79: Sr. Associate | H79: Accounting | I79: 167.9 | J79: 167.9 | K79: 167.9 | L79: 100% | O79: -- | P79: 03/03/2026 | U79: 152.57 | AI79: 5.25 | BJ79: 10.08 | CD79: 167.9
A80: 77 | B80: Chhavi.S | C80: CAS-RT_2386 | D80: Shefali | E80: Nikita Shah | F80: Remote | G80: Sr. Associate | H80: Accounting, VA | I80: 165.71 | J80: 165.71 | K80: 165.71 | L80: 100% | M80: 176.93333 | N80: -11.223333 | O80: 6.34% | P80: 03/03/2026 | U80: 17.83 | AI80: 3.33 | AZ80: 25.66 | BV80: 3.75 | BW80: 115.14 | CD80: 165.71
A81: 78 | B81: Surbhi.A | C81: CAS-RT_2390 | D81: Anshul Ohri | E81: Jasleen.D | F81: Remote | G81: Asst. Team Lead | H81: Accounting | I81: 146.58 | J81: 146.58 | K81: 146.58 | L81: 100% | O81: -- | P81: 03/03/2026 | Y81: 30.75 | AE81: 15.5 | AI81: 9.75 | AQ81: 28.08 | BG81: 43.75 | BO81: 18.75 | CD81: 146.58
A82: 79 | B82: Jatin.S | C82: CAS-IH_1165 | D82: Sachi Mazumdar | E82: Sachi Mazumdar | F82: In-house | G82: Sr. Manager | H82: FP&A | I82: 186 | J82: 139 | K82: 139 | L82: 74.73% | O82: -- | P82: 03/03/2026 | AI82: 139 | CD82: 139
A83: 80 | B83: Angela | C83: CASUS-IH_002 | D83: Sam | E83: -- | F83: In-house | G83: Controller | H83: Marketing | I83: 16 | J83: 16 | K83: 16 | L83: 100% | O83: -- | P83: 03/02/2026 | AI83: 16 | CD83: 16
A84: 81 | B84: Harsh.G | C84: CAS-RT_2392 | D84: Suhani | E84: Ayushi | F84: Remote | G84: Sr. Associate | H84: Accounting | L84: -- | O84: --
A85: 82 | B85: Namya.S | C85: CAS-IH_1166 | D85: Jasleen.D | E85: Jasleen.D | F85: In-house | G85: Asst. Team Lead | H85: Accounting | I85: 146.28 | J85: 146.28 | K85: 146.28 | L85: 100% | O85: -- | P85: 03/03/2026 | R85: 30.83 | AB85: 33.75 | AE85: 10 | AI85: 10.08 | AL85: 61.62 | CD85: 146.28
A86: 83 | B86: Kashish.B | C86: CAS-RT_2393 | D86: Preety | E86: Nikita Shah | F86: Remote | G86: Sr. Associate | H86: Accounting | I86: 165.25 | J86: 156.25 | K86: 156.25 | L86: 94.55% | O86: -- | P86: 03/03/2026 | AI86: 6.33 | AO86: 23.17 | AV86: 107 | AW86: 2.83 | BL86: 8.5 | CB86: 8.42 | CD86: 156.25
A87: 84 | B87: Amishi.S | C87: CAS-RT_2396 | D87: Aishwarya.V | E87: Jasleen.D | F87: Remote | G87: Sr. Associate | H87: Accounting | I87: 170.87 | J87: 170.87 | K87: 170.87 | L87: 100% | M87: 173.23333 | N87: -2.3633333 | O87: 1.36% | P87: 03/03/2026 | T87: 158.33 | AI87: 12.54 | CD87: 170.87
A88: 85 | B88: Harsh.V | C88: CAS-RR_2372 | D88: Robin | E88: Jyoti | F88: Remote | G88: Associate | H88: Accounting | I88: 55.43 | J88: 46.67 | K88: 46.67 | L88: 84.2% | M88: 61.983333 | N88: -15.313333 | O88: 24.71% | P88: 03/03/2026 | AI88: 1.75 | AN88: 28.25 | BC88: 1.67 | BS88: 15 | CD88: 46.67
A89: 86 | B89: Ash | C89: 209 | D89: -- | E89: -- | F89: Remote | G89: Controller | H89: IT | L89: -- | O89: --
A90: 87 | B90: Anshika.B | C90: CASCFO-IH-004 | D90: Monika.M | E90: Vinita Dagar | F90: In-house | G90: Associate | H90: HR | I90: 159 | J90: 151 | K90: 151 | L90: 94.97% | M90: 111.85 | N90: 39.15 | O90: 35% | P90: 03/03/2026 | AI90: 151 | CD90: 151
A91: 88 | B91: Deepak | C91: CASCFO-IH-005 | D91: Akhilesh Sirvi | E91: Vinita Dagar | F91: In-house | G91: Sr. Associate | H91: HR | L91: -- | O91: --
A92: 89 | B92: Simran. | C92: CAS-RT_2401 | D92: Raj.B | E92: Nikita Shah | F92: Remote | G92: Sr. Associate | H92: Accounting | I92: 178.85 | J92: 178.85 | K92: 178.85 | L92: 100% | O92: -- | P92: 03/03/2026 | U92: 152.68 | W92: 0.5 | AI92: 3.33 | BJ92: 9.17 | CA92: 13.17 | CD92: 178.85
A93: 90 | B93: Marta | C93: CASUS-IH_003 | D93: Angela | E93: Angela | F93: Remote | G93: Associate | H93: Marketing | L93: -- | O93: --
A94: 91 | B94: Sakshi.M | C94: CAS-IH_1170 | D94: Prachi Guglani | E94: Prachi Guglani | F94: Remote | G94: Manager | H94: FP&A | I94: 171 | J94: 153 | K94: 153 | L94: 89.47% | O94: -- | P94: 03/03/2026 | BY94: 153 | CD94: 153
A95: 92 | B95: Tracey.G | C95: CASCFO**** | D95: Sam | E95: -- | F95: Remote | G95: Coo | H95: Accounting, Individual Tax, Business Tax, VA | L95: -- | O95: --
A96: 93 | B96: Khushboo.S | C96: CAS-IH_1171 | D96: Jasleen.D | E96: Jasleen.D | F96: In-house | G96: Manager | H96: Accounting | I96: 181.12 | J96: 181.12 | K96: 181.12 | L96: 100% | O96: -- | P96: 03/03/2026 | T96: 166.68 | AI96: 14.44 | CD96: 181.12
A97: 94 | B97: Prerna.G | C97: CAS-RT_2402 | D97: Suhani | E97: Ayushi | F97: Remote | G97: Manager | H97: Accounting | I97: 157.46 | J97: 117.89 | K97: 117.89 | L97: 74.87% | O97: -- | P97: 03/03/2026 | AA97: 50.34 | AI97: 15.93 | AK97: 1.25 | AP97: 17.42 | BK97: 8.25 | BP97: 24.7 | CD97: 117.89
A98: 95 | B98: Monika.M | C98: CASCFO-IH-007 | D98: Andrew Jindal | E98: Vinita Dagar | F98: In-house | G98: Manager | H98: HR | I98: 158 | J98: 134 | K98: 134 | L98: 84.81% | O98: -- | P98: 03/03/2026 | AI98: 134 | CD98: 134
A99: 96 | B99: Richa.A | C99: CAS-RT_2403 | D99: Sukhmeen.K | E99: Ayushi | F99: Remote | G99: Sr. Associate | H99: Accounting | I99: 162.27 | J99: 130.19 | K99: 130.19 | L99: 80.23% | O99: -- | P99: 03/03/2026 | AA99: 19.01 | AI99: 0.5 | AK99: 10.07 | AP99: 40.06 | BD99: 11.24 | BK99: 0.75 | BP99: 48.56 | CD99: 130.19
A100: 97 | B100: brandon | C100: CASUS-IH_004 | D100: Angela | E100: Angela | F100: Remote | G100: Marketing | H100: Marketing | L100: -- | O100: --
...

Sheet ② Salary Input
A1: PASTE YOUR SALARY REGISTER HERE
A2: Instructions: Copy-paste monthly salary register. Keep headers in Row 3. Employee Number must match Timelog Employee ID.
A3: Employee Number | B3: Employee Name | C3: Employee Type | D3: Basic | E3: Basic Pay | F3: House Rent Allowance | G3: Conveyance Allowance | H3: Variable Incentive | I3: Fixed Allowance | J3: Hourly Professional Fees | K3: Variable Pay | L3: Bonus | M3: Reimbursement | N3: Gross Pay | O3: Income Tax | P3: Tax on Income | Q3: Surcharge | R3: Cess | S3: Total Income Tax | T3: Withheld Salary | U3: Business Expense Reimbursements | V3: Net Pay
A4: CAS-IH_1005 | B4: Rajesh Gujrati | C4: employee | D4: 35000 | E4: 0 | F4: 17500 | G4: 5000 | H4: 12500 | I4: 0 | J4: 0 | K4: 0 | L4: 0 | M4: 0 | N4: 70000 | O4: 0 | P4: 0 | Q4: 0 | R4: 0 | S4: 0 | T4: 0 | U4: 0 | V4: 70000
A5: CAS-IH_1038 | B5: Nishu Sharma | C5: employee | D5: 21500 | E5: 0 | F5: 10750 | G5: 4750 | H5: 6000 | I5: 0 | J5: 0 | K5: 0 | L5: 0 | M5: 0 | N5: 43000 | O5: 0 | P5: 0 | Q5: 0 | R5: 0 | S5: 0 | T5: 0 | U5: 0 | V5: 43000
A6: CAS-IH_1046 | B6: Melita Dias | C6: employee | D6: 67500 | E6: 0 | F6: 33750 | G6: 16875 | H6: 0 | I6: 16875 | J6: 0 | K6: 0 | L6: 0 | M6: 0 | N6: 135000 | O6: 0 | P6: 9615 | Q6: 0 | R6: 385 | S6: 10000 | T6: 0 | U6: 0 | V6: 125000
A7: CAS-IH_1049 | B7: Asmita Mandan | C7: employee | D7: 31250 | E7: 0 | F7: 15625 | G7: 7813 | H7: 3000 | I7: 4812 | J7: 0 | K7: 0 | L7: 0 | M7: 0 | N7: 62500 | O7: 0 | P7: 0 | Q7: 0 | R7: 0 | S7: 0 | T7: 0 | U7: 0 | V7: 62500
A8: CAS-IH_1056 | B8: Preety Soni | C8: employee | D8: 50000 | E8: 0 | F8: 25000 | G8: 12500 | H8: 0 | I8: 12500 | J8: 0 | K8: 0 | L8: 0 | M8: 0 | N8: 100000 | O8: 0 | P8: 0 | Q8: 0 | R8: 0 | S8: 0 | T8: 0 | U8: 0 | V8: 100000
A9: CAS-IH_1061 | B9: Jillela Abhilash | C9: employee | D9: 50000 | E9: 0 | F9: 25000 | G9: 12500 | H9: 0 | I9: 12500 | J9: 0 | K9: 0 | L9: 0 | M9: 0 | N9: 100000 | O9: 0 | P9: 0 | Q9: 0 | R9: 0 | S9: 0 | T9: 0 | U9: 0 | V9: 100000
A10: CAS-IH_1065 | B10: Shefali Mantri | C10: employee | D10: 67500 | E10: 0 | F10: 33750 | G10: 13750 | H10: 20000 | I10: 0 | J10: 0 | K10: 0 | L10: 0 | M10: 0 | N10: 135000 | O10: 0 | P10: 9615 | Q10: 0 | R10: 385 | S10: 10000 | T10: 0 | U10: 0 | V10: 125000
A11: CAS-IH_1070 | B11: Ankit Gupta | C11: employee | D11: 30000 | E11: 0 | F11: 15000 | G11: 7500 | H11: 0 | I11: 7500 | J11: 0 | K11: 0 | L11: 0 | M11: 0 | N11: 60000 | O11: 0 | P11: 0 | Q11: 0 | R11: 0 | S11: 0 | T11: 0 | U11: 0 | V11: 60000
A12: CAS-IH_1077 | B12: Rashi Varshney | C12: employee | D12: 35000 | E12: 0 | F12: 17500 | G12: 8750 | H12: 0 | I12: 8750 | J12: 0 | K12: 0 | L12: 0 | M12: 0 | N12: 70000 | O12: 0 | P12: 0 | Q12: 0 | R12: 0 | S12: 0 | T12: 0 | U12: 0 | V12: 70000
A13: CAS-IH_1078 | B13: Sakshi Bansal | C13: employee | D13: 27500 | E13: 0 | F13: 13750 | G13: 6875 | H13: 0 | I13: 6875 | J13: 0 | K13: 0 | L13: 0 | M13: 0 | N13: 55000 | O13: 0 | P13: 0 | Q13: 0 | R13: 0 | S13: 0 | T13: 0 | U13: 0 | V13: 55000
A14: CAS-IH_1082 | B14: Shradha Jain | C14: employee | D14: 25500 | E14: 0 | F14: 12750 | G14: 6375 | H14: 0 | I14: 6375 | J14: 0 | K14: 0 | L14: 0 | M14: 0 | N14: 51000 | O14: 0 | P14: 0 | Q14: 0 | R14: 0 | S14: 0 | T14: 0 | U14: 0 | V14: 51000
A15: CAS-IH_1092 | B15: Astha Dhanotiya | C15: employee | D15: 22500 | E15: 0 | F15: 11250 | G15: 5625 | H15: 5000 | I15: 625 | J15: 0 | K15: 0 | L15: 0 | M15: 0 | N15: 45000 | O15: 0 | P15: 0 | Q15: 0 | R15: 0 | S15: 0 | T15: 0 | U15: 0 | V15: 45000
... A121: CAS-RT_2319 | B121: Shikha Agrawal | C121: contractor | D121: 0 | E121: 500 | F121: 0 | G121: 0 | H121: 0 | I121: 0 | J121: 38700 | K121: 0 | L121: 0 | M121: 0 | N121: 39200 | O121: 3920 | P121: 0 | Q121: 0 | R121: 0 | S121: 0 | T121: 0 | U121: 0 | V121: 35280

Sheet ③ Billing Input
A1: ENTER CLIENT BILLING HERE
A2: Instructions: Enter billing in USD. INR auto-calculates using conversion rate from Settings. Max 100 clients. | I2: Project code from Worksheet
A3: S.No | B3: Client Name | C3: Controller | D3: Service(s) | E3: Billing USD (Monthly) | F3: Billing INR (Auto) | G3: Conversion Rate → | H3: =Settings!B8 -> 85 | I3: Project Code | J3: Contract Hrs | K3: # End Clients | L3: Firm Status
A4: 1 | B4: FULL COMPLIANCE, LLC | C4: Ammie, Jyoti | D4: Acctg, B.Tax, I.Tax, VA | E4: 2600 | F4: =IF(E4="",0,E4*Settings!B8) -> 221000 | I4: CAS 102 | J4: 640 | K4: 89 | L4: In Progress
A5: 2 | B5: MEJIA & ASSOCIATES, INC. | C5: Jyoti | D5: Accounting | E5: 1800 | F5: =IF(E5="",0,E5*Settings!B8) -> 153000 | I5: CAS 103 | J5: 161 | L5: Active
A6: 3 | B6: SOUTH FLORIDA SECURITY GROUP | C6: Jyoti | D6: Accounting | E6: 2320 | F6: =IF(E6="",0,E6*Settings!B8) -> 197200 | I6: CAS 115 | J6: 320 | L6: Active
A7: 4 | B7: SOUTH FLORIDA SECURITY GROUP- Billing | C7: Jyoti | D7: Accounting | E7: 1500 | F7: =IF(E7="",0,E7*Settings!B8) -> 127500 | I7: CAS 115 | J7: 320 | L7: Active
A8: 5 | B8: BEAM ACCOUNTING INC | C8: Nikita | D8: Accounting | E8: 650 | F8: =IF(E8="",0,E8*Settings!B8) -> 55250 | I8: CAS 118 | J8: 40 | K8: 13 | L8: In Progress
A9: 6 | B9: BRIGHTSKIES BUSINESS SERVICES, LLC | C9: Jasleen.D | D9: Accounting | E9: 2600 | F9: =IF(E9="",0,E9*Settings!B8) -> 221000 | I9: CAS 123 | J9: 400 | K9: 41 | L9: In Progress
A10: 7 | B10: AB CAPSTONE | C10: Nikita | D10: Accounting | E10: 1800 | F10: =IF(E10="",0,E10*Settings!B8) -> 153000 | I10: CAS 134 | J10: 240 | K10: 27 | L10: Active
A11: 8 | B11: jmWILLIAMS, CPA LLP | C11: Ammie, Jyoti | D11: B.Tax, I.Tax | E11: 1200 | F11: =IF(E11="",0,E11*Settings!B8) -> 102000 | I11: CAS 139 | J11: 160 | K11: 41 | L11: In Progress
A12: 9 | B12: MARTIN EINSTEIN | C12: Ammie, Jyoti, Nikita | D12: Acctg, B.Tax, I.Tax, VA | E12: 1440 | F12: =IF(E12="",0,E12*Settings!B8) -> 122400 | I12: CAS 144 | J12: 400 | K12: 38 | L12: In Progress
A13: 10 | B13: DOR BUSINESS GROUP LLC | C13: Ayushi | D13: Accounting | E13: 350 | F13: =IF(E13="",0,E13*Settings!B8) -> 29750 | I13: CAS 149 | J13: 40 | K13: 7 | L13: In Progress
A14: 11 | B14: CHRIS WHALEN CPA, LLC | C14: Ammie, Nikita | D14: Acctg, I.Tax | E14: 1880 | F14: =IF(E14="",0,E14*Settings!B8) -> 159800 | I14: CAS 153 | J14: 320 | K14: 64 | L14: Active
A15: 12 | B15: TREE OF LIFE FUNDING | C15: Nikita | D15: Accounting | E15: 1200 | F15: =IF(E15="",0,E15*Settings!B8) -> 102000 | I15: CAS 161 | J15: 160 | L15: In Progress
A16: 13 | B16: ROSEN KUSLANSKY CPA PC | C16: Nikita | D16: Accounting | E16: 1000 | F16: =IF(E16="",0,E16*Settings!B8) -> 85000 | I16: CAS 162 | J16: 160 | K16: 31 | L16: Active
A17: 14 | B17: INVENT WEALTH, CPA | C17: Ammie, Jasleen.D, Jyoti | D17: Acctg, B.Tax, I.Tax | E17: 2640 | F17: =IF(E17="",0,E17*Settings!B8) -> 224400 | I17: CAS 114 | J17: 480 | K17: 72 | L17: In Progress
A18: 15 | B18: ACT NOW FINANCIAL SERVICES | C18: Nikita | D18: Accounting | E18: 800 | F18: =IF(E18="",0,E18*Settings!B8) -> 68000 | I18: CAS 169 | J18: 80 | K18: 16 | L18: In Progress
A19: 16 | B19: BRADLEY FINANCIAL SERVICES LLC | C19: Jasleen.D | D19: Accounting | E19: 700 | F19: =IF(E19="",0,E19*Settings!B8) -> 59500 | I19: CAS 170 | J19: 140 | K19: 11 | L19: Active
A20: 17 | B20: JOHNSON & ROBINSON LLC | C20: Nikita | D20: Accounting | E20: 800 | F20: =IF(E20="",0,E20*Settings!B8) -> 68000 | I20: CAS 172 | J20: 80 | K20: 44 | L20: Active
A21: 18 | B21: PW ADVISORS LLC | C21: Ammie, Jyoti, Nikita | D21: Acctg, B.Tax, I.Tax | E21: 3600 | F21: =IF(E21="",0,E21*Settings!B8) -> 306000 | I21: CAS 175 | J21: 480 | K21: 50 | L21: Active
A22: 19 | B22: LIFETIME FUNDING, LLC | C22: Ayushi | D22: Accounting | E22: 1900 | F22: =IF(E22="",0,E22*Settings!B8) -> 161500 | I22: CAS 178 | J22: 400 | K22: 1 | L22: In Progress
A23: 20 | B23: NEW AGE IRON WORKS, INC. | C23: Ayushi | D23: Accounting | E23: 1000 | F23: =IF(E23="",0,E23*Settings!B8) -> 85000 | I23: CAS 193 | J23: 160 | K23: 1 | L23: In Progress
A24: 21 | B24: MCFADDEN ACCOUNTING | C24: Nikita | D24: Accounting | E24: 1000 | F24: =IF(E24="",0,E24*Settings!B8) -> 85000 | I24: CAS 199 | J24: 160 | K24: 14 | L24: Active
A25: 22 | B25: IAM ACCOUNTING | C25: Jasleen.D | D25: Accounting | E25: 3400 | F25: =IF(E25="",0,E25*Settings!B8) -> 289000 | I25: CAS 202 | J25: 320 | K25: 29 | L25: In Progress
A26: 23 | B26: H J EDWARDS | C26: Nikita | D26: Accounting | E26: 600 | F26: =IF(E26="",0,E26*Settings!B8) -> 51000 | I26: CAS 204 | J26: 80 | K26: 12 | L26: Active
A27: 24 | B27: RTWXXACT | C27: Ayushi | D27: Accounting | E27: 1000 | F27: =IF(E27="",0,E27*Settings!B8) -> 85000 | I27: CAS 208 | J27: 160 | K27: 12 | L27: In Progress
A28: 25 | B28: BORISMTAX INC | C28: Ayushi | D28: Accounting | E28: 3600 | F28: =IF(E28="",0,E28*Settings!B8) -> 306000 | I28: CAS 214 | J28: 480 | K28: 40 | L28: In Progress
A29: 26 | B29: LASTMILE DELIVERY | C29: Nikita | D29: Accounting | E29: 500 | F29: =IF(E29="",0,E29*Settings!B8) -> 42500 | I29: CAS 216 | J29: 160 | K29: 2 | L29: Active
A30: 27 | B30: NEWELL TAYLOR CPA | C30: Jasleen.D | D30: Accounting | E30: 1000 | F30: =IF(E30="",0,E30*Settings!B8) -> 85000 | I30: CAS 219 | J30: 160 | K30: 18 | L30: Active
A31: 28 | B31: WEAREQUADRANT | C31: Ayushi, Nikita | D31: Accounting | E31: 3200 | F31: =IF(E31="",0,E31*Settings!B8) -> 272000 | I31: CAS 220 | J31: 240 | K31: 41 | L31: Active
A32: 29 | B32: BUSINESS NAVIGATORS LLC | C32: Jasleen.D | D32: Accounting | E32: 1000 | F32: =IF(E32="",0,E32*Settings!B8) -> 85000 | I32: CAS 163 | J32: 161 | K32: 9 | L32: In Progress
A33: 30 | B33: RRAW CPA LLP | C33: Jasleen.D | D33: Accounting | E33: 400 | F33: =IF(E33="",0,E33*Settings!B8) -> 34000 | I33: CAS 222 | J33: 40 | K33: 4 | L33: Active
A34: 31 | B34: AMI HOLDING | C34: Sachi, Vinita | D34: FP&A, HR | E34: 21820 | F34: =IF(E34="",0,E34*Settings!B8) -> 1854700 | I34: CAS 223 | J34: 960 | K34: 1 | L34: Finished
A35: 32 | B35: PROVISION ACCOUNTING SOLUTIONS | C35: Ammie, Jyoti | D35: B.Tax, I.Tax | E35: 250 | F35: =IF(E35="",0,E35*Settings!B8) -> 21250 | I35: CAS 226 | J35: 220 | K35: 23 | L35: In Progress
A36: 33 | B36: MERAKI ACCOUNTING & TAX LLC | C36: Ayushi | D36: Accounting | E36: 600 | F36: =IF(E36="",0,E36*Settings!B8) -> 51000 | I36: CAS 229 | J36: 80 | K36: 31 | L36: In Progress
A37: 34 | B37: MAINSPRING SOLUTIONS | C37: Jasleen.D | D37: Accounting | E37: 1200 | F37: =IF(E37="",0,E37*Settings!B8) -> 102000 | I37: CAS 230 | J37: 160 | K37: 14 | L37: Active
A38: 35 | B38: HELLO ACCOUNTAX | C38: Ayushi | D38: Accounting | E38: 600 | F38: =IF(E38="",0,E38*Settings!B8) -> 51000 | I38: CAS 231 | J38: 140 | K38: 7 | L38: In Progress
A39: 36 | B39: XPERT BOOKKEEPING LLC | C39: Nikita | D39: Accounting | E39: 1100 | F39: =IF(E39="",0,E39*Settings!B8) -> 93500 | I39: CAS 234 | J39: 200 | K39: 10 | L39: In Progress
A40: 37 | B40: THINKING MAPS, INC. | C40: Nikita | D40: Accounting | E40: 2600 | F40: =IF(E40="",0,E40*Settings!B8) -> 221000 | I40: CAS 236 | J40: 320 | L40: Active
A41: 38 | B41: NATIONAL TAX CENTERS, LLC | C41: Ayushi | D41: Accounting | E41: 4000 | F41: =IF(E41="",0,E41*Settings!B8) -> 340000 | I41: CAS 238 | J41: 480 | K41: 68 | L41: In Progress
A42: 39 | B42: WIGGS CPA TAX & ACCOUNTING | C42: Nikita | D42: Accounting | E42: 600 | F42: =IF(E42="",0,E42*Settings!B8) -> 51000 | I42: CAS 240 | J42: 80 | K42: 23 | L42: Active
A43: 40 | B43: EVERMORE FINANCIAL SERVICES LLC | C43: Jasleen.D | D43: Accounting | E43: 2000 | F43: =IF(E43="",0,E43*Settings!B8) -> 170000 | I43: CAS 241 | J43: 240 | K43: 33 | L43: In Progress
A44: 41 | B44: ANCIENT CITY ACCOUNTING LLC | C44: Jasleen.D | D44: Accounting | E44: 1200 | F44: =IF(E44="",0,E44*Settings!B8) -> 102000 | I44: CAS 243 | J44: 160 | K44: 19 | L44: In Progress
A45: 42 | B45: ABACUS BUSINESS SOLUTIONS, LLC | C45: Jasleen.D | D45: Accounting | E45: 5800 | F45: =IF(E45="",0,E45*Settings!B8) -> 493000 | I45: CAS 246 | J45: 640 | K45: 55 | L45: Active
A46: 43 | B46: TAX GEEK LLC | C46: Ammie, Jyoti, Nikita | D46: Acctg, B.Tax, I.Tax | E46: 1800 | F46: =IF(E46="",0,E46*Settings!B8) -> 153000 | I46: CAS 253 | J46: 220 | K46: 23 | L46: In Progress
A47: 44 | B47: TRI SCAPES LLC | C47: Ayushi, Prachi | D47: Accounting, FP&A | E47: 12550 | F47: =IF(E47="",0,E47*Settings!B8) -> 1066750 | I47: CAS 256 | J47: 640 | L47: In Progress
A48: 45 | B48: HIA TAX | C48: Jasleen.D | D48: Accounting | E48: 1200 | F48: =IF(E48="",0,E48*Settings!B8) -> 102000 | I48: CAS 257 | J48: 160 | K48: 13 | L48: In Progress
A49: 46 | B49: ACE CPA | C49: Nikita | D49: Accounting | E49: 3400 | F49: =IF(E49="",0,E49*Settings!B8) -> 289000 | I49: CAS 258 | J49: 480 | K49: 10 | L49: In Progress
A50: 47 | B50: THE PROFIT SCALE THRIVE | C50: Nikita | D50: Accounting | E50: 600 | F50: =IF(E50="",0,E50*Settings!B8) -> 51000 | I50: CAS 259 | J50: 80 | K50: 14 | L50: In Progress
A51: 48 | B51: CLARK FINANCIALS | C51: Ayushi | D51: Accounting | E51: 700 | F51: =IF(E51="",0,E51*Settings!B8) -> 59500 | I51: CAS 261 | J51: 80 | K51: 11 | L51: In Progress
A52: 49 | B52: MATHESON & ASSOCIATES | C52: Jasleen.D | D52: Accounting | E52: 1200 | F52: =IF(E52="",0,E52*Settings!B8) -> 102000 | I52: CAS 262 | J52: 160 | K52: 13 | L52: In Progress
A53: 50 | B53: ACTION ACCOUNTING | C53: Ammie, Jyoti, Nikita | D53: Acctg, B.Tax, I.Tax | E53: 1200 | F53: =IF(E53="",0,E53*Settings!B8) -> 102000 | I53: CAS 264 | J53: 240 | K53: 25 | L53: In Progress
A54: 51 | B54: LEANCORP ACCOUNTING | C54: Nikita | D54: Accounting | E54: 0 | F54: =IF(E54="",0,E54*Settings!B8) -> 0 | I54: CAS 266 | J54: 80 | K54: 5 | L54: In Progress
A55: 52 | B55: INNOVATIVE CONSULTING & SOLUTIONS, LLC | C55: Ayushi | D55: Accounting | E55: 450 | F55: =IF(E55="",0,E55*Settings!B8) -> 38250 | I55: CAS 267 | J55: 80 | K55: 9 | L55: In Progress
A56: 53 | B56: NUMBER NUTTZ CONSULTING | C56: Ayushi | D56: Accounting | E56: 450 | F56: =IF(E56="",0,E56*Settings!B8) -> 38250 | I56: CAS 268 | J56: 40 | K56: 2 | L56: In Progress
A57: 54 | B57: 4P TAXES LLC | C57: Jasleen.D | D57: Accounting | E57: 1200 | F57: =IF(E57="",0,E57*Settings!B8) -> 102000 | I57: CAS 265 | J57: 160 | K57: 14 | L57: In Progress
A58: 55 | B58: 406 CONSULTING LLC | C58: Ammie, Jyoti | D58: B.Tax, I.Tax | E58: 3600 | F58: =IF(E58="",0,E58*Settings!B8) -> 306000 | I58: CAS 269 | J58: 240 | K58: 22 | L58: In Progress
A59: 56 | B59: ONE KOSMOS, INC. | C59: Tithi | D59: FP&A | E59: 8300 | F59: =IF(E59="",0,E59*Settings!B8) -> 705500 | I59: CAS 270 | J59: 200 | L59: In Progress
A60: 57 | B60: FLEMING ACCOUNTING SOLUTIONS | C60: Ammie, Jyoti, Snehal | D60: Acctg, B.Tax, I.Tax | E60: 3000 | F60: =IF(E60="",0,E60*Settings!B8) -> 255000 | I60: CAS 271 | J60: 240 | K60: 41 | L60: In Progress
A61: 58 | B61: DEDICATED BOOKS LLC | C61: Jasleen.D | D61: Accounting | E61: 1400 | F61: =IF(E61="",0,E61*Settings!B8) -> 119000 | I61: CAS 273 | J61: 160 | L61: In Progress
A62: 59 | B62: WB MORROW | C62: Anshul.O | D62: Accounting | E62: 1800 | F62: =IF(E62="",0,E62*Settings!B8) -> 153000 | I62: CAS 272 | J62: 480 | K62: 1 | L62: In Progress
A63: 60 | B63: PORCHEA & LOTT ACCOUNTING | C63: Nikita | D63: Accounting | E63: 500 | F63: =IF(E63="",0,E63*Settings!B8) -> 42500 | I63: CAS 260 | J63: 80 | K63: 3 | L63: In Progress
A64: 61 | B64: RATHEL’S ACCOUNTING SERVICE, INC | E64: 1400 | F64: =IF(E64="",0,E64*Settings!B8) -> 119000 | I64: CAS 275 | J64: 160 | L64: In Progress
A65: =IF(B65="","",ROW()-3) | F65: =IF(E65="",0,E65*Settings!B8) -> 0
A66: =IF(B66="","",ROW()-3) | F66: =IF(E66="",0,E66*Settings!B8) -> 0
A67: =IF(B67="","",ROW()-3) | F67: =IF(E67="",0,E67*Settings!B8) -> 0
A68: =IF(B68="","",ROW()-3) | F68: =IF(E68="",0,E68*Settings!B8) -> 0
A69: =IF(B69="","",ROW()-3) | F69: =IF(E69="",0,E69*Settings!B8) -> 0
A70: =IF(B70="","",ROW()-3) | F70: =IF(E70="",0,E70*Settings!B8) -> 0
A71: =IF(B71="","",ROW()-3) | F71: =IF(E71="",0,E71*Settings!B8) -> 0
A72: =IF(B72="","",ROW()-3) | F72: =IF(E72="",0,E72*Settings!B8) -> 0
A73: =IF(B73="","",ROW()-3) | F73: =IF(E73="",0,E73*Settings!B8) -> 0
A74: =IF(B74="","",ROW()-3) | F74: =IF(E74="",0,E74*Settings!B8) -> 0
A75: =IF(B75="","",ROW()-3) | F75: =IF(E75="",0,E75*Settings!B8) -> 0
A76: =IF(B76="","",ROW()-3) | F76: =IF(E76="",0,E76*Settings!B8) -> 0
A77: =IF(B77="","",ROW()-3) | F77: =IF(E77="",0,E77*Settings!B8) -> 0
A78: =IF(B78="","",ROW()-3) | F78: =IF(E78="",0,E78*Settings!B8) -> 0
A79: =IF(B79="","",ROW()-3) | F79: =IF(E79="",0,E79*Settings!B8) -> 0
A80: =IF(B80="","",ROW()-3) | F80: =IF(E80="",0,E80*Settings!B8) -> 0
A81: =IF(B81="","",ROW()-3) | F81: =IF(E81="",0,E81*Settings!B8) -> 0
A82: =IF(B82="","",ROW()-3) | F82: =IF(E82="",0,E82*Settings!B8) -> 0
A83: =IF(B83="","",ROW()-3) | F83: =IF(E83="",0,E83*Settings!B8) -> 0
A84: =IF(B84="","",ROW()-3) | F84: =IF(E84="",0,E84*Settings!B8) -> 0
A85: =IF(B85="","",ROW()-3) | F85: =IF(E85="",0,E85*Settings!B8) -> 0
A86: =IF(B86="","",ROW()-3) | F86: =IF(E86="",0,E86*Settings!B8) -> 0
A87: =IF(B87="","",ROW()-3) | F87: =IF(E87="",0,E87*Settings!B8) -> 0
A88: =IF(B88="","",ROW()-3) | F88: =IF(E88="",0,E88*Settings!B8) -> 0
A89: =IF(B89="","",ROW()-3) | F89: =IF(E89="",0,E89*Settings!B8) -> 0
A90: =IF(B90="","",ROW()-3) | F90: =IF(E90="",0,E90*Settings!B8) -> 0
A91: =IF(B91="","",ROW()-3) | F91: =IF(E91="",0,E91*Settings!B8) -> 0
A92: =IF(B92="","",ROW()-3) | F92: =IF(E92="",0,E92*Settings!B8) -> 0
A93: =IF(B93="","",ROW()-3) | F93: =IF(E93="",0,E93*Settings!B8) -> 0
A94: =IF(B94="","",ROW()-3) | F94: =IF(E94="",0,E94*Settings!B8) -> 0
A95: =IF(B95="","",ROW()-3) | F95: =IF(E95="",0,E95*Settings!B8) -> 0
A96: =IF(B96="","",ROW()-3) | F96: =IF(E96="",0,E96*Settings!B8) -> 0
A97: =IF(B97="","",ROW()-3) | F97: =IF(E97="",0,E97*Settings!B8) -> 0
A98: =IF(B98="","",ROW()-3) | F98: =IF(E98="",0,E98*Settings!B8) -> 0
A99: =IF(B99="","",ROW()-3) | F99: =IF(E99="",0,E99*Settings!B8) -> 0
A100: =IF(B100="","",ROW()-3) | F100: =IF(E100="",0,E100*Settings!B8) -> 0
...

Sheet ④ Client-Service Map
A1: CLIENT-SERVICE MAPPING (Seats Allocation)
A2: Instructions: Enter which services each client uses and how many seats (FTEs allocated).
A3: Client Name | B3: Service | C3: Seats Allocated | D3: Status | E3: Controller
A4: 406 CONSULTING LLC | B4: Business Tax | C4: 0.6 | D4: ACTIVE
A5: 406 CONSULTING LLC | B5: Individual Tax | C5: 1.4 | D5: ACTIVE
A6: 4P TAXES LLC | B6: Accounting | C6: 1 | D6: ACTIVE
A7: AB CAPSTONE GROUP | B7: Accounting | C7: 1.5 | D7: ACTIVE
A8: ABACUS BUSINESS SOLUTIONS, LLC | B8: Accounting | C8: 4 | D8: ACTIVE
A9: ACE CPA | B9: Accounting | C9: 2 | D9: ACTIVE
A10: ACT NOW FINANCIAL SERVICES, LLC | B10: Accounting | C10: 0.5 | D10: ACTIVE
A11: ACTION ACCOUNTING | B11: Accounting | C11: 1 | D11: ACTIVE
A12: ACTION ACCOUNTING | B12: Business Tax | C12: 0.15 | D12: ACTIVE
A13: ACTION ACCOUNTING | B13: Individual Tax | C13: 0.35 | D13: ACTIVE
A14: AMI US HOLDING INC. | B14: FP&A | C14: 5 | D14: ACTIVE
A15: AMI US HOLDING INC. | B15: HR | C15: 1 | D15: ACTIVE
... A90: XPERT BOOKKEEPING LLC | B90: Accounting | C90: 1 | D90: ACTIVE

Sheet ⑤ Emp-Client Hours
A1: EMPLOYEE-CLIENT HOURS MAPPING (AUTO-GENERATED)
A2: Formula-driven from ① Timelog Input. Each row = one employee × one client combination with hours > 0.
A3: Employee Name | B3: Employee ID | C3: Client Name | D3: Hours on Client | E3: Department | F3: Is Overhead? | G3: Emp Hourly Rate (₹) AUTO
A4: ='① Timelog Input'!B4 -> Ankit | B4: ='① Timelog Input'!C4 -> CAS-IH_1070 | C4: ='① Timelog Input'!R$3 -> 4P TAXES LLC | D4: ='① Timelog Input'!R4 -> 21.5 | E4: ='① Timelog Input'!H4 -> Accounting | F4: =IF(OR(E4="HR",E4="IT",E4="Marketing"),"YES","NO") -> NO | G4: =IFERROR(VLOOKUP(B4,'② Salary Input'!A:V,14,FALSE())/Settings!B6,0) -> 375
A5: ='① Timelog Input'!B4 -> Ankit | B5: ='① Timelog Input'!C4 -> CAS-IH_1070 | C5: ='① Timelog Input'!AI$3 -> CLOUDIT | D5: ='① Timelog Input'!AI4 -> 5.84 | E5: ='① Timelog Input'!H4 -> Accounting | F5: =IF(OR(E5="HR",E5="IT",E5="Marketing"),"YES","NO") -> NO | G5: =IFERROR(VLOOKUP(B5,'② Salary Input'!A:V,14,FALSE())/Settings!B6,0) -> 375
A6: ='① Timelog Input'!B4 -> Ankit | B6: ='① Timelog Input'!C4 -> CAS-IH_1070 | C6: ='① Timelog Input'!AR$3 -> IAM ACCOUNTING LLC | D6: ='① Timelog Input'!AR4 -> 86.08 | E6: ='① Timelog Input'!H4 -> Accounting | F6: =IF(OR(E6="HR",E6="IT",E6="Marketing"),"YES","NO") -> NO | G6: =IFERROR(VLOOKUP(B6,'② Salary Input'!A:V,14,FALSE())/Settings!B6,0) -> 375
A7: ='① Timelog Input'!B5 -> Astha.D | B7: ='① Timelog Input'!C5 -> CAS-IH_1092 | C7: ='① Timelog Input'!AT$3 -> INVENT WEALTH, CPA | D7: ='① Timelog Input'!AT5 -> 156.75 | E7: ='① Timelog Input'!H5 -> Accounting | F7: =IF(OR(E7="HR",E7="IT",E7="Marketing"),"YES","NO") -> NO | G7: =IFERROR(VLOOKUP(B7,'② Salary Input'!A:V,14,FALSE())/Settings!B6,0) -> 281.25
A8: ='① Timelog Input'!B6 -> Pragati.S | B8: ='① Timelog Input'!C6 -> CAS-IH_1105 | C8: ='① Timelog Input'!AC$3 -> BRIGHTSKIES BUSINESS SERVICES, LLC | D8: ='① Timelog Input'!AC6 -> 69.58 | E8: ='① Timelog Input'!H6 -> Accounting | F8: =IF(OR(E8="HR",E8="IT",E8="Marketing"),"YES","NO") -> NO | G8: =IFERROR(VLOOKUP(B8,'② Salary Input'!A:V,14,FALSE())/Settings!B6,0) -> 406.25
A9: ='① Timelog Input'!B6 -> Pragati.S | B9: ='① Timelog Input'!C6 -> CAS-IH_1105 | C9: ='① Timelog Input'!AI$3 -> CLOUDIT | D9: ='① Timelog Input'!AI6 -> 16.61 | E9: ='① Timelog Input'!H6 -> Accounting | F9: =IF(OR(E9="HR",E9="IT",E9="Marketing"),"YES","NO") -> NO | G9: =IFERROR(VLOOKUP(B9,'② Salary Input'!A:V,14,FALSE())/Settings!B6,0) -> 406.25
A10: ='① Timelog Input'!B6 -> Pragati.S | B10: ='① Timelog Input'!C6 -> CAS-IH_1105 | C10: ='① Timelog Input'!AT$3 -> INVENT WEALTH, CPA | D10: ='① Timelog Input'!AT6 -> 3.82 | E10: ='① Timelog Input'!H6 -> Accounting | F10: =IF(OR(E10="HR",E10="IT",E10="Marketing"),"YES","NO") -> NO | G10: =IFERROR(VLOOKUP(B10,'② Salary Input'!A:V,14,FALSE())/Settings!B6,0) -> 406.25
A11: ='① Timelog Input'!B6 -> Pragati.S | B11: ='① Timelog Input'!C6 -> CAS-IH_1105 | C11: ='① Timelog Input'!AY$3 -> MAINSPRING SOLUTIONS | D11: ='① Timelog Input'!AY6 -> 27.4 | E11: ='① Timelog Input'!H6 -> Accounting | F11: =IF(OR(E11="HR",E11="IT",E11="Marketing"),"YES","NO") -> NO | G11: =IFERROR(VLOOKUP(B11,'② Salary Input'!A:V,14,FALSE())/Settings!B6,0) -> 406.25
A12: ='① Timelog Input'!B6 -> Pragati.S | B12: ='① Timelog Input'!C6 -> CAS-IH_1105 | C12: ='① Timelog Input'!BA$3 -> MATHESON & ASSOCIATES | D12: ='① Timelog Input'!BA6 -> 8.17 | E12: ='① Timelog Input'!H6 -> Accounting | F12: =IF(OR(E12="HR",E12="IT",E12="Marketing"),"YES","NO") -> NO | G12: =IFERROR(VLOOKUP(B12,'② Salary Input'!A:V,14,FALSE())/Settings!B6,0) -> 406.25
A13: ='① Timelog Input'!B7 -> Anshul.O | B13: ='① Timelog Input'!C7 -> CAS-IH_1109 | C13: ='① Timelog Input'!Y$3 -> ANCIENT CITY ACCOUNTING LLC | D13: ='① Timelog Input'!Y7 -> 4.5 | E13: ='① Timelog Input'!H7 -> Accounting | F13: =IF(OR(E13="HR",E13="IT",E13="Marketing"),"YES","NO") -> NO | G13: =IFERROR(VLOOKUP(B13,'② Salary Input'!A:V,14,FALSE())/Settings!B6,0) -> 525
A14: ='① Timelog Input'!B7 -> Anshul.O | B14: ='① Timelog Input'!C7 -> CAS-IH_1109 | C14: ='① Timelog Input'!AC$3 -> BRIGHTSKIES BUSINESS SERVICES, LLC | D14: ='① Timelog Input'!AC7 -> 31.67 | E14: ='① Timelog Input'!H7 -> Accounting | F14: =IF(OR(E14="HR",E14="IT",E14="Marketing"),"YES","NO") -> NO | G14: =IFERROR(VLOOKUP(B14,'② Salary Input'!A:V,14,FALSE())/Settings!B6,0) -> 525
A15: ='① Timelog Input'!B7 -> Anshul.O | B15: ='① Timelog Input'!C7 -> CAS-IH_1109 | C15: ='① Timelog Input'!AD$3 -> BUSINESS NAVIGATORS LLC | D15: ='① Timelog Input'!AD7 -> 9.5 | E15: ='① Timelog Input'!H7 -> Accounting | F15: =IF(OR(E15="HR",E15="IT",E15="Marketing"),"YES","NO") -> NO | G15: =IFERROR(VLOOKUP(B15,'② Salary Input'!A:V,14,FALSE())/Settings!B6,0) -> 525
A16: ='① Timelog Input'!B7 -> Anshul.O | B16: ='① Timelog Input'!C7 -> CAS-IH_1109 | C16: ='① Timelog Input'!AI$3 -> CLOUDIT | D16: ='① Timelog Input'!AI7 -> 19.5 | E16: ='① Timelog Input'!H7 -> Accounting | F16: =IF(OR(E16="HR",E16="IT",E16="Marketing"),"YES","NO") -> NO | G16: =IFERROR(VLOOKUP(B16,'② Salary Input'!A:V,14,FALSE())/Settings!B6,0) -> 525
A17: ='① Timelog Input'!B7 -> Anshul.O | B17: ='① Timelog Input'!C7 -> CAS-IH_1109 | C17: ='① Timelog Input'!AQ$3 -> HIA TAX | D17: ='① Timelog Input'!AQ7 -> 6 | E17: ='① Timelog Input'!H7 -> Accounting | F17: =IF(OR(E17="HR",E17="IT",E17="Marketing"),"YES","NO") -> NO | G17: =IFERROR(VLOOKUP(B17,'② Salary Input'!A:V,14,FALSE())/Settings!B6,0) -> 525
A18: ='① Timelog Input'!B7 -> Anshul.O | B18: ='① Timelog Input'!C7 -> CAS-IH_1109 | C18: ='① Timelog Input'!AT$3 -> INVENT WEALTH, CPA | D18: ='① Timelog Input'!AT7 -> 19.5 | E18: ='① Timelog Input'!H7 -> Accounting | F18: =IF(OR(E18="HR",E18="IT",E18="Marketing"),"YES","NO") -> NO | G18: =IFERROR(VLOOKUP(B18,'② Salary Input'!A:V,14,FALSE())/Settings!B6,0) -> 525
A19: ='① Timelog Input'!B7 -> Anshul.O | B19: ='① Timelog Input'!C7 -> CAS-IH_1109 | C19: ='① Timelog Input'!AY$3 -> MAINSPRING SOLUTIONS | D19: ='① Timelog Input'!AY7 -> 6 | E19: ='① Timelog Input'!H7 -> Accounting | F19: =IF(OR(E19="HR",E19="IT",E19="Marketing"),"YES","NO") -> NO | G19: =IFERROR(VLOOKUP(B19,'② Salary Input'!A:V,14,FALSE())/Settings!B6,0) -> 525
A20: ='① Timelog Input'!B7 -> Anshul.O | B20: ='① Timelog Input'!C7 -> CAS-IH_1109 | C20: ='① Timelog Input'!BA$3 -> MATHESON & ASSOCIATES | D20: ='① Timelog Input'!BA7 -> 0.5 | E20: ='① Timelog Input'!H7 -> Accounting | F20: =IF(OR(E20="HR",E20="IT",E20="Marketing"),"YES","NO") -> NO | G20: =IFERROR(VLOOKUP(B20,'② Salary Input'!A:V,14,FALSE())/Settings!B6,0) -> 525
A21: ='① Timelog Input'!B7 -> Anshul.O | B21: ='① Timelog Input'!C7 -> CAS-IH_1109 | C21: ='① Timelog Input'!BG$3 -> NEWELL TAYLOR CPA | D21: ='① Timelog Input'!BG7 -> 2 | E21: ='① Timelog Input'!H7 -> Accounting | F21: =IF(OR(E21="HR",E21="IT",E21="Marketing"),"YES","NO") -> NO | G21: =IFERROR(VLOOKUP(B21,'② Salary Input'!A:V,14,FALSE())/Settings!B6,0) -> 525
A22: ='① Timelog Input'!B7 -> Anshul.O | B22: ='① Timelog Input'!C7 -> CAS-IH_1109 | C22: ='① Timelog Input'!BO$3 -> RRAW CPA LLP | D22: ='① Timelog Input'!BO7 -> 5 | E22: ='① Timelog Input'!H7 -> Accounting | F22: =IF(OR(E22="HR",E22="IT",E22="Marketing"),"YES","NO") -> NO | G22: =IFERROR(VLOOKUP(B22,'② Salary Input'!A:V,14,FALSE())/Settings!B6,0) -> 525
A23: ='① Timelog Input'!B7 -> Anshul.O | B23: ='① Timelog Input'!C7 -> CAS-IH_1109 | C23: ='① Timelog Input'!BZ$3 -> WB MORROW | D23: ='① Timelog Input'!BZ7 -> 53.25 | E23: ='① Timelog Input'!H7 -> Accounting | F23: =IF(OR(E23="HR",E23="IT",E23="Marketing"),"YES","NO") -> NO | G23: =IFERROR(VLOOKUP(B23,'② Salary Input'!A:V,14,FALSE())/Settings!B6,0) -> 525
A24: ='① Timelog Input'!B8 -> Shefali.B | B24: ='① Timelog Input'!C8 -> CAS-IH_1122 | C24: ='① Timelog Input'!AI$3 -> CLOUDIT | D24: ='① Timelog Input'!AI8 -> 5.92 | E24: ='① Timelog Input'!H8 -> Accounting | F24: =IF(OR(E24="HR",E24="IT",E24="Marketing"),"YES","NO") -> NO | G24: =IFERROR(VLOOKUP(B24,'② Salary Input'!A:V,14,FALSE())/Settings!B6,0) -> 281.25
A25: ='① Timelog Input'!B8 -> Shefali.B | B25: ='① Timelog Input'!C8 -> CAS-IH_1122 | C25: ='① Timelog Input'!BA$3 -> MATHESON & ASSOCIATES | D25: ='① Timelog Input'!BA8 -> 141.49 | E25: ='① Timelog Input'!H8 -> Accounting | F25: =IF(OR(E25="HR",E25="IT",E25="Marketing"),"YES","NO") -> NO | G25: =IFERROR(VLOOKUP(B25,'② Salary Input'!A:V,14,FALSE())/Settings!B6,0) -> 281.25
A26: ='① Timelog Input'!B9 -> Sandesh.H | B26: ='① Timelog Input'!C9 -> CAS-IH_1149 | C26: ='① Timelog Input'!AB$3 -> BRADLEY FINANCIAL SERVICES LLC | D26: ='① Timelog Input'!AB9 -> 43.5 | E26: ='① Timelog Input'!H9 -> Accounting | F26: =IF(OR(E26="HR",E26="IT",E26="Marketing"),"YES","NO") -> NO | G26: =IFERROR(VLOOKUP(B26,'② Salary Input'!A:V,14,FALSE())/Settings!B6,0) -> 250
A27: ='① Timelog Input'!B9 -> Sandesh.H | B27: ='① Timelog Input'!C9 -> CAS-IH_1149 | C27: ='① Timelog Input'!AC$3 -> BRIGHTSKIES BUSINESS SERVICES, LLC | D27: ='① Timelog Input'!AC9 -> 122.5 | E27: ='① Timelog Input'!H9 -> Accounting | F27: =IF(OR(E27="HR",E27="IT",E27="Marketing"),"YES","NO") -> NO | G27: =IFERROR(VLOOKUP(B27,'② Salary Input'!A:V,14,FALSE())/Settings!B6,0) -> 250
A28: ='① Timelog Input'!B10 -> Robin.S | B28: ='① Timelog Input'!C10 -> CAS-IH_1162 | C28: ='① Timelog Input'!AI$3 -> CLOUDIT | D28: ='① Timelog Input'!AI10 -> 1 | E28: ='① Timelog Input'!H10 -> Accounting | F28: =IF(OR(E28="HR",E28="IT",E28="Marketing"),"YES","NO") -> NO | G28: =IFERROR(VLOOKUP(B28,'② Salary Input'!A:V,14,FALSE())/Settings!B6,0) -> 250
A29: ='① Timelog Input'!B10 -> Robin.S | B29: ='① Timelog Input'!C10 -> CAS-IH_1162 | C29: ='① Timelog Input'!AT$3 -> INVENT WEALTH, CPA | D29: ='① Timelog Input'!AT10 -> 140.24 | E29: ='① Timelog Input'!H10 -> Accounting | F29: =IF(OR(E29="HR",E29="IT",E29="Marketing"),"YES","NO") -> NO | G29: =IFERROR(VLOOKUP(B29,'② Salary Input'!A:V,14,FALSE())/Settings!B6,0) -> 250
A30: ='① Timelog Input'!B11 -> Vijet.B | B30: ='① Timelog Input'!C11 -> CAS-RR_2371 | C30: ='① Timelog Input'!AI$3 -> CLOUDIT | D30: ='① Timelog Input'!AI11 -> 2 | E30: ='① Timelog Input'!H11 -> Accounting | F30: =IF(OR(E30="HR",E30="IT",E30="Marketing"),"YES","NO") -> NO | G30: =IFERROR(VLOOKUP(B30,'② Salary Input'!A:V,14,FALSE())/Settings!B6,0) -> 200
A31: ='① Timelog Input'!B11 -> Vijet.B | B31: ='① Timelog Input'!C11 -> CAS-RR_2371 | C31: ='① Timelog Input'!AQ$3 -> HIA TAX | D31: ='① Timelog Input'!AQ11 -> 73 | E31: ='① Timelog Input'!H11 -> Accounting | F31: =IF(OR(E31="HR",E31="IT",E31="Marketing"),"YES","NO") -> NO | G31: =IFERROR(VLOOKUP(B31,'② Salary Input'!A:V,14,FALSE())/Settings!B6,0) -> 200
A32: ='① Timelog Input'!B11 -> Vijet.B | B32: ='① Timelog Input'!C11 -> CAS-RR_2371 | C32: ='① Timelog Input'!BG$3 -> NEWELL TAYLOR CPA | D32: ='① Timelog Input'!BG11 -> 82.75 | E32: ='① Timelog Input'!H11 -> Accounting | F32: =IF(OR(E32="HR",E32="IT",E32="Marketing"),"YES","NO") -> NO | G32: =IFERROR(VLOOKUP(B32,'② Salary Input'!A:V,14,FALSE())/Settings!B6,0) -> 200
A33: ='① Timelog Input'!B12 -> Somya.B | B33: ='① Timelog Input'!C12 -> CAS-IH_1169 | C33: ='① Timelog Input'!Y$3 -> ANCIENT CITY ACCOUNTING LLC | D33: ='① Timelog Input'!Y12 -> 139.75 | E33: ='① Timelog Input'!H12 -> Accounting | F33: =IF(OR(E33="HR",E33="IT",E33="Marketing"),"YES","NO") -> NO | G33: =IFERROR(VLOOKUP(B33,'② Salary Input'!A:V,14,FALSE())/Settings!B6,0) -> 312.5
A34: ='① Timelog Input'!B12 -> Somya.B | B34: ='① Timelog Input'!C12 -> CAS-IH_1169 | C34: ='① Timelog Input'!AI$3 -> CLOUDIT | D34: ='① Timelog Input'!AI12 -> 7 | E34: ='① Timelog Input'!H12 -> Accounting | F34: =IF(OR(E34="HR",E34="IT",E34="Marketing"),"YES","NO") -> NO | G34: =IFERROR(VLOOKUP(B34,'② Salary Input'!A:V,14,FALSE())/Settings!B6,0) -> 312.5
A35: ='① Timelog Input'!B13 -> Jasleen.D | B35: ='① Timelog Input'!C13 -> CAS-IH_1069 | C35: ='① Timelog Input'!Q$3 -> 406 CONSULTING LLC | D35: ='① Timelog Input'!Q13 -> 0 | E35: ='① Timelog Input'!H13 -> Accounting | F35: =IF(OR(E35="HR",E35="IT",E35="Marketing"),"YES","NO") -> NO | G35: =IFERROR(VLOOKUP(B35,'② Salary Input'!A:V,14,FALSE())/Settings!B6,0) -> 1531.25
A36: ='① Timelog Input'!B13 -> Jasleen.D | B36: ='① Timelog Input'!C13 -> CAS-IH_1069 | C36: ='① Timelog Input'!AI$3 -> CLOUDIT | D36: ='① Timelog Input'!AI13 -> 54 | E36: ='① Timelog Input'!H13 -> Accounting | F36: =IF(OR(E36="HR",E36="IT",E36="Marketing"),"YES","NO") -> NO | G36: =IFERROR(VLOOKUP(B36,'② Salary Input'!A:V,14,FALSE())/Settings!B6,0) -> 1531.25
A37: ='① Timelog Input'!B13 -> Jasleen.D | B37: ='① Timelog Input'!C13 -> CAS-IH_1069 | C37: ='① Timelog Input'!AM$3 -> Fleming Accounting Solutions | D37: ='① Timelog Input'!AM13 -> 0 | E37: ='① Timelog Input'!H13 -> Accounting | F37: =IF(OR(E37="HR",E37="IT",E37="Marketing"),"YES","NO") -> NO | G37: =IFERROR(VLOOKUP(B37,'② Salary Input'!A:V,14,FALSE())/Settings!B6,0) -> 1531.25
A38: ='① Timelog Input'!B13 -> Jasleen.D | B38: ='① Timelog Input'!C13 -> CAS-IH_1069 | C38: ='① Timelog Input'!AN$3 -> FULL COMPLIANCE, LLC | D38: ='① Timelog Input'!AN13 -> 0 | E38: ='① Timelog Input'!H13 -> Accounting | F38: =IF(OR(E38="HR",E38="IT",E38="Marketing"),"YES","NO") -> NO | G38: =IFERROR(VLOOKUP(B38,'② Salary Input'!A:V,14,FALSE())/Settings!B6,0) -> 1531.25
A39: ='① Timelog Input'!B13 -> Jasleen.D | B39: ='① Timelog Input'!C13 -> CAS-IH_1069 | C39: ='① Timelog Input'!AT$3 -> INVENT WEALTH, CPA | D39: ='① Timelog Input'!AT13 -> 2 | E39: ='① Timelog Input'!H13 -> Accounting | F39: =IF(OR(E39="HR",E39="IT",E39="Marketing"),"YES","NO") -> NO | G39: =IFERROR(VLOOKUP(B39,'② Salary Input'!A:V,14,FALSE())/Settings!B6,0) -> 1531.25
A40: ='① Timelog Input'!B13 -> Jasleen.D | B40: ='① Timelog Input'!C13 -> CAS-IH_1069 | C40: ='① Timelog Input'!AZ$3 -> MARTIN D. EISENSTEIN, CPA | D40: ='① Timelog Input'!AZ13 -> 0 | E40: ='① Timelog Input'!H13 -> Accounting | F40: =IF(OR(E40="HR",E40="IT",E40="Marketing"),"YES","NO") -> NO | G40: =IFERROR(VLOOKUP(B40,'② Salary Input'!A:V,14,FALSE())/Settings!B6,0) -> 1531.25
A41: ='① Timelog Input'!B13 -> Jasleen.D | B41: ='① Timelog Input'!C13 -> CAS-IH_1069 | C41: ='① Timelog Input'!BE$3 -> NATIONAL TAX CENTERS, LLC | D41: ='① Timelog Input'!BE13 -> 0 | E41: ='① Timelog Input'!H13 -> Accounting | F41: =IF(OR(E41="HR",E41="IT",E41="Marketing"),"YES","NO") -> NO | G41: =IFERROR(VLOOKUP(B41,'② Salary Input'!A:V,14,FALSE())/Settings!B6,0) -> 1531.25
A42: ='① Timelog Input'!B13 -> Jasleen.D | B42: ='① Timelog Input'!C13 -> CAS-IH_1069 | C42: ='① Timelog Input'!BK$3 -> PROVISION ACCOUNTING SOLUTIONS | D42: ='① Timelog Input'!BK13 -> 0 | E42: ='① Timelog Input'!H13 -> Accounting | F42: =IF(OR(E42="HR",E42="IT",E42="Marketing"),"YES","NO") -> NO | G42: =IFERROR(VLOOKUP(B42,'② Salary Input'!A:V,14,FALSE())/Settings!B6,0) -> 1531.25
A43: ='① Timelog Input'!B13 -> Jasleen.D | B43: ='① Timelog Input'!C13 -> CAS-IH_1069 | C43: ='① Timelog Input'!BL$3 -> PW ADVISORS LLC | D43: ='① Timelog Input'!BL13 -> 0 | E43: ='① Timelog Input'!H13 -> Accounting | F43: =IF(OR(E43="HR",E43="IT",E43="Marketing"),"YES","NO") -> NO | G43: =IFERROR(VLOOKUP(B43,'② Salary Input'!A:V,14,FALSE())/Settings!B6,0) -> 1531.25
A44: ='① Timelog Input'!B14 -> Jyoti | B44: ='① Timelog Input'!C14 -> CAS-IH_1037 | C44: ='① Timelog Input'!AI$3 -> CLOUDIT | D44: ='① Timelog Input'!AI14 -> 40.16 | E44: ='① Timelog Input'!H14 -> Accounting, Business Tax, VA | F44: =IF(OR(E44="HR",E44="IT",E44="Marketing"),"YES","NO") -> NO | G44: =IFERROR(VLOOKUP(B44,'② Salary Input'!A:V,14,FALSE())/Settings!B6,0) -> 0
A45: ='① Timelog Input'!B15 -> Vini | B45: ='① Timelog Input'!C15 -> CAS-IH_1018 | C45: ='① Timelog Input'!AI$3 -> CLOUDIT | D45: ='① Timelog Input'!AI15 -> 10.42 | E45: ='① Timelog Input'!H15 -> HR | F45: =IF(OR(E45="HR",E45="IT",E45="Marketing"),"YES","NO") -> YES | G45: =IFERROR(VLOOKUP(B45,'② Salary Input'!A:V,14,FALSE())/Settings!B6,0) -> 1093.75
A46: ='① Timelog Input'!B15 -> Vini | B46: ='① Timelog Input'!C15 -> CAS-IH_1018 | C46: ='① Timelog Input'!AM$3 -> Fleming Accounting Solutions | D46: ='① Timelog Input'!AM15 -> 0 | E46: ='① Timelog Input'!H15 -> HR | F46: =IF(OR(E46="HR",E46="IT",E46="Marketing"),"YES","NO") -> YES | G46: =IFERROR(VLOOKUP(B46,'② Salary Input'!A:V,14,FALSE())/Settings!B6,0) -> 1093.75
A47: ='① Timelog Input'!B15 -> Vini | B47: ='① Timelog Input'!C15 -> CAS-IH_1018 | C47: ='① Timelog Input'!AT$3 -> INVENT WEALTH, CPA | D47: ='① Timelog Input'!AT15 -> 0 | E47: ='① Timelog Input'!H15 -> HR | F47: =IF(OR(E47="HR",E47="IT",E47="Marketing"),"YES","NO") -> YES | G47: =IFERROR(VLOOKUP(B47,'② Salary Input'!A:V,14,FALSE())/Settings!B6,0) -> 1093.75
A48: ='① Timelog Input'!B15 -> Vini | B48: ='① Timelog Input'!C15 -> CAS-IH_1018 | C48: ='① Timelog Input'!AU$3 -> jmWILLIAMS, CPA, LLP | D48: ='① Timelog Input'!AU15 -> 0 | E48: ='① Timelog Input'!H15 -> HR | F48: =IF(OR(E48="HR",E48="IT",E48="Marketing"),"YES","NO") -> YES | G48: =IFERROR(VLOOKUP(B48,'② Salary Input'!A:V,14,FALSE())/Settings!B6,0) -> 1093.75
A49: ='① Timelog Input'!B15 -> Vini | B49: ='① Timelog Input'!C15 -> CAS-IH_1018 | C49: ='① Timelog Input'!AZ$3 -> MARTIN D. EISENSTEIN, CPA | D49: ='① Timelog Input'!AZ15 -> 0 | E49: ='① Timelog Input'!H15 -> HR | F49: =IF(OR(E49="HR",E49="IT",E49="Marketing"),"YES","NO") -> YES | G49: =IFERROR(VLOOKUP(B49,'② Salary Input'!A:V,14,FALSE())/Settings!B6,0) -> 1093.75
A50: ='① Timelog Input'!B15 -> Vini | B50: ='① Timelog Input'!C15 -> CAS-IH_1018 | C50: ='① Timelog Input'!BE$3 -> NATIONAL TAX CENTERS, LLC | D50: ='① Timelog Input'!BE15 -> 0 | E50: ='① Timelog Input'!H15 -> HR | F50: =IF(OR(E50="HR",E50="IT",E50="Marketing"),"YES","NO") -> YES | G50: =IFERROR(VLOOKUP(B50,'② Salary Input'!A:V,14,FALSE())/Settings!B6,0) -> 1093.75
A51: ='① Timelog Input'!B15 -> Vini | B51: ='① Timelog Input'!C15 -> CAS-IH_1018 | C51: ='① Timelog Input'!BK$3 -> PROVISION ACCOUNTING SOLUTIONS | D51: ='① Timelog Input'!BK15 -> 0 | E51: ='① Timelog Input'!H15 -> HR | F51: =IF(OR(E51="HR",E51="IT",E51="Marketing"),"YES","NO") -> YES | G51: =IFERROR(VLOOKUP(B51,'② Salary Input'!A:V,14,FALSE())/Settings!B6,0) -> 1093.75
A52: ='① Timelog Input'!B15 -> Vini | B52: ='① Timelog Input'!C15 -> CAS-IH_1018 | C52: ='① Timelog Input'!BL$3 -> PW ADVISORS LLC | D52: ='① Timelog Input'!BL15 -> 0 | E52: ='① Timelog Input'!H15 -> HR | F52: =IF(OR(E52="HR",E52="IT",E52="Marketing"),"YES","NO") -> YES | G52: =IFERROR(VLOOKUP(B52,'② Salary Input'!A:V,14,FALSE())/Settings!B6,0) -> 1093.75
A53: ='① Timelog Input'!B15 -> Vini | B53: ='① Timelog Input'!C15 -> CAS-IH_1018 | C53: ='① Timelog Input'!BT$3 -> TAX GEEK LLC | D53: ='① Timelog Input'!BT15 -> 0 | E53: ='① Timelog Input'!H15 -> HR | F53: =IF(OR(E53="HR",E53="IT",E53="Marketing"),"YES","NO") -> YES | G53: =IFERROR(VLOOKUP(B53,'② Salary Input'!A:V,14,FALSE())/Settings!B6,0) -> 1093.75
A54: ='① Timelog Input'!B16 -> Asmita | B54: ='① Timelog Input'!C16 -> CAS-IH_1049 | C54: ='① Timelog Input'!U$3 -> ACE CPA | D54: ='① Timelog Input'!U16 -> 0 | E54: ='① Timelog Input'!H16 -> Accounting, Business Tax | F54: =IF(OR(E54="HR",E54="IT",E54="Marketing"),"YES","NO") -> NO | G54: =IFERROR(VLOOKUP(B54,'② Salary Input'!A:V,14,FALSE())/Settings!B6,0) -> 390.625
A55: ='① Timelog Input'!B16 -> Asmita | B55: ='① Timelog Input'!C16 -> CAS-IH_1049 | C55: ='① Timelog Input'!AI$3 -> CLOUDIT | D55: ='① Timelog Input'!AI16 -> 1 | E55: ='① Timelog Input'!H16 -> Accounting, Business Tax | F55: =IF(OR(E55="HR",E55="IT",E55="Marketing"),"YES","NO") -> NO | G55: =IFERROR(VLOOKUP(B55,'② Salary Input'!A:V,14,FALSE())/Settings!B6,0) -> 390.625
A56: ='① Timelog Input'!B16 -> Asmita | B56: ='① Timelog Input'!C16 -> CAS-IH_1049 | C56: ='① Timelog Input'!BM$3 -> RATHEL’S ACCOUNTING SERVICE, INC | D56: ='① Timelog Input'!BM16 -> 0 | E56: ='① Timelog Input'!H16 -> Accounting, Business Tax | F56: =IF(OR(E56="HR",E56="IT",E56="Marketing"),"YES","NO") -> NO | G56: =IFERROR(VLOOKUP(B56,'② Salary Input'!A:V,14,FALSE())/Settings!B6,0) -> 390.625
A57: ='① Timelog Input'!B16 -> Asmita | B57: ='① Timelog Input'!C16 -> CAS-IH_1049 | C57: ='① Timelog Input'!CA$3 -> WE ARE QUADRANT | D57: ='① Timelog Input'!CA16 -> 0 | E57: ='① Timelog Input'!H16 -> Accounting, Business Tax | F57: =IF(OR(E57="HR",E57="IT",E57="Marketing"),"YES","NO") -> NO | G57: =IFERROR(VLOOKUP(B57,'② Salary Input'!A:V,14,FALSE())/Settings!B6,0) -> 390.625
A58: ='① Timelog Input'!B16 -> Asmita | B58: ='① Timelog Input'!C16 -> CAS-IH_1049 | C58: ='① Timelog Input'!CB$3 -> WIGGS CPA TAX & ACCOUNTING | D58: ='① Timelog Input'!CB16 -> 0 | E58: ='① Timelog Input'!H16 -> Accounting, Business Tax | F58: =IF(OR(E58="HR",E58="IT",E58="Marketing"),"YES","NO") -> NO | G58: =IFERROR(VLOOKUP(B58,'② Salary Input'!A:V,14,FALSE())/Settings!B6,0) -> 390.625
A59: ='① Timelog Input'!B18 -> Ayushi | B59: ='① Timelog Input'!C18 -> CAS-IH_1051 | C59: ='① Timelog Input'!U$3 -> ACE CPA | D59: ='① Timelog Input'!U18 -> 0 | E59: ='① Timelog Input'!H18 -> Accounting, Business Tax | F59: =IF(OR(E59="HR",E59="IT",E59="Marketing"),"YES","NO") -> NO | G59: =IFERROR(VLOOKUP(B59,'② Salary Input'!A:V,14,FALSE())/Settings!B6,0) -> 906.25
A60: ='① Timelog Input'!B18 -> Ayushi | B60: ='① Timelog Input'!C18 -> CAS-IH_1051 | C60: ='① Timelog Input'!W$3 -> ACTION ACCOUNTING | D60: ='① Timelog Input'!W18 -> 0 | E60: ='① Timelog Input'!H18 -> Accounting, Business Tax | F60: =IF(OR(E60="HR",E60="IT",E60="Marketing"),"YES","NO") -> NO | G60: =IFERROR(VLOOKUP(B60,'② Salary Input'!A:V,14,FALSE())/Settings!B6,0) -> 906.25
A61: ='① Timelog Input'!B18 -> Ayushi | B61: ='① Timelog Input'!C18 -> CAS-IH_1051 | C61: ='① Timelog Input'!AI$3 -> CLOUDIT | D61: ='① Timelog Input'!AI18 -> 0 | E61: ='① Timelog Input'!H18 -> Accounting, Business Tax | F61: =IF(OR(E61="HR",E61="IT",E61="Marketing"),"YES","NO") -> NO | G61: =IFERROR(VLOOKUP(B61,'② Salary Input'!A:V,14,FALSE())/Settings!B6,0) -> 906.25
A62: ='① Timelog Input'!B18 -> Ayushi | B62: ='① Timelog Input'!C18 -> CAS-IH_1051 | C62: ='① Timelog Input'!BB$3 -> MCFADDEN ACCOUNTING | D62: ='① Timelog Input'!BB18 -> 0 | E62: ='① Timelog Input'!H18 -> Accounting, Business Tax | F62: =IF(OR(E62="HR",E62="IT",E62="Marketing"),"YES","NO") -> NO | G62: =IFERROR(VLOOKUP(B62,'② Salary Input'!A:V,14,FALSE())/Settings!B6,0) -> 906.25
A63: ='① Timelog Input'!B18 -> Ayushi | B63: ='① Timelog Input'!C18 -> CAS-IH_1051 | C63: ='① Timelog Input'!BL$3 -> PW ADVISORS LLC | D63: ='① Timelog Input'!BL18 -> 0 | E63: ='① Timelog Input'!H18 -> Accounting, Business Tax | F63: =IF(OR(E63="HR",E63="IT",E63="Marketing"),"YES","NO") -> NO | G63: =IFERROR(VLOOKUP(B63,'② Salary Input'!A:V,14,FALSE())/Settings!B6,0) -> 906.25
A64: ='① Timelog Input'!B18 -> Ayushi | B64: ='① Timelog Input'!C18 -> CAS-IH_1051 | C64: ='① Timelog Input'!BM$3 -> RATHEL’S ACCOUNTING SERVICE, INC | D64: ='① Timelog Input'!BM18 -> 0 | E64: ='① Timelog Input'!H18 -> Accounting, Business Tax | F64: =IF(OR(E64="HR",E64="IT",E64="Marketing"),"YES","NO") -> NO | G64: =IFERROR(VLOOKUP(B64,'② Salary Input'!A:V,14,FALSE())/Settings!B6,0) -> 906.25
A65: ='① Timelog Input'!B18 -> Ayushi | B65: ='① Timelog Input'!C18 -> CAS-IH_1051 | C65: ='① Timelog Input'!BV$3 -> THE TAX CUTTERY | D65: ='① Timelog Input'!BV18 -> 0 | E65: ='① Timelog Input'!H18 -> Accounting, Business Tax | F65: =IF(OR(E65="HR",E65="IT",E65="Marketing"),"YES","NO") -> NO | G65: =IFERROR(VLOOKUP(B65,'② Salary Input'!A:V,14,FALSE())/Settings!B6,0) -> 906.25
A66: ='① Timelog Input'!B18 -> Ayushi | B66: ='① Timelog Input'!C18 -> CAS-IH_1051 | C66: ='① Timelog Input'!BW$3 -> THINKING MAPS, INC. | D66: ='① Timelog Input'!BW18 -> 0 | E66: ='① Timelog Input'!H18 -> Accounting, Business Tax | F66: =IF(OR(E66="HR",E66="IT",E66="Marketing"),"YES","NO") -> NO | G66: =IFERROR(VLOOKUP(B66,'② Salary Input'!A:V,14,FALSE())/Settings!B6,0) -> 906.25
A67: ='① Timelog Input'!B18 -> Ayushi | B67: ='① Timelog Input'!C18 -> CAS-IH_1051 | C67: ='① Timelog Input'!CA$3 -> WE ARE QUADRANT | D67: ='① Timelog Input'!CA18 -> 0 | E67: ='① Timelog Input'!H18 -> Accounting, Business Tax | F67: =IF(OR(E67="HR",E67="IT",E67="Marketing"),"YES","NO") -> NO | G67: =IFERROR(VLOOKUP(B67,'② Salary Input'!A:V,14,FALSE())/Settings!B6,0) -> 906.25
A68: ='① Timelog Input'!B18 -> Ayushi | B68: ='① Timelog Input'!C18 -> CAS-IH_1051 | C68: ='① Timelog Input'!CC$3 -> XPERT BOOKKEEPING LLC | D68: ='① Timelog Input'!CC18 -> 0 | E68: ='① Timelog Input'!H18 -> Accounting, Business Tax | F68: =IF(OR(E68="HR",E68="IT",E68="Marketing"),"YES","NO") -> NO | G68: =IFERROR(VLOOKUP(B68,'② Salary Input'!A:V,14,FALSE())/Settings!B6,0) -> 906.25
A69: ='① Timelog Input'!B21 -> Gaganjot | B69: ='① Timelog Input'!C21 -> CAS-IH_1159 | C69: ='① Timelog Input'!AI$3 -> CLOUDIT | D69: ='① Timelog Input'!AI21 -> 0 | E69: ='① Timelog Input'!H21 -> Accounting, Business Tax | F69: =IF(OR(E69="HR",E69="IT",E69="Marketing"),"YES","NO") -> NO | G69: =IFERROR(VLOOKUP(B69,'② Salary Input'!A:V,14,FALSE())/Settings!B6,0) -> 437.5
A70: ='① Timelog Input'!B21 -> Gaganjot | B70: ='① Timelog Input'!C21 -> CAS-IH_1159 | C70: ='① Timelog Input'!AN$3 -> FULL COMPLIANCE, LLC | D70: ='① Timelog Input'!AN21 -> 0 | E70: ='① Timelog Input'!H21 -> Accounting, Business Tax | F70: =IF(OR(E70="HR",E70="IT",E70="Marketing"),"YES","NO") -> NO | G70: =IFERROR(VLOOKUP(B70,'② Salary Input'!A:V,14,FALSE())/Settings!B6,0) -> 437.5
A71: ='① Timelog Input'!B21 -> Gaganjot | B71: ='① Timelog Input'!C21 -> CAS-IH_1159 | C71: ='① Timelog Input'!AZ$3 -> MARTIN D. EISENSTEIN, CPA | D71: ='① Timelog Input'!AZ21 -> 0 | E71: ='① Timelog Input'!H21 -> Accounting, Business Tax | F71: =IF(OR(E71="HR",E71="IT",E71="Marketing"),"YES","NO") -> NO | G71: =IFERROR(VLOOKUP(B71,'② Salary Input'!A:V,14,FALSE())/Settings!B6,0) -> 437.5
A72: ='① Timelog Input'!B21 -> Gaganjot | B72: ='① Timelog Input'!C21 -> CAS-IH_1159 | C72: ='① Timelog Input'!BC$3 -> MEJIA & ASSOCIATES, INC. | D72: ='① Timelog Input'!BC21 -> 0 | E72: ='① Timelog Input'!H21 -> Accounting, Business Tax | F72: =IF(OR(E72="HR",E72="IT",E72="Marketing"),"YES","NO") -> NO | G72: =IFERROR(VLOOKUP(B72,'② Salary Input'!A:V,14,FALSE())/Settings!B6,0) -> 437.5
A73: ='① Timelog Input'!B21 -> Gaganjot | B73: ='① Timelog Input'!C21 -> CAS-IH_1159 | C73: ='① Timelog Input'!BK$3 -> PROVISION ACCOUNTING SOLUTIONS | D73: ='① Timelog Input'!BK21 -> 0 | E73: ='① Timelog Input'!H21 -> Accounting, Business Tax | F73: =IF(OR(E73="HR",E73="IT",E73="Marketing"),"YES","NO") -> NO | G73: =IFERROR(VLOOKUP(B73,'② Salary Input'!A:V,14,FALSE())/Settings!B6,0) -> 437.5
A74: ='① Timelog Input'!B21 -> Gaganjot | B74: ='① Timelog Input'!C21 -> CAS-IH_1159 | C74: ='① Timelog Input'!BS$3 -> SOUTH FLORIDA SECURITY GROUP | D74: ='① Timelog Input'!BS21 -> 0 | E74: ='① Timelog Input'!H21 -> Accounting, Business Tax | F74: =IF(OR(E74="HR",E74="IT",E74="Marketing"),"YES","NO") -> NO | G74: =IFERROR(VLOOKUP(B74,'② Salary Input'!A:V,14,FALSE())/Settings!B6,0) -> 437.5
A75: ='① Timelog Input'!B22 -> Robin | B75: ='① Timelog Input'!C22 -> CAS-IH_1005 | C75: ='① Timelog Input'!AN$3 -> FULL COMPLIANCE, LLC | D75: ='① Timelog Input'!AN22 -> 130.25 | E75: ='① Timelog Input'!H22 -> Accounting | F75: =IF(OR(E75="HR",E75="IT",E75="Marketing"),"YES","NO") -> NO | G75: =IFERROR(VLOOKUP(B75,'② Salary Input'!A:V,14,FALSE())/Settings!B6,0) -> 437.5
A76: ='① Timelog Input'!B23 -> Nishu | B76: ='① Timelog Input'!C23 -> CAS-IH_1038 | C76: ='① Timelog Input'!S$3 -> AB CAPSTONE GROUP | D76: ='① Timelog Input'!S23 -> 0 | E76: ='① Timelog Input'!H23 -> Accounting, Business Tax, VA | F76: =IF(OR(E76="HR",E76="IT",E76="Marketing"),"YES","NO") -> NO | G76: =IFERROR(VLOOKUP(B76,'② Salary Input'!A:V,14,FALSE())/Settings!B6,0) -> 268.75
A77: ='① Timelog Input'!B24 -> Pinky | B77: ='① Timelog Input'!C24 -> CAS-RT_2045 | C77: ='① Timelog Input'!V$3 -> ACT NOW FINANCIAL SERVICES, LLC | D77: ='① Timelog Input'!V24 -> 0 | E77: ='① Timelog Input'!H24 -> Accounting | F77: =IF(OR(E77="HR",E77="IT",E77="Marketing"),"YES","NO") -> NO | G77: =IFERROR(VLOOKUP(B77,'② Salary Input'!A:V,14,FALSE())/Settings!B6,0) -> 429
A78: ='① Timelog Input'!B24 -> Pinky | B78: ='① Timelog Input'!C24 -> CAS-RT_2045 | C78: ='① Timelog Input'!AG$3 -> CHRIS WHALEN CPA, LLC | D78: ='① Timelog Input'!AG24 -> 0 | E78: ='① Timelog Input'!H24 -> Accounting | F78: =IF(OR(E78="HR",E78="IT",E78="Marketing"),"YES","NO") -> NO | G78: =IFERROR(VLOOKUP(B78,'② Salary Input'!A:V,14,FALSE())/Settings!B6,0) -> 429
A79: ='① Timelog Input'!B24 -> Pinky | B79: ='① Timelog Input'!C24 -> CAS-RT_2045 | C79: ='① Timelog Input'!AI$3 -> CLOUDIT | D79: ='① Timelog Input'!AI24 -> 0 | E79: ='① Timelog Input'!H24 -> Accounting | F79: =IF(OR(E79="HR",E79="IT",E79="Marketing"),"YES","NO") -> NO | G79: =IFERROR(VLOOKUP(B79,'② Salary Input'!A:V,14,FALSE())/Settings!B6,0) -> 429
A80: ='① Timelog Input'!B24 -> Pinky | B80: ='① Timelog Input'!C24 -> CAS-RT_2045 | C80: ='① Timelog Input'!AV$3 -> JOHNSON & ROBINSON LLC | D80: ='① Timelog Input'!AV24 -> 0 | E80: ='① Timelog Input'!H24 -> Accounting | F80: =IF(OR(E80="HR",E80="IT",E80="Marketing"),"YES","NO") -> NO | G80: =IFERROR(VLOOKUP(B80,'② Salary Input'!A:V,14,FALSE())/Settings!B6,0) -> 429
A81: ='① Timelog Input'!B24 -> Pinky | B81: ='① Timelog Input'!C24 -> CAS-RT_2045 | C81: ='① Timelog Input'!AW$3 -> LEANCORP ACCOUNTING | D81: ='① Timelog Input'!AW24 -> 0 | E81: ='① Timelog Input'!H24 -> Accounting | F81: =IF(OR(E81="HR",E81="IT",E81="Marketing"),"YES","NO") -> NO | G81: =IFERROR(VLOOKUP(B81,'② Salary Input'!A:V,14,FALSE())/Settings!B6,0) -> 429
A82: ='① Timelog Input'!B24 -> Pinky | B82: ='① Timelog Input'!C24 -> CAS-RT_2045 | C82: ='① Timelog Input'!BL$3 -> PW ADVISORS LLC | D82: ='① Timelog Input'!BL24 -> 0 | E82: ='① Timelog Input'!H24 -> Accounting | F82: =IF(OR(E82="HR",E82="IT",E82="Marketing"),"YES","NO") -> NO | G82: =IFERROR(VLOOKUP(B82,'② Salary Input'!A:V,14,FALSE())/Settings!B6,0) -> 429
A83: ='① Timelog Input'!B24 -> Pinky | B83: ='① Timelog Input'!C24 -> CAS-RT_2045 | C83: ='① Timelog Input'!BN$3 -> ROSEN KUSLANSKY CPA PC | D83: ='① Timelog Input'!BN24 -> 0 | E83: ='① Timelog Input'!H24 -> Accounting | F83: =IF(OR(E83="HR",E83="IT",E83="Marketing"),"YES","NO") -> NO | G83: =IFERROR(VLOOKUP(B83,'② Salary Input'!A:V,14,FALSE())/Settings!B6,0) -> 429
A84: ='① Timelog Input'!B24 -> Pinky | B84: ='① Timelog Input'!C24 -> CAS-RT_2045 | C84: ='① Timelog Input'!CB$3 -> WIGGS CPA TAX & ACCOUNTING | D84: ='① Timelog Input'!CB24 -> 0 | E84: ='① Timelog Input'!H24 -> Accounting | F84: =IF(OR(E84="HR",E84="IT",E84="Marketing"),"YES","NO") -> NO | G84: =IFERROR(VLOOKUP(B84,'② Salary Input'!A:V,14,FALSE())/Settings!B6,0) -> 429
A85: ='① Timelog Input'!B25 -> Preety | B85: ='① Timelog Input'!C25 -> CAS-IH_1056 | C85: ='① Timelog Input'!S$3 -> AB CAPSTONE GROUP | D85: ='① Timelog Input'!S25 -> 0 | E85: ='① Timelog Input'!H25 -> Accounting, Business Tax | F85: =IF(OR(E85="HR",E85="IT",E85="Marketing"),"YES","NO") -> NO | G85: =IFERROR(VLOOKUP(B85,'② Salary Input'!A:V,14,FALSE())/Settings!B6,0) -> 625
A86: ='① Timelog Input'!B26 -> Urvashi | B86: ='① Timelog Input'!C26 -> CAS-RT_2063 | C86: ='① Timelog Input'!AI$3 -> CLOUDIT | D86: ='① Timelog Input'!AI26 -> 0 | E86: ='① Timelog Input'!H26 -> Accounting | F86: =IF(OR(E86="HR",E86="IT",E86="Marketing"),"YES","NO") -> NO | G86: =IFERROR(VLOOKUP(B86,'② Salary Input'!A:V,14,FALSE())/Settings!B6,0) -> 158.59375
A87: ='① Timelog Input'!B26 -> Urvashi | B87: ='① Timelog Input'!C26 -> CAS-RT_2063 | C87: ='① Timelog Input'!AM$3 -> Fleming Accounting Solutions | D87: ='① Timelog Input'!AM26 -> 0 | E87: ='① Timelog Input'!H26 -> Accounting | F87: =IF(OR(E87="HR",E87="IT",E87="Marketing"),"YES","NO") -> NO | G87: =IFERROR(VLOOKUP(B87,'② Salary Input'!A:V,14,FALSE())/Settings!B6,0) -> 158.59375
A88: ='① Timelog Input'!B26 -> Urvashi | B88: ='① Timelog Input'!C26 -> CAS-RT_2063 | C88: ='① Timelog Input'!AN$3 -> FULL COMPLIANCE, LLC | D88: ='① Timelog Input'!AN26 -> 0 | E88: ='① Timelog Input'!H26 -> Accounting | F88: =IF(OR(E88="HR",E88="IT",E88="Marketing"),"YES","NO") -> NO | G88: =IFERROR(VLOOKUP(B88,'② Salary Input'!A:V,14,FALSE())/Settings!B6,0) -> 158.59375
A89: ='① Timelog Input'!B26 -> Urvashi | B89: ='① Timelog Input'!C26 -> CAS-RT_2063 | C89: ='① Timelog Input'!AT$3 -> INVENT WEALTH, CPA | D89: ='① Timelog Input'!AT26 -> 0 | E89: ='① Timelog Input'!H26 -> Accounting | F89: =IF(OR(E89="HR",E89="IT",E89="Marketing"),"YES","NO") -> NO | G89: =IFERROR(VLOOKUP(B89,'② Salary Input'!A:V,14,FALSE())/Settings!B6,0) -> 158.59375
A90: ='① Timelog Input'!B26 -> Urvashi | B90: ='① Timelog Input'!C26 -> CAS-RT_2063 | C90: ='① Timelog Input'!AU$3 -> jmWILLIAMS, CPA, LLP | D90: ='① Timelog Input'!AU26 -> 0 | E90: ='① Timelog Input'!H26 -> Accounting | F90: =IF(OR(E90="HR",E90="IT",E90="Marketing"),"YES","NO") -> NO | G90: =IFERROR(VLOOKUP(B90,'② Salary Input'!A:V,14,FALSE())/Settings!B6,0) -> 158.59375
A91: ='① Timelog Input'!B26 -> Urvashi | B91: ='① Timelog Input'!C26 -> CAS-RT_2063 | C91: ='① Timelog Input'!AZ$3 -> MARTIN D. EISENSTEIN, CPA | D91: ='① Timelog Input'!AZ26 -> 0 | E91: ='① Timelog Input'!H26 -> Accounting | F91: =IF(OR(E91="HR",E91="IT",E91="Marketing"),"YES","NO") -> NO | G91: =IFERROR(VLOOKUP(B91,'② Salary Input'!A:V,14,FALSE())/Settings!B6,0) -> 158.59375
A92: ='① Timelog Input'!B26 -> Urvashi | B92: ='① Timelog Input'!C26 -> CAS-RT_2063 | C92: ='① Timelog Input'!BC$3 -> MEJIA & ASSOCIATES, INC. | D92: ='① Timelog Input'!BC26 -> 0 | E92: ='① Timelog Input'!H26 -> Accounting | F92: =IF(OR(E92="HR",E92="IT",E92="Marketing"),"YES","NO") -> NO | G92: =IFERROR(VLOOKUP(B92,'② Salary Input'!A:V,14,FALSE())/Settings!B6,0) -> 158.59375
A93: ='① Timelog Input'!B26 -> Urvashi | B93: ='① Timelog Input'!C26 -> CAS-RT_2063 | C93: ='① Timelog Input'!BK$3 -> PROVISION ACCOUNTING SOLUTIONS | D93: ='① Timelog Input'!BK26 -> 0 | E93: ='① Timelog Input'!H26 -> Accounting | F93: =IF(OR(E93="HR",E93="IT",E93="Marketing"),"YES","NO") -> NO | G93: =IFERROR(VLOOKUP(B93,'② Salary Input'!A:V,14,FALSE())/Settings!B6,0) -> 158.59375
A94: ='① Timelog Input'!B27 -> Melita | B94: ='① Timelog Input'!C27 -> CAS-IH_1046 | C94: ='① Timelog Input'!BR$3 -> SMALLHOLD INC | D94: ='① Timelog Input'!BR27 -> 0 | E94: ='① Timelog Input'!H27 -> Individual Tax | F94: =IF(OR(E94="HR",E94="IT",E94="Marketing"),"YES","NO") -> NO | G94: =IFERROR(VLOOKUP(B94,'② Salary Input'!A:V,14,FALSE())/Settings!B6,0) -> 843.75
A95: ='① Timelog Input'!B27 -> Melita | B95: ='① Timelog Input'!C27 -> CAS-IH_1046 | C95: ='① Timelog Input'!BY$3 -> TRI SCAPES | D95: ='① Timelog Input'!BY27 -> 0 | E95: ='① Timelog Input'!H27 -> Individual Tax | F95: =IF(OR(E95="HR",E95="IT",E95="Marketing"),"YES","NO") -> NO | G95: =IFERROR(VLOOKUP(B95,'② Salary Input'!A:V,14,FALSE())/Settings!B6,0) -> 843.75
A96: ='① Timelog Input'!B28 -> Bhawna | B96: ='① Timelog Input'!C28 -> CAS-RR_2077 | C96: ='① Timelog Input'!AX$3 -> LIFETIME FUNDING, LLC | D96: ='① Timelog Input'!AX28 -> 0 | E96: ='① Timelog Input'!H28 -> Accounting | F96: =IF(OR(E96="HR",E96="IT",E96="Marketing"),"YES","NO") -> NO | G96: =IFERROR(VLOOKUP(B96,'② Salary Input'!A:V,14,FALSE())/Settings!B6,0) -> 750
A97: ='① Timelog Input'!B28 -> Bhawna | B97: ='① Timelog Input'!C28 -> CAS-RR_2077 | C97: ='① Timelog Input'!BX$3 -> TREE OF LIFE FUNDING INC | D97: ='① Timelog Input'!BX28 -> 0 | E97: ='① Timelog Input'!H28 -> Accounting | F97: =IF(OR(E97="HR",E97="IT",E97="Marketing"),"YES","NO") -> NO | G97: =IFERROR(VLOOKUP(B97,'② Salary Input'!A:V,14,FALSE())/Settings!B6,0) -> 750
A98: ='① Timelog Input'!B29 -> Anand | B98: ='① Timelog Input'!C29 -> CAS-RT_2078 | C98: ='① Timelog Input'!AG$3 -> CHRIS WHALEN CPA, LLC | D98: ='① Timelog Input'!AG29 -> 0 | E98: ='① Timelog Input'!H29 -> Accounting | F98: =IF(OR(E98="HR",E98="IT",E98="Marketing"),"YES","NO") -> NO | G98: =IFERROR(VLOOKUP(B98,'② Salary Input'!A:V,14,FALSE())/Settings!B6,0) -> 273.93125
A99: ='① Timelog Input'!B29 -> Anand | B99: ='① Timelog Input'!C29 -> CAS-RT_2078 | C99: ='① Timelog Input'!BN$3 -> ROSEN KUSLANSKY CPA PC | D99: ='① Timelog Input'!BN29 -> 0 | E99: ='① Timelog Input'!H29 -> Accounting | F99: =IF(OR(E99="HR",E99="IT",E99="Marketing"),"YES","NO") -> NO | G99: =IFERROR(VLOOKUP(B99,'② Salary Input'!A:V,14,FALSE())/Settings!B6,0) -> 273.93125
A100: ='① Timelog Input'!B30 -> Shivani | B100: ='① Timelog Input'!C30 -> CAS-RT_2102 | C100: ='① Timelog Input'!S$3 -> AB CAPSTONE GROUP | D100: ='① Timelog Input'!S30 -> 0 | E100: ='① Timelog Input'!H30 -> Accounting | F100: =IF(OR(E100="HR",E100="IT",E100="Marketing"),"YES","NO") -> NO | G100: =IFERROR(VLOOKUP(B100,'② Salary Input'!A:V,14,FALSE())/Settings!B6,0) -> 52.375
...

Sheet ⑥ Annual Performance
A1: ANNUAL PERFORMANCE SUMMARY — Last 12 Months (INPUT)
A2: Paste your 12-month aggregated data per employee here. GREEN cells = your input. GRAY cells = auto-calculated from your data.
A3: Employee ID | B3: Employee Name | C3: Emp Type | D3: Designation | E3: Department | F3: Controller | G3: Total Hours (12 Months) | H3: Billable Hours (12 Months) | I3: Non-Billable Hours | J3: Avg Monthly Utilization % | K3: # Clients Served | L3: Avg Client Satisfaction (1-5) | M3: Revenue Generated (₹ 12-Month) | N3: Revenue/Hour (₹) AUTO | O3: # Tasks Completed | P3: # Errors/ Rework | Q3: Accuracy % AUTO | R3: Tenure (Months)
A4: =IF('Employee Master'!B4="","",'Employee Master'!B4) -> CAS-IH_1070 | B4: =IF('Employee Master'!B4="","",'Employee Master'!C4) -> Ankit | C4: =IF('Employee Master'!B4="","",'Employee Master'!D4) -> In-house | D4: =IF('Employee Master'!B4="","",'Employee Master'!E4) -> Associate | E4: =IF('Employee Master'!B4="","",'Employee Master'!F4) -> Accounting | F4: =IF('Employee Master'!B4="","",'Employee Master'!G4) -> Jasleen.D | G4: 127.2 | H4: 127.2 | I4: =IF(A4="","",G4-H4) -> 0 | J4: =IF(A4="","",IF(H4=0,0,H4/(Settings!B6*12))) -> 0.06625 | K4: 3 | L4: 3.5 | M4: 0 | N4: =IF(A4="","",IF(H4=0,0,M4/H4)) -> 0 | O4: 0 | P4: 0 | Q4: =IF(A4="","",IF(O4=0,0,1-P4/O4)) -> 0 | R4: 12
A5: =IF('Employee Master'!B5="","",'Employee Master'!B5) -> CAS-IH_1092 | B5: =IF('Employee Master'!B5="","",'Employee Master'!C5) -> Astha.D | C5: =IF('Employee Master'!B5="","",'Employee Master'!D5) -> In-house | D5: =IF('Employee Master'!B5="","",'Employee Master'!E5) -> Associate | E5: =IF('Employee Master'!B5="","",'Employee Master'!F5) -> Accounting | F5: =IF('Employee Master'!B5="","",'Employee Master'!G5) -> Jasleen.D | G5: 149.8 | H5: 149.8 | I5: =IF(A5="","",G5-H5) -> 0 | J5: =IF(A5="","",IF(H5=0,0,H5/(Settings!B6*12))) -> 0.078020833 | K5: 1 | L5: 3.5 | M5: 0 | N5: =IF(A5="","",IF(H5=0,0,M5/H5)) -> 0 | O5: 0 | P5: 0 | Q5: =IF(A5="","",IF(O5=0,0,1-P5/O5)) -> 0 | R5: 12
A6: =IF('Employee Master'!B6="","",'Employee Master'!B6) -> CAS-IH_1105 | B6: =IF('Employee Master'!B6="","",'Employee Master'!C6) -> Pragati.S | C6: =IF('Employee Master'!B6="","",'Employee Master'!D6) -> In-house | D6: =IF('Employee Master'!B6="","",'Employee Master'!E6) -> Asst. Team Lead | E6: =IF('Employee Master'!B6="","",'Employee Master'!F6) -> Accounting | F6: =IF('Employee Master'!B6="","",'Employee Master'!G6) -> Jasleen.D | G6: 161 | H6: 161 | I6: =IF(A6="","",G6-H6) -> 0 | J6: =IF(A6="","",IF(H6=0,0,H6/(Settings!B6*12))) -> 0.083854167 | K6: 6 | L6: 3.5 | M6: 0 | N6: =IF(A6="","",IF(H6=0,0,M6/H6)) -> 0 | O6: 0 | P6: 0 | Q6: =IF(A6="","",IF(O6=0,0,1-P6/O6)) -> 0 | R6: 12
A7: =IF('Employee Master'!B7="","",'Employee Master'!B7) -> CAS-IH_1109 | B7: =IF('Employee Master'!B7="","",'Employee Master'!C7) -> Anshul.O | C7: =IF('Employee Master'!B7="","",'Employee Master'!D7) -> In-house | D7: =IF('Employee Master'!B7="","",'Employee Master'!E7) -> Team Lead | E7: =IF('Employee Master'!B7="","",'Employee Master'!F7) -> Accounting | F7: =IF('Employee Master'!B7="","",'Employee Master'!G7) -> Jasleen.D | G7: 152.6 | H7: 152.6 | I7: =IF(A7="","",G7-H7) -> 0 | J7: =IF(A7="","",IF(H7=0,0,H7/(Settings!B6*12))) -> 0.079479167 | K7: 10 | L7: 3.5 | M7: 0 | N7: =IF(A7="","",IF(H7=0,0,M7/H7)) -> 0 | O7: 0 | P7: 0 | Q7: =IF(A7="","",IF(O7=0,0,1-P7/O7)) -> 0 | R7: 12
A8: =IF('Employee Master'!B8="","",'Employee Master'!B8) -> CAS-IH_1122 | B8: =IF('Employee Master'!B8="","",'Employee Master'!C8) -> Shefali.B | C8: =IF('Employee Master'!B8="","",'Employee Master'!D8) -> In-house | D8: =IF('Employee Master'!B8="","",'Employee Master'!E8) -> Associate | E8: =IF('Employee Master'!B8="","",'Employee Master'!F8) -> Accounting | F8: =IF('Employee Master'!B8="","",'Employee Master'!G8) -> Jasleen.D | G8: 158.1 | H8: 158.1 | I8: =IF(A8="","",G8-H8) -> 0 | J8: =IF(A8="","",IF(H8=0,0,H8/(Settings!B6*12))) -> 0.08234375 | K8: 2 | L8: 3.5 | M8: 0 | N8: =IF(A8="","",IF(H8=0,0,M8/H8)) -> 0 | O8: 0 | P8: 0 | Q8: =IF(A8="","",IF(O8=0,0,1-P8/O8)) -> 0 | R8: 12
A9: =IF('Employee Master'!B9="","",'Employee Master'!B9) -> CAS-IH_1149 | B9: =IF('Employee Master'!B9="","",'Employee Master'!C9) -> Sandesh.H | C9: =IF('Employee Master'!B9="","",'Employee Master'!D9) -> In-house | D9: =IF('Employee Master'!B9="","",'Employee Master'!E9) -> Associate | E9: =IF('Employee Master'!B9="","",'Employee Master'!F9) -> Accounting | F9: =IF('Employee Master'!B9="","",'Employee Master'!G9) -> Jasleen.D | G9: 176.1 | H9: 176.1 | I9: =IF(A9="","",G9-H9) -> 0 | J9: =IF(A9="","",IF(H9=0,0,H9/(Settings!B6*12))) -> 0.09171875 | K9: 2 | L9: 3.5 | M9: 0 | N9: =IF(A9="","",IF(H9=0,0,M9/H9)) -> 0 | O9: 0 | P9: 0 | Q9: =IF(A9="","",IF(O9=0,0,1-P9/O9)) -> 0 | R9: 12
A10: =IF('Employee Master'!B10="","",'Employee Master'!B10) -> CAS-IH_1162 | B10: =IF('Employee Master'!B10="","",'Employee Master'!C10) -> Robin.S | C10: =IF('Employee Master'!B10="","",'Employee Master'!D10) -> Remote | D10: =IF('Employee Master'!B10="","",'Employee Master'!E10) -> Associate | E10: =IF('Employee Master'!B10="","",'Employee Master'!F10) -> Accounting | F10: =IF('Employee Master'!B10="","",'Employee Master'!G10) -> Jasleen.D | G10: 121.5 | H10: 121.5 | I10: =IF(A10="","",G10-H10) -> 0 | J10: =IF(A10="","",IF(H10=0,0,H10/(Settings!B6*12))) -> 0.06328125 | K10: 2 | L10: 3.5 | M10: 0 | N10: =IF(A10="","",IF(H10=0,0,M10/H10)) -> 0 | O10: 0 | P10: 0 | Q10: =IF(A10="","",IF(O10=0,0,1-P10/O10)) -> 0 | R10: 12
A11: =IF('Employee Master'!B11="","",'Employee Master'!B11) -> CAS-RR_2371 | B11: =IF('Employee Master'!B11="","",'Employee Master'!C11) -> Vijet.B | C11: =IF('Employee Master'!B11="","",'Employee Master'!D11) -> Remote | D11: =IF('Employee Master'!B11="","",'Employee Master'!E11) -> Associate | E11: =IF('Employee Master'!B11="","",'Employee Master'!F11) -> Accounting | F11: =IF('Employee Master'!B11="","",'Employee Master'!G11) -> Jasleen.D | G11: 151 | H11: 151 | I11: =IF(A11="","",G11-H11) -> 0 | J11: =IF(A11="","",IF(H11=0,0,H11/(Settings!B6*12))) -> 0.078645833 | K11: 3 | L11: 3.5 | M11: 0 | N11: =IF(A11="","",IF(H11=0,0,M11/H11)) -> 0 | O11: 0 | P11: 0 | Q11: =IF(A11="","",IF(O11=0,0,1-P11/O11)) -> 0 | R11: 12
A12: =IF('Employee Master'!B12="","",'Employee Master'!B12) -> CAS-IH_1169 | B12: =IF('Employee Master'!B12="","",'Employee Master'!C12) -> Somya.B | C12: =IF('Employee Master'!B12="","",'Employee Master'!D12) -> Retainer | D12: =IF('Employee Master'!B12="","",'Employee Master'!E12) -> Sr. Associate | E12: =IF('Employee Master'!B12="","",'Employee Master'!F12) -> Accounting | F12: =IF('Employee Master'!B12="","",'Employee Master'!G12) -> Jasleen.D | G12: 160 | H12: 160 | I12: =IF(A12="","",G12-H12) -> 0 | J12: =IF(A12="","",IF(H12=0,0,H12/(Settings!B6*12))) -> 0.083333333 | K12: 2 | L12: 3.5 | M12: 0 | N12: =IF(A12="","",IF(H12=0,0,M12/H12)) -> 0 | O12: 0 | P12: 0 | Q12: =IF(A12="","",IF(O12=0,0,1-P12/O12)) -> 0 | R12: 12
A13: =IF('Employee Master'!B13="","",'Employee Master'!B13) -> CAS-IH_1069 | B13: =IF('Employee Master'!B13="","",'Employee Master'!C13) -> Jasleen.D | C13: =IF('Employee Master'!B13="","",'Employee Master'!D13) -> In-house | D13: =IF('Employee Master'!B13="","",'Employee Master'!E13) -> Controller | E13: =IF('Employee Master'!B13="","",'Employee Master'!F13) -> Accounting | F13: =IF('Employee Master'!B13="","",'Employee Master'!G13) -> -- | G13: 140 | H13: 140 | I13: =IF(A13="","",G13-H13) -> 0 | J13: =IF(A13="","",IF(H13=0,0,H13/(Settings!B6*12))) -> 0.072916667 | K13: 16 | L13: 3.5 | M13: 0 | N13: =IF(A13="","",IF(H13=0,0,M13/H13)) -> 0 | O13: 0 | P13: 0 | Q13: =IF(A13="","",IF(O13=0,0,1-P13/O13)) -> 0 | R13: 12
A14: =IF('Employee Master'!B14="","",'Employee Master'!B14) -> CAS-IH_1037 | B14: =IF('Employee Master'!B14="","",'Employee Master'!C14) -> Jyoti | C14: =IF('Employee Master'!B14="","",'Employee Master'!D14) -> In-house | D14: =IF('Employee Master'!B14="","",'Employee Master'!E14) -> Controller | E14: =IF('Employee Master'!B14="","",'Employee Master'!F14) -> Accounting, Business Tax, VA | F14: =IF('Employee Master'!B14="","",'Employee Master'!G14) -> -- | G14: 109.2 | H14: 109.2 | I14: =IF(A14="","",G14-H14) -> 0 | J14: =IF(A14="","",IF(H14=0,0,H14/(Settings!B6*12))) -> 0.056875 | K14: 4 | L14: 3.5 | M14: 0 | N14: =IF(A14="","",IF(H14=0,0,M14/H14)) -> 0 | O14: 0 | P14: 0 | Q14: =IF(A14="","",IF(O14=0,0,1-P14/O14)) -> 0 | R14: 12
A15: =IF('Employee Master'!B15="","",'Employee Master'!B15) -> CAS-IH_1018 | B15: =IF('Employee Master'!B15="","",'Employee Master'!C15) -> Vini | C15: =IF('Employee Master'!B15="","",'Employee Master'!D15) -> In-house | D15: =IF('Employee Master'!B15="","",'Employee Master'!E15) -> Controller | E15: =IF('Employee Master'!B15="","",'Employee Master'!F15) -> HR | F15: =IF('Employee Master'!B15="","",'Employee Master'!G15) -> -- | G15: 45 | H15: 45 | I15: =IF(A15="","",G15-H15) -> 0 | J15: =IF(A15="","",IF(H15=0,0,H15/(Settings!B6*12))) -> 0.0234375 | K15: 1 | L15: 3.5 | M15: 0 | N15: =IF(A15="","",IF(H15=0,0,M15/H15)) -> 0 | O15: 0 | P15: 0 | Q15: =IF(A15="","",IF(O15=0,0,1-P15/O15)) -> 0 | R15: 12
A16: =IF('Employee Master'!B16="","",'Employee Master'!B16) -> CAS-IH_1049 | B16: =IF('Employee Master'!B16="","",'Employee Master'!C16) -> Asmita | C16: =IF('Employee Master'!B16="","",'Employee Master'!D16) -> In-house | D16: =IF('Employee Master'!B16="","",'Employee Master'!E16) -> Sr. Associate | E16: =IF('Employee Master'!B16="","",'Employee Master'!F16) -> Accounting, Business Tax | F16: =IF('Employee Master'!B16="","",'Employee Master'!G16) -> Jyoti | G16: 91.8 | H16: 91.8 | I16: =IF(A16="","",G16-H16) -> 0 | J16: =IF(A16="","",IF(H16=0,0,H16/(Settings!B6*12))) -> 0.0478125 | K16: 5 | L16: 3.5 | M16: 0 | N16: =IF(A16="","",IF(H16=0,0,M16/H16)) -> 0 | O16: 0 | P16: 0 | Q16: =IF(A16="","",IF(O16=0,0,1-P16/O16)) -> 0 | R16: 12
A17: =IF('Employee Master'!B17="","",'Employee Master'!B17) -> CAS-IH_1041 | B17: =IF('Employee Master'!B17="","",'Employee Master'!C17) -> Nikita | C17: =IF('Employee Master'!B17="","",'Employee Master'!D17) -> In-house | D17: =IF('Employee Master'!B17="","",'Employee Master'!E17) -> Controller | E17: =IF('Employee Master'!B17="","",'Employee Master'!F17) -> Accounting, Business Tax, VA, L&D | F17: =IF('Employee Master'!B17="","",'Employee Master'!G17) -> -- | G17: 75 | H17: 75 | I17: =IF(A17="","",G17-H17) -> 0 | J17: =IF(A17="","",IF(H17=0,0,H17/(Settings!B6*12))) -> 0.0390625 | K17: 10 | L17: 3.5 | M17: 0 | N17: =IF(A17="","",IF(H17=0,0,M17/H17)) -> 0 | O17: 0 | P17: 0 | Q17: =IF(A17="","",IF(O17=0,0,1-P17/O17)) -> 0 | R17: 12
A18: =IF('Employee Master'!B18="","",'Employee Master'!B18) -> CAS-IH_1051 | B18: =IF('Employee Master'!B18="","",'Employee Master'!C18) -> Ayushi | C18: =IF('Employee Master'!B18="","",'Employee Master'!D18) -> In-house | D18: =IF('Employee Master'!B18="","",'Employee Master'!E18) -> Asst. Controller | E18: =IF('Employee Master'!B18="","",'Employee Master'!F18) -> Accounting, Business Tax | F18: =IF('Employee Master'!B18="","",'Employee Master'!G18) -> -- | G18: 23 | H18: 23 | I18: =IF(A18="","",G18-H18) -> 0 | J18: =IF(A18="","",IF(H18=0,0,H18/(Settings!B6*12))) -> 0.011979167 | K18: 3 | L18: 3.5 | M18: 0 | N18: =IF(A18="","",IF(H18=0,0,M18/H18)) -> 0 | O18: 0 | P18: 0 | Q18: =IF(A18="","",IF(O18=0,0,1-P18/O18)) -> 0 | R18: 12
A19: =IF('Employee Master'!B19="","",'Employee Master'!B19) -> CAS-IH_1065 | B19: =IF('Employee Master'!B19="","",'Employee Master'!C19) -> Shefali | C19: =IF('Employee Master'!B19="","",'Employee Master'!D19) -> In-house | D19: =IF('Employee Master'!B19="","",'Employee Master'!E19) -> Team Lead | E19: =IF('Employee Master'!B19="","",'Employee Master'!F19) -> Accounting | F19: =IF('Employee Master'!B19="","",'Employee Master'!G19) -> Nikita Shah | G19: 105.5 | H19: 105.5 | I19: =IF(A19="","",G19-H19) -> 0 | J19: =IF(A19="","",IF(H19=0,0,H19/(Settings!B6*12))) -> 0.054947917 | K19: 8 | L19: 3.5 | M19: 0 | N19: =IF(A19="","",IF(H19=0,0,M19/H19)) -> 0 | O19: 0 | P19: 0 | Q19: =IF(A19="","",IF(O19=0,0,1-P19/O19)) -> 0 | R19: 12
A20: =IF('Employee Master'!B20="","",'Employee Master'!B20) -> CAS-IH_1077 | B20: =IF('Employee Master'!B20="","",'Employee Master'!C20) -> Rashi | C20: =IF('Employee Master'!B20="","",'Employee Master'!D20) -> In-house | D20: =IF('Employee Master'!B20="","",'Employee Master'!E20) -> Asst. Manager | E20: =IF('Employee Master'!B20="","",'Employee Master'!F20) -> HR | F20: =IF('Employee Master'!B20="","",'Employee Master'!G20) -> Vinita Dagar | G20: 0 | H20: 0 | I20: =IF(A20="","",G20-H20) -> 0 | J20: =IF(A20="","",IF(H20=0,0,H20/(Settings!B6*12))) -> 0 | K20: 0 | L20: 3.5 | M20: 0 | N20: =IF(A20="","",IF(H20=0,0,M20/H20)) -> 0 | O20: 0 | P20: 0 | Q20: =IF(A20="","",IF(O20=0,0,1-P20/O20)) -> 0 | R20: 12
A21: =IF('Employee Master'!B21="","",'Employee Master'!B21) -> CAS-IH_1159 | B21: =IF('Employee Master'!B21="","",'Employee Master'!C21) -> Gaganjot | C21: =IF('Employee Master'!B21="","",'Employee Master'!D21) -> In-house | D21: =IF('Employee Master'!B21="","",'Employee Master'!E21) -> Asst. Team Lead | E21: =IF('Employee Master'!B21="","",'Employee Master'!F21) -> Accounting, Business Tax | F21: =IF('Employee Master'!B21="","",'Employee Master'!G21) -> Nikita Shah | G21: 82.8 | H21: 82.8 | I21: =IF(A21="","",G21-H21) -> 0 | J21: =IF(A21="","",IF(H21=0,0,H21/(Settings!B6*12))) -> 0.043125 | K21: 5 | L21: 3.5 | M21: 0 | N21: =IF(A21="","",IF(H21=0,0,M21/H21)) -> 0 | O21: 0 | P21: 0 | Q21: =IF(A21="","",IF(O21=0,0,1-P21/O21)) -> 0 | R21: 12
A22: =IF('Employee Master'!B22="","",'Employee Master'!B22) -> CAS-IH_1005 | B22: =IF('Employee Master'!B22="","",'Employee Master'!C22) -> Robin | C22: =IF('Employee Master'!B22="","",'Employee Master'!D22) -> In-house | D22: =IF('Employee Master'!B22="","",'Employee Master'!E22) -> Sr. Associate | E22: =IF('Employee Master'!B22="","",'Employee Master'!F22) -> Accounting | F22: =IF('Employee Master'!B22="","",'Employee Master'!G22) -> Jyoti | G22: 158.8 | H22: 158.8 | I22: =IF(A22="","",G22-H22) -> 0 | J22: =IF(A22="","",IF(H22=0,0,H22/(Settings!B6*12))) -> 0.082708333 | K22: 5 | L22: 3.5 | M22: 0 | N22: =IF(A22="","",IF(H22=0,0,M22/H22)) -> 0 | O22: 0 | P22: 0 | Q22: =IF(A22="","",IF(O22=0,0,1-P22/O22)) -> 0 | R22: 12
A23: =IF('Employee Master'!B23="","",'Employee Master'!B23) -> CAS-IH_1038 | B23: =IF('Employee Master'!B23="","",'Employee Master'!C23) -> Nishu | C23: =IF('Employee Master'!B23="","",'Employee Master'!D23) -> In-house | D23: =IF('Employee Master'!B23="","",'Employee Master'!E23) -> Associate | E23: =IF('Employee Master'!B23="","",'Employee Master'!F23) -> Accounting, Business Tax, VA | F23: =IF('Employee Master'!B23="","",'Employee Master'!G23) -> Jyoti | G23: 156.1 | H23: 156.1 | I23: =IF(A23="","",G23-H23) -> 0 | J23: =IF(A23="","",IF(H23=0,0,H23/(Settings!B6*12))) -> 0.081302083 | K23: 1 | L23: 3.5 | M23: 0 | N23: =IF(A23="","",IF(H23=0,0,M23/H23)) -> 0 | O23: 0 | P23: 0 | Q23: =IF(A23="","",IF(O23=0,0,1-P23/O23)) -> 0 | R23: 12
A24: =IF('Employee Master'!B24="","",'Employee Master'!B24) -> CAS-RT_2045 | B24: =IF('Employee Master'!B24="","",'Employee Master'!C24) -> Pinky | C24: =IF('Employee Master'!B24="","",'Employee Master'!D24) -> Remote | D24: =IF('Employee Master'!B24="","",'Employee Master'!E24) -> Manager | E24: =IF('Employee Master'!B24="","",'Employee Master'!F24) -> Accounting | F24: =IF('Employee Master'!B24="","",'Employee Master'!G24) -> Nikita Shah | G24: 96.6 | H24: 96.6 | I24: =IF(A24="","",G24-H24) -> 0 | J24: =IF(A24="","",IF(H24=0,0,H24/(Settings!B6*12))) -> 0.0503125 | K24: 1 | L24: 3.5 | M24: 0 | N24: =IF(A24="","",IF(H24=0,0,M24/H24)) -> 0 | O24: 0 | P24: 0 | Q24: =IF(A24="","",IF(O24=0,0,1-P24/O24)) -> 0 | R24: 12
A25: =IF('Employee Master'!B25="","",'Employee Master'!B25) -> CAS-IH_1056 | B25: =IF('Employee Master'!B25="","",'Employee Master'!C25) -> Preety | C25: =IF('Employee Master'!B25="","",'Employee Master'!D25) -> In-house | D25: =IF('Employee Master'!B25="","",'Employee Master'!E25) -> Team Lead | E25: =IF('Employee Master'!B25="","",'Employee Master'!F25) -> Accounting, Business Tax | F25: =IF('Employee Master'!B25="","",'Employee Master'!G25) -> Nikita Shah | G25: 88.5 | H25: 88.5 | I25: =IF(A25="","",G25-H25) -> 0 | J25: =IF(A25="","",IF(H25=0,0,H25/(Settings!B6*12))) -> 0.04609375 | K25: 8 | L25: 3.5 | M25: 0 | N25: =IF(A25="","",IF(H25=0,0,M25/H25)) -> 0 | O25: 0 | P25: 0 | Q25: =IF(A25="","",IF(O25=0,0,1-P25/O25)) -> 0 | R25: 12
A26: =IF('Employee Master'!B26="","",'Employee Master'!B26) -> CAS-RT_2063 | B26: =IF('Employee Master'!B26="","",'Employee Master'!C26) -> Urvashi | C26: =IF('Employee Master'!B26="","",'Employee Master'!D26) -> Remote | D26: =IF('Employee Master'!B26="","",'Employee Master'!E26) -> Associate | E26: =IF('Employee Master'!B26="","",'Employee Master'!F26) -> Accounting | F26: =IF('Employee Master'!B26="","",'Employee Master'!G26) -> Nikita Shah | G26: 101.5 | H26: 101.5 | I26: =IF(A26="","",G26-H26) -> 0 | J26: =IF(A26="","",IF(H26=0,0,H26/(Settings!B6*12))) -> 0.052864583 | K26: 1 | L26: 3.5 | M26: 0 | N26: =IF(A26="","",IF(H26=0,0,M26/H26)) -> 0 | O26: 0 | P26: 0 | Q26: =IF(A26="","",IF(O26=0,0,1-P26/O26)) -> 0 | R26: 12
A27: =IF('Employee Master'!B27="","",'Employee Master'!B27) -> CAS-IH_1046 | B27: =IF('Employee Master'!B27="","",'Employee Master'!C27) -> Melita | C27: =IF('Employee Master'!B27="","",'Employee Master'!D27) -> In-house | D27: =IF('Employee Master'!B27="","",'Employee Master'!E27) -> Team Lead | E27: =IF('Employee Master'!B27="","",'Employee Master'!F27) -> Individual Tax | F27: =IF('Employee Master'!B27="","",'Employee Master'!G27) -> Smriti Shah | G27: 150.8 | H27: 150.8 | I27: =IF(A27="","",G27-H27) -> 0 | J27: =IF(A27="","",IF(H27=0,0,H27/(Settings!B6*12))) -> 0.078541667 | K27: 7 | L27: 3.5 | M27: 0 | N27: =IF(A27="","",IF(H27=0,0,M27/H27)) -> 0 | O27: 0 | P27: 0 | Q27: =IF(A27="","",IF(O27=0,0,1-P27/O27)) -> 0 | R27: 12
A28: =IF('Employee Master'!B28="","",'Employee Master'!B28) -> CAS-RR_2077 | B28: =IF('Employee Master'!B28="","",'Employee Master'!C28) -> Bhawna | C28: =IF('Employee Master'!B28="","",'Employee Master'!D28) -> Retainer | D28: =IF('Employee Master'!B28="","",'Employee Master'!E28) -> Manager | E28: =IF('Employee Master'!B28="","",'Employee Master'!F28) -> Accounting | F28: =IF('Employee Master'!B28="","",'Employee Master'!G28) -> Jyoti | G28: 162.4 | H28: 162.4 | I28: =IF(A28="","",G28-H28) -> 0 | J28: =IF(A28="","",IF(H28=0,0,H28/(Settings!B6*12))) -> 0.084583333 | K28: 2 | L28: 3.5 | M28: 0 | N28: =IF(A28="","",IF(H28=0,0,M28/H28)) -> 0 | O28: 0 | P28: 0 | Q28: =IF(A28="","",IF(O28=0,0,1-P28/O28)) -> 0 | R28: 12
A29: =IF('Employee Master'!B29="","",'Employee Master'!B29) -> CAS-RT_2078 | B29: =IF('Employee Master'!B29="","",'Employee Master'!C29) -> Anand | C29: =IF('Employee Master'!B29="","",'Employee Master'!D29) -> Remote | D29: =IF('Employee Master'!B29="","",'Employee Master'!E29) -> Associate | E29: =IF('Employee Master'!B29="","",'Employee Master'!F29) -> Accounting | F29: =IF('Employee Master'!B29="","",'Employee Master'!G29) -> Nikita Shah | G29: 155.3 | H29: 155.3 | I29: =IF(A29="","",G29-H29) -> 0 | J29: =IF(A29="","",IF(H29=0,0,H29/(Settings!B6*12))) -> 0.080885417 | K29: 2 | L29: 3.5 | M29: 0 | N29: =IF(A29="","",IF(H29=0,0,M29/H29)) -> 0 | O29: 0 | P29: 0 | Q29: =IF(A29="","",IF(O29=0,0,1-P29/O29)) -> 0 | R29: 12
A30: =IF('Employee Master'!B30="","",'Employee Master'!B30) -> CAS-RT_2102 | B30: =IF('Employee Master'!B30="","",'Employee Master'!C30) -> Shivani | C30: =IF('Employee Master'!B30="","",'Employee Master'!D30) -> Remote | D30: =IF('Employee Master'!B30="","",'Employee Master'!E30) -> Associate | E30: =IF('Employee Master'!B30="","",'Employee Master'!F30) -> Accounting | F30: =IF('Employee Master'!B30="","",'Employee Master'!G30) -> Nikita Shah | G30: 55.9 | H30: 55.9 | I30: =IF(A30="","",G30-H30) -> 0 | J30: =IF(A30="","",IF(H30=0,0,H30/(Settings!B6*12))) -> 0.029114583 | K30: 2 | L30: 3.5 | M30: 0 | N30: =IF(A30="","",IF(H30=0,0,M30/H30)) -> 0 | O30: 0 | P30: 0 | Q30: =IF(A30="","",IF(O30=0,0,1-P30/O30)) -> 0 | R30: 12
A31: =IF('Employee Master'!B31="","",'Employee Master'!B31) -> CAS-RT_2108 | B31: =IF('Employee Master'!B31="","",'Employee Master'!C31) -> Sreeja | C31: =IF('Employee Master'!B31="","",'Employee Master'!D31) -> Remote | D31: =IF('Employee Master'!B31="","",'Employee Master'!E31) -> Manager | E31: =IF('Employee Master'!B31="","",'Employee Master'!F31) -> Accounting | F31: =IF('Employee Master'!B31="","",'Employee Master'!G31) -> Nikita Shah | G31: 105.4 | H31: 105.4 | I31: =IF(A31="","",G31-H31) -> 0 | J31: =IF(A31="","",IF(H31=0,0,H31/(Settings!B6*12))) -> 0.054895833 | K31: 1 | L31: 3.5 | M31: 0 | N31: =IF(A31="","",IF(H31=0,0,M31/H31)) -> 0 | O31: 0 | P31: 0 | Q31: =IF(A31="","",IF(O31=0,0,1-P31/O31)) -> 0 | R31: 12
A32: =IF('Employee Master'!B32="","",'Employee Master'!B32) -> CAS-RT_2113 | B32: =IF('Employee Master'!B32="","",'Employee Master'!C32) -> Divya.M | C32: =IF('Employee Master'!B32="","",'Employee Master'!D32) -> Remote | D32: =IF('Employee Master'!B32="","",'Employee Master'!E32) -> Manager | E32: =IF('Employee Master'!B32="","",'Employee Master'!F32) -> Accounting | F32: =IF('Employee Master'!B32="","",'Employee Master'!G32) -> Nikita Shah | G32: 98 | H32: 98 | I32: =IF(A32="","",G32-H32) -> 0 | J32: =IF(A32="","",IF(H32=0,0,H32/(Settings!B6*12))) -> 0.051041667 | K32: 3 | L32: 3.5 | M32: 0 | N32: =IF(A32="","",IF(H32=0,0,M32/H32)) -> 0 | O32: 0 | P32: 0 | Q32: =IF(A32="","",IF(O32=0,0,1-P32/O32)) -> 0 | R32: 12
A33: =IF('Employee Master'!B33="","",'Employee Master'!B33) -> CAS-IH_1102 | B33: =IF('Employee Master'!B33="","",'Employee Master'!C33) -> Kritika | C33: =IF('Employee Master'!B33="","",'Employee Master'!D33) -> In-house | D33: =IF('Employee Master'!B33="","",'Employee Master'!E33) -> Manager | E33: =IF('Employee Master'!B33="","",'Employee Master'!F33) -> FP&A | F33: =IF('Employee Master'!B33="","",'Employee Master'!G33) -> Sachi Mazumdar | G33: 147 | H33: 147 | I33: =IF(A33="","",G33-H33) -> 0 | J33: =IF(A33="","",IF(H33=0,0,H33/(Settings!B6*12))) -> 0.0765625 | K33: 1 | L33: 3.5 | M33: 0 | N33: =IF(A33="","",IF(H33=0,0,M33/H33)) -> 0 | O33: 0 | P33: 0 | Q33: =IF(A33="","",IF(O33=0,0,1-P33/O33)) -> 0 | R33: 12
A34: =IF('Employee Master'!B34="","",'Employee Master'!B34) -> CAS-IH_1061 | B34: =IF('Employee Master'!B34="","",'Employee Master'!C34) -> Abhilash | C34: =IF('Employee Master'!B34="","",'Employee Master'!D34) -> In-house | D34: =IF('Employee Master'!B34="","",'Employee Master'!E34) -> Sr. Associate | E34: =IF('Employee Master'!B34="","",'Employee Master'!F34) -> Individual Tax | F34: =IF('Employee Master'!B34="","",'Employee Master'!G34) -> Smriti Shah | G34: 59.8 | H34: 59.8 | I34: =IF(A34="","",G34-H34) -> 0 | J34: =IF(A34="","",IF(H34=0,0,H34/(Settings!B6*12))) -> 0.031145833 | K34: 5 | L34: 3.5 | M34: 0 | N34: =IF(A34="","",IF(H34=0,0,M34/H34)) -> 0 | O34: 0 | P34: 0 | Q34: =IF(A34="","",IF(O34=0,0,1-P34/O34)) -> 0 | R34: 12
A35: =IF('Employee Master'!B35="","",'Employee Master'!B35) -> CAS-IH_1108 | B35: =IF('Employee Master'!B35="","",'Employee Master'!C35) -> Kavita | C35: =IF('Employee Master'!B35="","",'Employee Master'!D35) -> In-house | D35: =IF('Employee Master'!B35="","",'Employee Master'!E35) -> Manager | E35: =IF('Employee Master'!B35="","",'Employee Master'!F35) -> FP&A | F35: =IF('Employee Master'!B35="","",'Employee Master'!G35) -> Sachi Mazumdar | G35: 48 | H35: 48 | I35: =IF(A35="","",G35-H35) -> 0 | J35: =IF(A35="","",IF(H35=0,0,H35/(Settings!B6*12))) -> 0.025 | K35: 1 | L35: 3.5 | M35: 0 | N35: =IF(A35="","",IF(H35=0,0,M35/H35)) -> 0 | O35: 0 | P35: 0 | Q35: =IF(A35="","",IF(O35=0,0,1-P35/O35)) -> 0 | R35: 12
A36: =IF('Employee Master'!B36="","",'Employee Master'!B36) -> CAS-IH_1078 | B36: =IF('Employee Master'!B36="","",'Employee Master'!C36) -> Sakshi | C36: =IF('Employee Master'!B36="","",'Employee Master'!D36) -> In-house | D36: =IF('Employee Master'!B36="","",'Employee Master'!E36) -> Associate | E36: =IF('Employee Master'!B36="","",'Employee Master'!F36) -> Accounting | F36: =IF('Employee Master'!B36="","",'Employee Master'!G36) -> Nikita Shah | G36: 135.2 | H36: 135.2 | I36: =IF(A36="","",G36-H36) -> 0 | J36: =IF(A36="","",IF(H36=0,0,H36/(Settings!B6*12))) -> 0.070416667 | K36: 1 | L36: 3.5 | M36: 0 | N36: =IF(A36="","",IF(H36=0,0,M36/H36)) -> 0 | O36: 0 | P36: 0 | Q36: =IF(A36="","",IF(O36=0,0,1-P36/O36)) -> 0 | R36: 12
A37: =IF('Employee Master'!B37="","",'Employee Master'!B37) -> CAS-RR_2370 | B37: =IF('Employee Master'!B37="","",'Employee Master'!C37) -> Suhani | C37: =IF('Employee Master'!B37="","",'Employee Master'!D37) -> Retainer | D37: =IF('Employee Master'!B37="","",'Employee Master'!E37) -> Team Lead | E37: =IF('Employee Master'!B37="","",'Employee Master'!F37) -> Accounting | F37: =IF('Employee Master'!B37="","",'Employee Master'!G37) -> Ayushi | G37: 165 | H37: 165 | I37: =IF(A37="","",G37-H37) -> 0 | J37: =IF(A37="","",IF(H37=0,0,H37/(Settings!B6*12))) -> 0.0859375 | K37: 10 | L37: 3.5 | M37: 0 | N37: =IF(A37="","",IF(H37=0,0,M37/H37)) -> 0 | O37: 0 | P37: 0 | Q37: =IF(A37="","",IF(O37=0,0,1-P37/O37)) -> 0 | R37: 12
A38: =IF('Employee Master'!B38="","",'Employee Master'!B38) -> CAS-IH_1082 | B38: =IF('Employee Master'!B38="","",'Employee Master'!C38) -> Shradha | C38: =IF('Employee Master'!B38="","",'Employee Master'!D38) -> In-house | D38: =IF('Employee Master'!B38="","",'Employee Master'!E38) -> Sr. Associate | E38: =IF('Employee Master'!B38="","",'Employee Master'!F38) -> Accounting | F38: =IF('Employee Master'!B38="","",'Employee Master'!G38) -> Jyoti | G38: 150.6 | H38: 150.6 | I38: =IF(A38="","",G38-H38) -> 0 | J38: =IF(A38="","",IF(H38=0,0,H38/(Settings!B6*12))) -> 0.0784375 | K38: 2 | L38: 3.5 | M38: 0 | N38: =IF(A38="","",IF(H38=0,0,M38/H38)) -> 0 | O38: 0 | P38: 0 | Q38: =IF(A38="","",IF(O38=0,0,1-P38/O38)) -> 0 | R38: 12
A39: =IF('Employee Master'!B39="","",'Employee Master'!B39) -> CAS-IH_1146 | B39: =IF('Employee Master'!B39="","",'Employee Master'!C39) -> Ridhi.G | C39: =IF('Employee Master'!B39="","",'Employee Master'!D39) -> In-house | D39: =IF('Employee Master'!B39="","",'Employee Master'!E39) -> Asst. Team Lead | E39: =IF('Employee Master'!B39="","",'Employee Master'!F39) -> Accounting, Business Tax | F39: =IF('Employee Master'!B39="","",'Employee Master'!G39) -> Nikita Shah | G39: 136 | H39: 136 | I39: =IF(A39="","",G39-H39) -> 0 | J39: =IF(A39="","",IF(H39=0,0,H39/(Settings!B6*12))) -> 0.070833333 | K39: 4 | L39: 3.5 | M39: 0 | N39: =IF(A39="","",IF(H39=0,0,M39/H39)) -> 0 | O39: 0 | P39: 0 | Q39: =IF(A39="","",IF(O39=0,0,1-P39/O39)) -> 0 | R39: 12
A40: =IF('Employee Master'!B40="","",'Employee Master'!B40) -> CAS-IH_1160 | B40: =IF('Employee Master'!B40="","",'Employee Master'!C40) -> Bhairavi.M | C40: =IF('Employee Master'!B40="","",'Employee Master'!D40) -> In-house | D40: =IF('Employee Master'!B40="","",'Employee Master'!E40) -> Associate | E40: =IF('Employee Master'!B40="","",'Employee Master'!F40) -> Accounting | F40: =IF('Employee Master'!B40="","",'Employee Master'!G40) -> Ayushi | G40: 110.1 | H40: 110.1 | I40: =IF(A40="","",G40-H40) -> 0 | J40: =IF(A40="","",IF(H40=0,0,H40/(Settings!B6*12))) -> 0.05734375 | K40: 5 | L40: 3.5 | M40: 0 | N40: =IF(A40="","",IF(H40=0,0,M40/H40)) -> 0 | O40: 0 | P40: 0 | Q40: =IF(A40="","",IF(O40=0,0,1-P40/O40)) -> 0 | R40: 12
A41: =IF('Employee Master'!B41="","",'Employee Master'!B41) -> CAS-IH_1150 | B41: =IF('Employee Master'!B41="","",'Employee Master'!C41) -> Ujjwal.J | C41: =IF('Employee Master'!B41="","",'Employee Master'!D41) -> In-house | D41: =IF('Employee Master'!B41="","",'Employee Master'!E41) -> Associate | E41: =IF('Employee Master'!B41="","",'Employee Master'!F41) -> Accounting, Business Tax | F41: =IF('Employee Master'!B41="","",'Employee Master'!G41) -> Nikita Shah | G41: 164.2 | H41: 164.2 | I41: =IF(A41="","",G41-H41) -> 0 | J41: =IF(A41="","",IF(H41=0,0,H41/(Settings!B6*12))) -> 0.085520833 | K41: 2 | L41: 3.5 | M41: 0 | N41: =IF(A41="","",IF(H41=0,0,M41/H41)) -> 0 | O41: 0 | P41: 0 | Q41: =IF(A41="","",IF(O41=0,0,1-P41/O41)) -> 0 | R41: 12
A42: =IF('Employee Master'!B42="","",'Employee Master'!B42) -> CAS-RR_2253 | B42: =IF('Employee Master'!B42="","",'Employee Master'!C42) -> Sukhmeen.K | C42: =IF('Employee Master'!B42="","",'Employee Master'!D42) -> Retainer | D42: =IF('Employee Master'!B42="","",'Employee Master'!E42) -> Manager | E42: =IF('Employee Master'!B42="","",'Employee Master'!F42) -> Accounting | F42: =IF('Employee Master'!B42="","",'Employee Master'!G42) -> Ayushi | G42: 131.2 | H42: 131.2 | I42: =IF(A42="","",G42-H42) -> 0 | J42: =IF(A42="","",IF(H42=0,0,H42/(Settings!B6*12))) -> 0.068333333 | K42: 5 | L42: 3.5 | M42: 0 | N42: =IF(A42="","",IF(H42=0,0,M42/H42)) -> 0 | O42: 0 | P42: 0 | Q42: =IF(A42="","",IF(O42=0,0,1-P42/O42)) -> 0 | R42: 12
A43: =IF('Employee Master'!B43="","",'Employee Master'!B43) -> CAS-IH_1111 | B43: =IF('Employee Master'!B43="","",'Employee Master'!C43) -> Tanisha.J | C43: =IF('Employee Master'!B43="","",'Employee Master'!D43) -> In-house | D43: =IF('Employee Master'!B43="","",'Employee Master'!E43) -> Associate | E43: =IF('Employee Master'!B43="","",'Employee Master'!F43) -> HR | F43: =IF('Employee Master'!B43="","",'Employee Master'!G43) -> Vinita Dagar | G43: 146.5 | H43: 146.5 | I43: =IF(A43="","",G43-H43) -> 0 | J43: =IF(A43="","",IF(H43=0,0,H43/(Settings!B6*12))) -> 0.076302083 | K43: 9 | L43: 3.5 | M43: 0 | N43: =IF(A43="","",IF(H43=0,0,M43/H43)) -> 0 | O43: 0 | P43: 0 | Q43: =IF(A43="","",IF(O43=0,0,1-P43/O43)) -> 0 | R43: 12
A44: =IF('Employee Master'!B44="","",'Employee Master'!B44) -> CAS-IH_1113 | B44: =IF('Employee Master'!B44="","",'Employee Master'!C44) -> Disha.M | C44: =IF('Employee Master'!B44="","",'Employee Master'!D44) -> In-house | D44: =IF('Employee Master'!B44="","",'Employee Master'!E44) -> Associate | E44: =IF('Employee Master'!B44="","",'Employee Master'!F44) -> HR | F44: =IF('Employee Master'!B44="","",'Employee Master'!G44) -> Vinita Dagar | G44: 131 | H44: 131 | I44: =IF(A44="","",G44-H44) -> 0 | J44: =IF(A44="","",IF(H44=0,0,H44/(Settings!B6*12))) -> 0.068229167 | K44: 1 | L44: 3.5 | M44: 0 | N44: =IF(A44="","",IF(H44=0,0,M44/H44)) -> 0 | O44: 0 | P44: 0 | Q44: =IF(A44="","",IF(O44=0,0,1-P44/O44)) -> 0 | R44: 12
A45: =IF('Employee Master'!B45="","",'Employee Master'!B45) -> CAS-IH_1114 | B45: =IF('Employee Master'!B45="","",'Employee Master'!C45) -> Smriti.S | C45: =IF('Employee Master'!B45="","",'Employee Master'!D45) -> In-house | D45: =IF('Employee Master'!B45="","",'Employee Master'!E45) -> Controller | E45: =IF('Employee Master'!B45="","",'Employee Master'!F45) -> Individual Tax | F45: =IF('Employee Master'!B45="","",'Employee Master'!G45) -> -- | G45: 9 | H45: 9 | I45: =IF(A45="","",G45-H45) -> 0 | J45: =IF(A45="","",IF(H45=0,0,H45/(Settings!B6*12))) -> 0.0046875 | K45: 1 | L45: 3.5 | M45: 0 | N45: =IF(A45="","",IF(H45=0,0,M45/H45)) -> 0 | O45: 0 | P45: 0 | Q45: =IF(A45="","",IF(O45=0,0,1-P45/O45)) -> 0 | R45: 12
A46: =IF('Employee Master'!B46="","",'Employee Master'!B46) -> CAS-RT_2283 | B46: =IF('Employee Master'!B46="","",'Employee Master'!C46) -> Muhammad.S | C46: =IF('Employee Master'!B46="","",'Employee Master'!D46) -> Remote | D46: =IF('Employee Master'!B46="","",'Employee Master'!E46) -> Associate | E46: =IF('Employee Master'!B46="","",'Employee Master'!F46) -> Accounting | F46: =IF('Employee Master'!B46="","",'Employee Master'!G46) -> Ayushi | G46: 85.1 | H46: 87.1 | I46: =IF(A46="","",G46-H46) -> -2 | J46: =IF(A46="","",IF(H46=0,0,H46/(Settings!B6*12))) -> 0.045364583 | K46: 5 | L46: 3.5 | M46: 0 | N46: =IF(A46="","",IF(H46=0,0,M46/H46)) -> 0 | O46: 0 | P46: 0 | Q46: =IF(A46="","",IF(O46=0,0,1-P46/O46)) -> 0 | R46: 12
A47: =IF('Employee Master'!B47="","",'Employee Master'!B47) -> CAS-RT_2296 | B47: =IF('Employee Master'!B47="","",'Employee Master'!C47) -> Farheen.K | C47: =IF('Employee Master'!B47="","",'Employee Master'!D47) -> Remote | D47: =IF('Employee Master'!B47="","",'Employee Master'!E47) -> Asst. Team Lead | E47: =IF('Employee Master'!B47="","",'Employee Master'!F47) -> Accounting | F47: =IF('Employee Master'!B47="","",'Employee Master'!G47) -> Sukhmeen.K | G47: 173 | H47: 173 | I47: =IF(A47="","",G47-H47) -> 0 | J47: =IF(A47="","",IF(H47=0,0,H47/(Settings!B6*12))) -> 0.090104167 | K47: 7 | L47: 3.5 | M47: 0 | N47: =IF(A47="","",IF(H47=0,0,M47/H47)) -> 0 | O47: 0 | P47: 0 | Q47: =IF(A47="","",IF(O47=0,0,1-P47/O47)) -> 0 | R47: 12
A48: =IF('Employee Master'!B48="","",'Employee Master'!B48) -> CAS-IH_1120 | B48: =IF('Employee Master'!B48="","",'Employee Master'!C48) -> Vaibhav.A | C48: =IF('Employee Master'!B48="","",'Employee Master'!D48) -> In-house | D48: =IF('Employee Master'!B48="","",'Employee Master'!E48) -> Manager | E48: =IF('Employee Master'!B48="","",'Employee Master'!F48) -> FP&A | F48: =IF('Employee Master'!B48="","",'Employee Master'!G48) -> Sachi Mazumdar | G48: 159.3 | H48: 159.3 | I48: =IF(A48="","",G48-H48) -> 0 | J48: =IF(A48="","",IF(H48=0,0,H48/(Settings!B6*12))) -> 0.08296875 | K48: 7 | L48: 3.5 | M48: 0 | N48: =IF(A48="","",IF(H48=0,0,M48/H48)) -> 0 | O48: 0 | P48: 0 | Q48: =IF(A48="","",IF(O48=0,0,1-P48/O48)) -> 0 | R48: 12
A49: =IF('Employee Master'!B49="","",'Employee Master'!B49) -> CAS-IH_1123 | B49: =IF('Employee Master'!B49="","",'Employee Master'!C49) -> Shikha.A | C49: =IF('Employee Master'!B49="","",'Employee Master'!D49) -> In-house | D49: =IF('Employee Master'!B49="","",'Employee Master'!E49) -> Asst. Team Lead | E49: =IF('Employee Master'!B49="","",'Employee Master'!F49) -> Individual Tax | F49: =IF('Employee Master'!B49="","",'Employee Master'!G49) -> Smriti Shah | G49: 185 | H49: 185 | I49: =IF(A49="","",G49-H49) -> 0 | J49: =IF(A49="","",IF(H49=0,0,H49/(Settings!B6*12))) -> 0.096354167 | K49: 1 | L49: 3.5 | M49: 0 | N49: =IF(A49="","",IF(H49=0,0,M49/H49)) -> 0 | O49: 0 | P49: 0 | Q49: =IF(A49="","",IF(O49=0,0,1-P49/O49)) -> 0 | R49: 12
A50: =IF('Employee Master'!B50="","",'Employee Master'!B50) -> CAS-IH_1124 | B50: =IF('Employee Master'!B50="","",'Employee Master'!C50) -> Rupesh.A | C50: =IF('Employee Master'!B50="","",'Employee Master'!D50) -> In-house | D50: =IF('Employee Master'!B50="","",'Employee Master'!E50) -> Sr. Manager | E50: =IF('Employee Master'!B50="","",'Employee Master'!F50) -> FP&A | F50: =IF('Employee Master'!B50="","",'Employee Master'!G50) -> Sachi Mazumdar | G50: 176 | H50: 176 | I50: =IF(A50="","",G50-H50) -> 0 | J50: =IF(A50="","",IF(H50=0,0,H50/(Settings!B6*12))) -> 0.091666667 | K50: 7 | L50: 3.5 | M50: 0 | N50: =IF(A50="","",IF(H50=0,0,M50/H50)) -> 0 | O50: 0 | P50: 0 | Q50: =IF(A50="","",IF(O50=0,0,1-P50/O50)) -> 0 | R50: 12
A51: =IF('Employee Master'!B51="","",'Employee Master'!B51) -> CAS-IH_1126 | B51: =IF('Employee Master'!B51="","",'Employee Master'!C51) -> Deepika.B | C51: =IF('Employee Master'!B51="","",'Employee Master'!D51) -> In-house | D51: =IF('Employee Master'!B51="","",'Employee Master'!E51) -> Associate | E51: =IF('Employee Master'!B51="","",'Employee Master'!F51) -> Individual Tax | F51: =IF('Employee Master'!B51="","",'Employee Master'!G51) -> Smriti Shah | G51: 0 | H51: 0 | I51: =IF(A51="","",G51-H51) -> 0 | J51: =IF(A51="","",IF(H51=0,0,H51/(Settings!B6*12))) -> 0 | K51: 0 | L51: 3.5 | M51: 0 | N51: =IF(A51="","",IF(H51=0,0,M51/H51)) -> 0 | O51: 0 | P51: 0 | Q51: =IF(A51="","",IF(O51=0,0,1-P51/O51)) -> 0 | R51: 12
A52: =IF('Employee Master'!B52="","",'Employee Master'!B52) -> CAS-IH_1127 | B52: =IF('Employee Master'!B52="","",'Employee Master'!C52) -> Vandana.M | C52: =IF('Employee Master'!B52="","",'Employee Master'!D52) -> In-house | D52: =IF('Employee Master'!B52="","",'Employee Master'!E52) -> Associate | E52: =IF('Employee Master'!B52="","",'Employee Master'!F52) -> Individual Tax | F52: =IF('Employee Master'!B52="","",'Employee Master'!G52) -> Smriti Shah | G52: 106.9 | H52: 106.9 | I52: =IF(A52="","",G52-H52) -> 0 | J52: =IF(A52="","",IF(H52=0,0,H52/(Settings!B6*12))) -> 0.055677083 | K52: 5 | L52: 3.5 | M52: 0 | N52: =IF(A52="","",IF(H52=0,0,M52/H52)) -> 0 | O52: 0 | P52: 0 | Q52: =IF(A52="","",IF(O52=0,0,1-P52/O52)) -> 0 | R52: 12
A53: =IF('Employee Master'!B53="","",'Employee Master'!B53) -> CAS-RT_2319 | B53: =IF('Employee Master'!B53="","",'Employee Master'!C53) -> Shikha.AG | C53: =IF('Employee Master'!B53="","",'Employee Master'!D53) -> Remote | D53: =IF('Employee Master'!B53="","",'Employee Master'!E53) -> Asst. Team Lead | E53: =IF('Employee Master'!B53="","",'Employee Master'!F53) -> Accounting | F53: =IF('Employee Master'!B53="","",'Employee Master'!G53) -> Ayushi | G53: 65.1 | H53: 65.1 | I53: =IF(A53="","",G53-H53) -> 0 | J53: =IF(A53="","",IF(H53=0,0,H53/(Settings!B6*12))) -> 0.03390625 | K53: 5 | L53: 3.5 | M53: 0 | N53: =IF(A53="","",IF(H53=0,0,M53/H53)) -> 0 | O53: 0 | P53: 0 | Q53: =IF(A53="","",IF(O53=0,0,1-P53/O53)) -> 0 | R53: 12
A54: =IF('Employee Master'!B54="","",'Employee Master'!B54) -> CAS-RT_2324 | B54: =IF('Employee Master'!B54="","",'Employee Master'!C54) -> Falguni.M | C54: =IF('Employee Master'!B54="","",'Employee Master'!D54) -> Remote | D54: =IF('Employee Master'!B54="","",'Employee Master'!E54) -> Manager | E54: =IF('Employee Master'!B54="","",'Employee Master'!F54) -> Business Tax | F54: =IF('Employee Master'!B54="","",'Employee Master'!G54) -> Jyoti | G54: 78.4 | H54: 78.4 | I54: =IF(A54="","",G54-H54) -> 0 | J54: =IF(A54="","",IF(H54=0,0,H54/(Settings!B6*12))) -> 0.040833333 | K54: 4 | L54: 3.5 | M54: 0 | N54: =IF(A54="","",IF(H54=0,0,M54/H54)) -> 0 | O54: 0 | P54: 0 | Q54: =IF(A54="","",IF(O54=0,0,1-P54/O54)) -> 0 | R54: 12
A55: =IF('Employee Master'!B55="","",'Employee Master'!B55) -> CAS-RT_2332 | B55: =IF('Employee Master'!B55="","",'Employee Master'!C55) -> Saumil.M | C55: =IF('Employee Master'!B55="","",'Employee Master'!D55) -> Remote | D55: =IF('Employee Master'!B55="","",'Employee Master'!E55) -> Associate | E55: =IF('Employee Master'!B55="","",'Employee Master'!F55) -> Accounting | F55: =IF('Employee Master'!B55="","",'Employee Master'!G55) -> Ayushi | G55: 80.9 | H55: 80.9 | I55: =IF(A55="","",G55-H55) -> 0 | J55: =IF(A55="","",IF(H55=0,0,H55/(Settings!B6*12))) -> 0.042135417 | K55: 6 | L55: 3.5 | M55: 0 | N55: =IF(A55="","",IF(H55=0,0,M55/H55)) -> 0 | O55: 0 | P55: 0 | Q55: =IF(A55="","",IF(O55=0,0,1-P55/O55)) -> 0 | R55: 12
A56: =IF('Employee Master'!B56="","",'Employee Master'!B56) -> CAS-RT_2335 | B56: =IF('Employee Master'!B56="","",'Employee Master'!C56) -> Seemu.A | C56: =IF('Employee Master'!B56="","",'Employee Master'!D56) -> Remote | D56: =IF('Employee Master'!B56="","",'Employee Master'!E56) -> Associate | E56: =IF('Employee Master'!B56="","",'Employee Master'!F56) -> Accounting | F56: =IF('Employee Master'!B56="","",'Employee Master'!G56) -> Nikita Shah | G56: 59.6 | H56: 59.6 | I56: =IF(A56="","",G56-H56) -> 0 | J56: =IF(A56="","",IF(H56=0,0,H56/(Settings!B6*12))) -> 0.031041667 | K56: 2 | L56: 3.5 | M56: 0 | N56: =IF(A56="","",IF(H56=0,0,M56/H56)) -> 0 | O56: 0 | P56: 0 | Q56: =IF(A56="","",IF(O56=0,0,1-P56/O56)) -> 0 | R56: 12
A57: =IF('Employee Master'!B57="","",'Employee Master'!B57) -> CAS-RT_2340 | B57: =IF('Employee Master'!B57="","",'Employee Master'!C57) -> Kanica.P | C57: =IF('Employee Master'!B57="","",'Employee Master'!D57) -> Remote | D57: =IF('Employee Master'!B57="","",'Employee Master'!E57) -> Sr. Associate | E57: =IF('Employee Master'!B57="","",'Employee Master'!F57) -> Accounting | F57: =IF('Employee Master'!B57="","",'Employee Master'!G57) -> Nikita Shah | G57: 73.2 | H57: 73.2 | I57: =IF(A57="","",G57-H57) -> 0 | J57: =IF(A57="","",IF(H57=0,0,H57/(Settings!B6*12))) -> 0.038125 | K57: 7 | L57: 3.5 | M57: 0 | N57: =IF(A57="","",IF(H57=0,0,M57/H57)) -> 0 | O57: 0 | P57: 0 | Q57: =IF(A57="","",IF(O57=0,0,1-P57/O57)) -> 0 | R57: 12
A58: =IF('Employee Master'!B58="","",'Employee Master'!B58) -> CAS-IH_1137 | B58: =IF('Employee Master'!B58="","",'Employee Master'!C58) -> Ammie | C58: =IF('Employee Master'!B58="","",'Employee Master'!D58) -> In-house | D58: =IF('Employee Master'!B58="","",'Employee Master'!E58) -> Sr. Controller | E58: =IF('Employee Master'!B58="","",'Employee Master'!F58) -> Individual Tax, Business Tax | F58: =IF('Employee Master'!B58="","",'Employee Master'!G58) -> -- | G58: 146.5 | H58: 146.5 | I58: =IF(A58="","",G58-H58) -> 0 | J58: =IF(A58="","",IF(H58=0,0,H58/(Settings!B6*12))) -> 0.076302083 | K58: 3 | L58: 3.5 | M58: 0 | N58: =IF(A58="","",IF(H58=0,0,M58/H58)) -> 0 | O58: 0 | P58: 0 | Q58: =IF(A58="","",IF(O58=0,0,1-P58/O58)) -> 0 | R58: 12
A59: =IF('Employee Master'!B59="","",'Employee Master'!B59) -> CAS-RT_2349 | B59: =IF('Employee Master'!B59="","",'Employee Master'!C59) -> Pranjali.M | C59: =IF('Employee Master'!B59="","",'Employee Master'!D59) -> Remote | D59: =IF('Employee Master'!B59="","",'Employee Master'!E59) -> Associate | E59: =IF('Employee Master'!B59="","",'Employee Master'!F59) -> Accounting | F59: =IF('Employee Master'!B59="","",'Employee Master'!G59) -> Ayushi | G59: 153 | H59: 154.5 | I59: =IF(A59="","",G59-H59) -> -1.5 | J59: =IF(A59="","",IF(H59=0,0,H59/(Settings!B6*12))) -> 0.08046875 | K59: 3 | L59: 3.5 | M59: 0 | N59: =IF(A59="","",IF(H59=0,0,M59/H59)) -> 0 | O59: 0 | P59: 0 | Q59: =IF(A59="","",IF(O59=0,0,1-P59/O59)) -> 0 | R59: 12
A60: =IF('Employee Master'!B60="","",'Employee Master'!B60) -> CAS-RT_2351 | B60: =IF('Employee Master'!B60="","",'Employee Master'!C60) -> Shikha.S | C60: =IF('Employee Master'!B60="","",'Employee Master'!D60) -> Remote | D60: =IF('Employee Master'!B60="","",'Employee Master'!E60) -> Associate | E60: =IF('Employee Master'!B60="","",'Employee Master'!F60) -> Accounting | F60: =IF('Employee Master'!B60="","",'Employee Master'!G60) -> Nikita Shah | G60: 87.8 | H60: 87.8 | I60: =IF(A60="","",G60-H60) -> 0 | J60: =IF(A60="","",IF(H60=0,0,H60/(Settings!B6*12))) -> 0.045729167 | K60: 3 | L60: 3.5 | M60: 0 | N60: =IF(A60="","",IF(H60=0,0,M60/H60)) -> 0 | O60: 0 | P60: 0 | Q60: =IF(A60="","",IF(O60=0,0,1-P60/O60)) -> 0 | R60: 12
A61: =IF('Employee Master'!B61="","",'Employee Master'!B61) -> CAS-RT_2359 | B61: =IF('Employee Master'!B61="","",'Employee Master'!C61) -> Rutu.G | C61: =IF('Employee Master'!B61="","",'Employee Master'!D61) -> Remote | D61: =IF('Employee Master'!B61="","",'Employee Master'!E61) -> Associate | E61: =IF('Employee Master'!B61="","",'Employee Master'!F61) -> Accounting | F61: =IF('Employee Master'!B61="","",'Employee Master'!G61) -> Nikita Shah | G61: 161.6 | H61: 161.6 | I61: =IF(A61="","",G61-H61) -> 0 | J61: =IF(A61="","",IF(H61=0,0,H61/(Settings!B6*12))) -> 0.084166667 | K61: 3 | L61: 3.5 | M61: 0 | N61: =IF(A61="","",IF(H61=0,0,M61/H61)) -> 0 | O61: 0 | P61: 0 | Q61: =IF(A61="","",IF(O61=0,0,1-P61/O61)) -> 0 | R61: 12
A62: =IF('Employee Master'!B62="","",'Employee Master'!B62) -> CAS-IH_1003 | B62: =IF('Employee Master'!B62="","",'Employee Master'!C62) -> Sachi | C62: =IF('Employee Master'!B62="","",'Employee Master'!D62) -> In-house | D62: =IF('Employee Master'!B62="","",'Employee Master'!E62) -> Coo | E62: =IF('Employee Master'!B62="","",'Employee Master'!F62) -> FP&A | F62: =IF('Employee Master'!B62="","",'Employee Master'!G62) -> -- | G62: 125.7 | H62: 125.7 | I62: =IF(A62="","",G62-H62) -> 0 | J62: =IF(A62="","",IF(H62=0,0,H62/(Settings!B6*12))) -> 0.06546875 | K62: 5 | L62: 3.5 | M62: 0 | N62: =IF(A62="","",IF(H62=0,0,M62/H62)) -> 0 | O62: 0 | P62: 0 | Q62: =IF(A62="","",IF(O62=0,0,1-P62/O62)) -> 0 | R62: 12
A63: =IF('Employee Master'!B63="","",'Employee Master'!B63) -> CAS-RR_2374 | B63: =IF('Employee Master'!B63="","",'Employee Master'!C63) -> Aishwarya.V | C63: =IF('Employee Master'!B63="","",'Employee Master'!D63) -> Remote | D63: =IF('Employee Master'!B63="","",'Employee Master'!E63) -> Asst. Team Lead | E63: =IF('Employee Master'!B63="","",'Employee Master'!F63) -> Accounting | F63: =IF('Employee Master'!B63="","",'Employee Master'!G63) -> Jasleen.D | G63: 0 | H63: 0 | I63: =IF(A63="","",G63-H63) -> 0 | J63: =IF(A63="","",IF(H63=0,0,H63/(Settings!B6*12))) -> 0 | K63: 0 | L63: 3.5 | M63: 0 | N63: =IF(A63="","",IF(H63=0,0,M63/H63)) -> 0 | O63: 0 | P63: 0 | Q63: =IF(A63="","",IF(O63=0,0,1-P63/O63)) -> 0 | R63: 12
A64: =IF('Employee Master'!B64="","",'Employee Master'!B64) -> CAS-RT_2367 | B64: =IF('Employee Master'!B64="","",'Employee Master'!C64) -> Tejas.P | C64: =IF('Employee Master'!B64="","",'Employee Master'!D64) -> Remote | D64: =IF('Employee Master'!B64="","",'Employee Master'!E64) -> Sr. Associate | E64: =IF('Employee Master'!B64="","",'Employee Master'!F64) -> Accounting | F64: =IF('Employee Master'!B64="","",'Employee Master'!G64) -> Jasleen.D | G64: 153.5 | H64: 153.5 | I64: =IF(A64="","",G64-H64) -> 0 | J64: =IF(A64="","",IF(H64=0,0,H64/(Settings!B6*12))) -> 0.079947917 | K64: 2 | L64: 3.5 | M64: 0 | N64: =IF(A64="","",IF(H64=0,0,M64/H64)) -> 0 | O64: 0 | P64: 0 | Q64: =IF(A64="","",IF(O64=0,0,1-P64/O64)) -> 0 | R64: 12
A65: =IF('Employee Master'!B65="","",'Employee Master'!B65) -> CAS-RT_2361 | B65: =IF('Employee Master'!B65="","",'Employee Master'!C65) -> Priyam.B | C65: =IF('Employee Master'!B65="","",'Employee Master'!D65) -> Remote | D65: =IF('Employee Master'!B65="","",'Employee Master'!E65) -> Asst. Team Lead | E65: =IF('Employee Master'!B65="","",'Employee Master'!F65) -> Accounting | F65: =IF('Employee Master'!B65="","",'Employee Master'!G65) -> Nikita Shah | G65: 182.9 | H65: 182.9 | I65: =IF(A65="","",G65-H65) -> 0 | J65: =IF(A65="","",IF(H65=0,0,H65/(Settings!B6*12))) -> 0.095260417 | K65: 3 | L65: 3.5 | M65: 0 | N65: =IF(A65="","",IF(H65=0,0,M65/H65)) -> 0 | O65: 0 | P65: 0 | Q65: =IF(A65="","",IF(O65=0,0,1-P65/O65)) -> 0 | R65: 12
A66: =IF('Employee Master'!B66="","",'Employee Master'!B66) -> CAS-IH_1151 | B66: =IF('Employee Master'!B66="","",'Employee Master'!C66) -> Jaya.L | C66: =IF('Employee Master'!B66="","",'Employee Master'!D66) -> In-house | D66: =IF('Employee Master'!B66="","",'Employee Master'!E66) -> Asst. Team Lead | E66: =IF('Employee Master'!B66="","",'Employee Master'!F66) -> Accounting, L&D | F66: =IF('Employee Master'!B66="","",'Employee Master'!G66) -> Sarah | G66: 80 | H66: 80 | I66: =IF(A66="","",G66-H66) -> 0 | J66: =IF(A66="","",IF(H66=0,0,H66/(Settings!B6*12))) -> 0.041666667 | K66: 5 | L66: 3.5 | M66: 0 | N66: =IF(A66="","",IF(H66=0,0,M66/H66)) -> 0 | O66: 0 | P66: 0 | Q66: =IF(A66="","",IF(O66=0,0,1-P66/O66)) -> 0 | R66: 12
A67: =IF('Employee Master'!B67="","",'Employee Master'!B67) -> CAS-RT_2369 | B67: =IF('Employee Master'!B67="","",'Employee Master'!C67) -> Ayushi.B | C67: =IF('Employee Master'!B67="","",'Employee Master'!D67) -> Remote | D67: =IF('Employee Master'!B67="","",'Employee Master'!E67) -> Associate | E67: =IF('Employee Master'!B67="","",'Employee Master'!F67) -> Accounting | F67: =IF('Employee Master'!B67="","",'Employee Master'!G67) -> Jyoti | G67: 177.3 | H67: 177.3 | I67: =IF(A67="","",G67-H67) -> 0 | J67: =IF(A67="","",IF(H67=0,0,H67/(Settings!B6*12))) -> 0.09234375 | K67: 1 | L67: 3.5 | M67: 0 | N67: =IF(A67="","",IF(H67=0,0,M67/H67)) -> 0 | O67: 0 | P67: 0 | Q67: =IF(A67="","",IF(O67=0,0,1-P67/O67)) -> 0 | R67: 12
A68: =IF('Employee Master'!B68="","",'Employee Master'!B68) -> CAS-IH_1144 | B68: =IF('Employee Master'!B68="","",'Employee Master'!C68) -> Akanksha.V | C68: =IF('Employee Master'!B68="","",'Employee Master'!D68) -> In-house | D68: =IF('Employee Master'!B68="","",'Employee Master'!E68) -> Associate | E68: =IF('Employee Master'!B68="","",'Employee Master'!F68) -> HR | F68: =IF('Employee Master'!B68="","",'Employee Master'!G68) -> Vinita Dagar | G68: 163.1 | H68: 163.1 | I68: =IF(A68="","",G68-H68) -> 0 | J68: =IF(A68="","",IF(H68=0,0,H68/(Settings!B6*12))) -> 0.084947917 | K68: 2 | L68: 3.5 | M68: 0 | N68: =IF(A68="","",IF(H68=0,0,M68/H68)) -> 0 | O68: 0 | P68: 0 | Q68: =IF(A68="","",IF(O68=0,0,1-P68/O68)) -> 0 | R68: 12
A69: =IF('Employee Master'!B69="","",'Employee Master'!B69) -> CAS-RT_2372 | B69: =IF('Employee Master'!B69="","",'Employee Master'!C69) -> Teja.R | C69: =IF('Employee Master'!B69="","",'Employee Master'!D69) -> Remote | D69: =IF('Employee Master'!B69="","",'Employee Master'!E69) -> Associate | E69: =IF('Employee Master'!B69="","",'Employee Master'!F69) -> Accounting | F69: =IF('Employee Master'!B69="","",'Employee Master'!G69) -> Nikita Shah | G69: 56 | H69: 56 | I69: =IF(A69="","",G69-H69) -> 0 | J69: =IF(A69="","",IF(H69=0,0,H69/(Settings!B6*12))) -> 0.029166667 | K69: 1 | L69: 3.5 | M69: 0 | N69: =IF(A69="","",IF(H69=0,0,M69/H69)) -> 0 | O69: 0 | P69: 0 | Q69: =IF(A69="","",IF(O69=0,0,1-P69/O69)) -> 0 | R69: 12
A70: =IF('Employee Master'!B70="","",'Employee Master'!B70) -> CAS-RT_2373 | B70: =IF('Employee Master'!B70="","",'Employee Master'!C70) -> Upasana | C70: =IF('Employee Master'!B70="","",'Employee Master'!D70) -> Remote | D70: =IF('Employee Master'!B70="","",'Employee Master'!E70) -> Sr. Associate | E70: =IF('Employee Master'!B70="","",'Employee Master'!F70) -> Accounting | F70: =IF('Employee Master'!B70="","",'Employee Master'!G70) -> Jyoti | G70: 157.9 | H70: 157.9 | I70: =IF(A70="","",G70-H70) -> 0 | J70: =IF(A70="","",IF(H70=0,0,H70/(Settings!B6*12))) -> 0.082239583 | K70: 2 | L70: 3.5 | M70: 0 | N70: =IF(A70="","",IF(H70=0,0,M70/H70)) -> 0 | O70: 0 | P70: 0 | Q70: =IF(A70="","",IF(O70=0,0,1-P70/O70)) -> 0 | R70: 12
A71: =IF('Employee Master'!B71="","",'Employee Master'!B71) -> CAS-RT_2374 | B71: =IF('Employee Master'!B71="","",'Employee Master'!C71) -> Scarlett.C | C71: =IF('Employee Master'!B71="","",'Employee Master'!D71) -> Remote | D71: =IF('Employee Master'!B71="","",'Employee Master'!E71) -> Sr. Associate | E71: =IF('Employee Master'!B71="","",'Employee Master'!F71) -> Accounting | F71: =IF('Employee Master'!B71="","",'Employee Master'!G71) -> Jasleen.D | G71: 80.9 | H71: 80.9 | I71: =IF(A71="","",G71-H71) -> 0 | J71: =IF(A71="","",IF(H71=0,0,H71/(Settings!B6*12))) -> 0.042135417 | K71: 3 | L71: 3.5 | M71: 0 | N71: =IF(A71="","",IF(H71=0,0,M71/H71)) -> 0 | O71: 0 | P71: 0 | Q71: =IF(A71="","",IF(O71=0,0,1-P71/O71)) -> 0 | R71: 12
A72: =IF('Employee Master'!B72="","",'Employee Master'!B72) -> CAS-IH_1148 | B72: =IF('Employee Master'!B72="","",'Employee Master'!C72) -> Alan | C72: =IF('Employee Master'!B72="","",'Employee Master'!D72) -> In-house | D72: =IF('Employee Master'!B72="","",'Employee Master'!E72) -> Project Manager (S/W) | E72: =IF('Employee Master'!B72="","",'Employee Master'!F72) -> IT | F72: =IF('Employee Master'!B72="","",'Employee Master'!G72) -> -- | G72: 180.4 | H72: 180.2 | I72: =IF(A72="","",G72-H72) -> 0.2 | J72: =IF(A72="","",IF(H72=0,0,H72/(Settings!B6*12))) -> 0.093854167 | K72: 2 | L72: 3.5 | M72: 0 | N72: =IF(A72="","",IF(H72=0,0,M72/H72)) -> 0 | O72: 0 | P72: 0 | Q72: =IF(A72="","",IF(O72=0,0,1-P72/O72)) -> 0 | R72: 12
A73: =IF('Employee Master'!B73="","",'Employee Master'!B73) -> CAS-RT_2375 | B73: =IF('Employee Master'!B73="","",'Employee Master'!C73) -> Farheen.F | C73: =IF('Employee Master'!B73="","",'Employee Master'!D73) -> Remote | D73: =IF('Employee Master'!B73="","",'Employee Master'!E73) -> Associate | E73: =IF('Employee Master'!B73="","",'Employee Master'!F73) -> Accounting | F73: =IF('Employee Master'!B73="","",'Employee Master'!G73) -> Jasleen.D | G73: 0 | H73: 0 | I73: =IF(A73="","",G73-H73) -> 0 | J73: =IF(A73="","",IF(H73=0,0,H73/(Settings!B6*12))) -> 0 | K73: 0 | L73: 3.5 | M73: 0 | N73: =IF(A73="","",IF(H73=0,0,M73/H73)) -> 0 | O73: 0 | P73: 0 | Q73: =IF(A73="","",IF(O73=0,0,1-P73/O73)) -> 0 | R73: 12
A74: =IF('Employee Master'!B74="","",'Employee Master'!B74) -> CAS-RT_2376 | B74: =IF('Employee Master'!B74="","",'Employee Master'!C74) -> Megha.J | C74: =IF('Employee Master'!B74="","",'Employee Master'!D74) -> Remote | D74: =IF('Employee Master'!B74="","",'Employee Master'!E74) -> Associate | E74: =IF('Employee Master'!B74="","",'Employee Master'!F74) -> Accounting | F74: =IF('Employee Master'!B74="","",'Employee Master'!G74) -> Jasleen.D | G74: 158 | H74: 158 | I74: =IF(A74="","",G74-H74) -> 0 | J74: =IF(A74="","",IF(H74=0,0,H74/(Settings!B6*12))) -> 0.082291667 | K74: 2 | L74: 3.5 | M74: 0 | N74: =IF(A74="","",IF(H74=0,0,M74/H74)) -> 0 | O74: 0 | P74: 0 | Q74: =IF(A74="","",IF(O74=0,0,1-P74/O74)) -> 0 | R74: 12
A75: =IF('Employee Master'!B75="","",'Employee Master'!B75) -> CAS-IH_1161 | B75: =IF('Employee Master'!B75="","",'Employee Master'!C75) -> Prachi.G | C75: =IF('Employee Master'!B75="","",'Employee Master'!D75) -> In-house | D75: =IF('Employee Master'!B75="","",'Employee Master'!E75) -> Sr. Manager | E75: =IF('Employee Master'!B75="","",'Employee Master'!F75) -> FP&A | F75: =IF('Employee Master'!B75="","",'Employee Master'!G75) -> Sachi Mazumdar | G75: 161.2 | H75: 161.2 | I75: =IF(A75="","",G75-H75) -> 0 | J75: =IF(A75="","",IF(H75=0,0,H75/(Settings!B6*12))) -> 0.083958333 | K75: 2 | L75: 3.5 | M75: 0 | N75: =IF(A75="","",IF(H75=0,0,M75/H75)) -> 0 | O75: 0 | P75: 0 | Q75: =IF(A75="","",IF(O75=0,0,1-P75/O75)) -> 0 | R75: 12
A76: =IF('Employee Master'!B76="","",'Employee Master'!B76) -> CAS-RT_2382 | B76: =IF('Employee Master'!B76="","",'Employee Master'!C76) -> Itee.S | C76: =IF('Employee Master'!B76="","",'Employee Master'!D76) -> Remote | D76: =IF('Employee Master'!B76="","",'Employee Master'!E76) -> Associate | E76: =IF('Employee Master'!B76="","",'Employee Master'!F76) -> Accounting | F76: =IF('Employee Master'!B76="","",'Employee Master'!G76) -> Ayushi | G76: 198 | H76: 198 | I76: =IF(A76="","",G76-H76) -> 0 | J76: =IF(A76="","",IF(H76=0,0,H76/(Settings!B6*12))) -> 0.103125 | K76: 1 | L76: 3.5 | M76: 0 | N76: =IF(A76="","",IF(H76=0,0,M76/H76)) -> 0 | O76: 0 | P76: 0 | Q76: =IF(A76="","",IF(O76=0,0,1-P76/O76)) -> 0 | R76: 12
A77: =IF('Employee Master'!B77="","",'Employee Master'!B77) -> CAS-RT_2383 | B77: =IF('Employee Master'!B77="","",'Employee Master'!C77) -> Anushka.G | C77: =IF('Employee Master'!B77="","",'Employee Master'!D77) -> Remote | D77: =IF('Employee Master'!B77="","",'Employee Master'!E77) -> Associate | E77: =IF('Employee Master'!B77="","",'Employee Master'!F77) -> L&D | F77: =IF('Employee Master'!B77="","",'Employee Master'!G77) -> Nikita Shah | G77: 166.8 | H77: 166.8 | I77: =IF(A77="","",G77-H77) -> 0 | J77: =IF(A77="","",IF(H77=0,0,H77/(Settings!B6*12))) -> 0.086875 | K77: 5 | L77: 3.5 | M77: 0 | N77: =IF(A77="","",IF(H77=0,0,M77/H77)) -> 0 | O77: 0 | P77: 0 | Q77: =IF(A77="","",IF(O77=0,0,1-P77/O77)) -> 0 | R77: 12
A78: =IF('Employee Master'!B78="","",'Employee Master'!B78) -> CAS-RT_2384 | B78: =IF('Employee Master'!B78="","",'Employee Master'!C78) -> Priyanka.M | C78: =IF('Employee Master'!B78="","",'Employee Master'!D78) -> Remote | D78: =IF('Employee Master'!B78="","",'Employee Master'!E78) -> Asst. Team Lead | E78: =IF('Employee Master'!B78="","",'Employee Master'!F78) -> Accounting | F78: =IF('Employee Master'!B78="","",'Employee Master'!G78) -> Ayushi | G78: 166 | H78: 166 | I78: =IF(A78="","",G78-H78) -> 0 | J78: =IF(A78="","",IF(H78=0,0,H78/(Settings!B6*12))) -> 0.086458333 | K78: 1 | L78: 3.5 | M78: 0 | N78: =IF(A78="","",IF(H78=0,0,M78/H78)) -> 0 | O78: 0 | P78: 0 | Q78: =IF(A78="","",IF(O78=0,0,1-P78/O78)) -> 0 | R78: 12
A79: =IF('Employee Master'!B79="","",'Employee Master'!B79) -> CAS-RT_2385 | B79: =IF('Employee Master'!B79="","",'Employee Master'!C79) -> Raj.B | C79: =IF('Employee Master'!B79="","",'Employee Master'!D79) -> Remote | D79: =IF('Employee Master'!B79="","",'Employee Master'!E79) -> Sr. Associate | E79: =IF('Employee Master'!B79="","",'Employee Master'!F79) -> Accounting | F79: =IF('Employee Master'!B79="","",'Employee Master'!G79) -> Nikita Shah | G79: 158.2 | H79: 158.2 | I79: =IF(A79="","",G79-H79) -> 0 | J79: =IF(A79="","",IF(H79=0,0,H79/(Settings!B6*12))) -> 0.082395833 | K79: 3 | L79: 3.5 | M79: 0 | N79: =IF(A79="","",IF(H79=0,0,M79/H79)) -> 0 | O79: 0 | P79: 0 | Q79: =IF(A79="","",IF(O79=0,0,1-P79/O79)) -> 0 | R79: 12
A80: =IF('Employee Master'!B80="","",'Employee Master'!B80) -> CAS-RT_2386 | B80: =IF('Employee Master'!B80="","",'Employee Master'!C80) -> Chhavi.S | C80: =IF('Employee Master'!B80="","",'Employee Master'!D80) -> Remote | D80: =IF('Employee Master'!B80="","",'Employee Master'!E80) -> Sr. Associate | E80: =IF('Employee Master'!B80="","",'Employee Master'!F80) -> Accounting, VA | F80: =IF('Employee Master'!B80="","",'Employee Master'!G80) -> Nikita Shah | G80: 164.3 | H80: 164.3 | I80: =IF(A80="","",G80-H80) -> 0 | J80: =IF(A80="","",IF(H80=0,0,H80/(Settings!B6*12))) -> 0.085572917 | K80: 4 | L80: 3.5 | M80: 0 | N80: =IF(A80="","",IF(H80=0,0,M80/H80)) -> 0 | O80: 0 | P80: 0 | Q80: =IF(A80="","",IF(O80=0,0,1-P80/O80)) -> 0 | R80: 12
A81: =IF('Employee Master'!B81="","",'Employee Master'!B81) -> CAS-RT_2390 | B81: =IF('Employee Master'!B81="","",'Employee Master'!C81) -> Surbhi.A | C81: =IF('Employee Master'!B81="","",'Employee Master'!D81) -> Remote | D81: =IF('Employee Master'!B81="","",'Employee Master'!E81) -> Asst. Team Lead | E81: =IF('Employee Master'!B81="","",'Employee Master'!F81) -> Accounting | F81: =IF('Employee Master'!B81="","",'Employee Master'!G81) -> Jasleen.D | G81: 115.1 | H81: 115.1 | I81: =IF(A81="","",G81-H81) -> 0 | J81: =IF(A81="","",IF(H81=0,0,H81/(Settings!B6*12))) -> 0.059947917 | K81: 4 | L81: 3.5 | M81: 0 | N81: =IF(A81="","",IF(H81=0,0,M81/H81)) -> 0 | O81: 0 | P81: 0 | Q81: =IF(A81="","",IF(O81=0,0,1-P81/O81)) -> 0 | R81: 12
A82: =IF('Employee Master'!B82="","",'Employee Master'!B82) -> CAS-IH_1165 | B82: =IF('Employee Master'!B82="","",'Employee Master'!C82) -> Jatin.S | C82: =IF('Employee Master'!B82="","",'Employee Master'!D82) -> In-house | D82: =IF('Employee Master'!B82="","",'Employee Master'!E82) -> Sr. Manager | E82: =IF('Employee Master'!B82="","",'Employee Master'!F82) -> FP&A | F82: =IF('Employee Master'!B82="","",'Employee Master'!G82) -> Sachi Mazumdar | G82: 158.5 | H82: 158.5 | I82: =IF(A82="","",G82-H82) -> 0 | J82: =IF(A82="","",IF(H82=0,0,H82/(Settings!B6*12))) -> 0.082552083 | K82: 6 | L82: 3.5 | M82: 0 | N82: =IF(A82="","",IF(H82=0,0,M82/H82)) -> 0 | O82: 0 | P82: 0 | Q82: =IF(A82="","",IF(O82=0,0,1-P82/O82)) -> 0 | R82: 12
A83: =IF('Employee Master'!B83="","",'Employee Master'!B83) -> CASUS-IH_002 | B83: =IF('Employee Master'!B83="","",'Employee Master'!C83) -> Angela | C83: =IF('Employee Master'!B83="","",'Employee Master'!D83) -> In-house | D83: =IF('Employee Master'!B83="","",'Employee Master'!E83) -> Controller | E83: =IF('Employee Master'!B83="","",'Employee Master'!F83) -> Marketing | F83: =IF('Employee Master'!B83="","",'Employee Master'!G83) -> -- | G83: 177 | H83: 177 | I83: =IF(A83="","",G83-H83) -> 0 | J83: =IF(A83="","",IF(H83=0,0,H83/(Settings!B6*12))) -> 0.0921875 | K83: 1 | L83: 3.5 | M83: 0 | N83: =IF(A83="","",IF(H83=0,0,M83/H83)) -> 0 | O83: 0 | P83: 0 | Q83: =IF(A83="","",IF(O83=0,0,1-P83/O83)) -> 0 | R83: 12
A84: =IF('Employee Master'!B84="","",'Employee Master'!B84) -> CAS-RT_2392 | B84: =IF('Employee Master'!B84="","",'Employee Master'!C84) -> Harsh.G | C84: =IF('Employee Master'!B84="","",'Employee Master'!D84) -> Remote | D84: =IF('Employee Master'!B84="","",'Employee Master'!E84) -> Sr. Associate | E84: =IF('Employee Master'!B84="","",'Employee Master'!F84) -> Accounting | F84: =IF('Employee Master'!B84="","",'Employee Master'!G84) -> Ayushi | G84: 0 | H84: 0 | I84: =IF(A84="","",G84-H84) -> 0 | J84: =IF(A84="","",IF(H84=0,0,H84/(Settings!B6*12))) -> 0 | K84: 0 | L84: 3.5 | M84: 0 | N84: =IF(A84="","",IF(H84=0,0,M84/H84)) -> 0 | O84: 0 | P84: 0 | Q84: =IF(A84="","",IF(O84=0,0,1-P84/O84)) -> 0 | R84: 12
A85: =IF('Employee Master'!B85="","",'Employee Master'!B85) -> CAS-IH_1166 | B85: =IF('Employee Master'!B85="","",'Employee Master'!C85) -> Namya.S | C85: =IF('Employee Master'!B85="","",'Employee Master'!D85) -> In-house | D85: =IF('Employee Master'!B85="","",'Employee Master'!E85) -> Asst. Team Lead | E85: =IF('Employee Master'!B85="","",'Employee Master'!F85) -> Accounting | F85: =IF('Employee Master'!B85="","",'Employee Master'!G85) -> Jasleen.D | G85: 60 | H85: 60 | I85: =IF(A85="","",G85-H85) -> 0 | J85: =IF(A85="","",IF(H85=0,0,H85/(Settings!B6*12))) -> 0.03125 | K85: 4 | L85: 3.5 | M85: 0 | N85: =IF(A85="","",IF(H85=0,0,M85/H85)) -> 0 | O85: 0 | P85: 0 | Q85: =IF(A85="","",IF(O85=0,0,1-P85/O85)) -> 0 | R85: 12
A86: =IF('Employee Master'!B86="","",'Employee Master'!B86) -> CAS-RT_2393 | B86: =IF('Employee Master'!B86="","",'Employee Master'!C86) -> Kashish.B | C86: =IF('Employee Master'!B86="","",'Employee Master'!D86) -> Remote | D86: =IF('Employee Master'!B86="","",'Employee Master'!E86) -> Sr. Associate | E86: =IF('Employee Master'!B86="","",'Employee Master'!F86) -> Accounting | F86: =IF('Employee Master'!B86="","",'Employee Master'!G86) -> Nikita Shah | G86: 161.1 | H86: 161.1 | I86: =IF(A86="","",G86-H86) -> 0 | J86: =IF(A86="","",IF(H86=0,0,H86/(Settings!B6*12))) -> 0.08390625 | K86: 5 | L86: 3.5 | M86: 0 | N86: =IF(A86="","",IF(H86=0,0,M86/H86)) -> 0 | O86: 0 | P86: 0 | Q86: =IF(A86="","",IF(O86=0,0,1-P86/O86)) -> 0 | R86: 12
A87: =IF('Employee Master'!B87="","",'Employee Master'!B87) -> CAS-RT_2396 | B87: =IF('Employee Master'!B87="","",'Employee Master'!C87) -> Amishi.S | C87: =IF('Employee Master'!B87="","",'Employee Master'!D87) -> Remote | D87: =IF('Employee Master'!B87="","",'Employee Master'!E87) -> Sr. Associate | E87: =IF('Employee Master'!B87="","",'Employee Master'!F87) -> Accounting | F87: =IF('Employee Master'!B87="","",'Employee Master'!G87) -> Jasleen.D | G87: 163.2 | H87: 163.2 | I87: =IF(A87="","",G87-H87) -> 0 | J87: =IF(A87="","",IF(H87=0,0,H87/(Settings!B6*12))) -> 0.085 | K87: 3 | L87: 3.5 | M87: 0 | N87: =IF(A87="","",IF(H87=0,0,M87/H87)) -> 0 | O87: 0 | P87: 0 | Q87: =IF(A87="","",IF(O87=0,0,1-P87/O87)) -> 0 | R87: 12
A88: =IF('Employee Master'!B88="","",'Employee Master'!B88) -> CAS-RR_2372 | B88: =IF('Employee Master'!B88="","",'Employee Master'!C88) -> Harsh.V | C88: =IF('Employee Master'!B88="","",'Employee Master'!D88) -> Remote | D88: =IF('Employee Master'!B88="","",'Employee Master'!E88) -> Associate | E88: =IF('Employee Master'!B88="","",'Employee Master'!F88) -> Accounting | F88: =IF('Employee Master'!B88="","",'Employee Master'!G88) -> Jyoti | G88: 78.7 | H88: 78.7 | I88: =IF(A88="","",G88-H88) -> 0 | J88: =IF(A88="","",IF(H88=0,0,H88/(Settings!B6*12))) -> 0.040989583 | K88: 3 | L88: 3.5 | M88: 0 | N88: =IF(A88="","",IF(H88=0,0,M88/H88)) -> 0 | O88: 0 | P88: 0 | Q88: =IF(A88="","",IF(O88=0,0,1-P88/O88)) -> 0 | R88: 12
A89: =IF('Employee Master'!B89="","",'Employee Master'!B89) -> 209 | B89: =IF('Employee Master'!B89="","",'Employee Master'!C89) -> Ash | C89: =IF('Employee Master'!B89="","",'Employee Master'!D89) -> Remote | D89: =IF('Employee Master'!B89="","",'Employee Master'!E89) -> Controller | E89: =IF('Employee Master'!B89="","",'Employee Master'!F89) -> IT | F89: =IF('Employee Master'!B89="","",'Employee Master'!G89) -> -- | G89: 169.2 | H89: 169.2 | I89: =IF(A89="","",G89-H89) -> 0 | J89: =IF(A89="","",IF(H89=0,0,H89/(Settings!B6*12))) -> 0.088125 | K89: 2 | L89: 3.5 | M89: 0 | N89: =IF(A89="","",IF(H89=0,0,M89/H89)) -> 0 | O89: 0 | P89: 0 | Q89: =IF(A89="","",IF(O89=0,0,1-P89/O89)) -> 0 | R89: 12
A90: =IF('Employee Master'!B90="","",'Employee Master'!B90) -> CASCFO-IH-004 | B90: =IF('Employee Master'!B90="","",'Employee Master'!C90) -> Anshika.B | C90: =IF('Employee Master'!B90="","",'Employee Master'!D90) -> In-house | D90: =IF('Employee Master'!B90="","",'Employee Master'!E90) -> Associate | E90: =IF('Employee Master'!B90="","",'Employee Master'!F90) -> HR | F90: =IF('Employee Master'!B90="","",'Employee Master'!G90) -> Vinita Dagar | G90: 107.5 | H90: 102.5 | I90: =IF(A90="","",G90-H90) -> 5 | J90: =IF(A90="","",IF(H90=0,0,H90/(Settings!B6*12))) -> 0.053385417 | K90: 4 | L90: 3.5 | M90: 0 | N90: =IF(A90="","",IF(H90=0,0,M90/H90)) -> 0 | O90: 0 | P90: 0 | Q90: =IF(A90="","",IF(O90=0,0,1-P90/O90)) -> 0 | R90: 12
A91: =IF('Employee Master'!B91="","",'Employee Master'!B91) -> CASCFO-IH-005 | B91: =IF('Employee Master'!B91="","",'Employee Master'!C91) -> Deepak | C91: =IF('Employee Master'!B91="","",'Employee Master'!D91) -> In-house | D91: =IF('Employee Master'!B91="","",'Employee Master'!E91) -> Sr. Associate | E91: =IF('Employee Master'!B91="","",'Employee Master'!F91) -> HR | F91: =IF('Employee Master'!B91="","",'Employee Master'!G91) -> Vinita Dagar | G91: 0 | H91: 0 | I91: =IF(A91="","",G91-H91) -> 0 | J91: =IF(A91="","",IF(H91=0,0,H91/(Settings!B6*12))) -> 0 | K91: 0 | L91: 3.5 | M91: 0 | N91: =IF(A91="","",IF(H91=0,0,M91/H91)) -> 0 | O91: 0 | P91: 0 | Q91: =IF(A91="","",IF(O91=0,0,1-P91/O91)) -> 0 | R91: 12
A92: =IF('Employee Master'!B92="","",'Employee Master'!B92) -> CAS-RT_2401 | B92: =IF('Employee Master'!B92="","",'Employee Master'!C92) -> Simran. | C92: =IF('Employee Master'!B92="","",'Employee Master'!D92) -> Remote | D92: =IF('Employee Master'!B92="","",'Employee Master'!E92) -> Sr. Associate | E92: =IF('Employee Master'!B92="","",'Employee Master'!F92) -> Accounting | F92: =IF('Employee Master'!B92="","",'Employee Master'!G92) -> Nikita Shah | G92: 150 | H92: 150 | I92: =IF(A92="","",G92-H92) -> 0 | J92: =IF(A92="","",IF(H92=0,0,H92/(Settings!B6*12))) -> 0.078125 | K92: 1 | L92: 3.5 | M92: 0 | N92: =IF(A92="","",IF(H92=0,0,M92/H92)) -> 0 | O92: 0 | P92: 0 | Q92: =IF(A92="","",IF(O92=0,0,1-P92/O92)) -> 0 | R92: 12
A93: =IF('Employee Master'!B93="","",'Employee Master'!B93) -> CASUS-IH_003 | B93: =IF('Employee Master'!B93="","",'Employee Master'!C93) -> Marta | C93: =IF('Employee Master'!B93="","",'Employee Master'!D93) -> Remote | D93: =IF('Employee Master'!B93="","",'Employee Master'!E93) -> Associate | E93: =IF('Employee Master'!B93="","",'Employee Master'!F93) -> Marketing | F93: =IF('Employee Master'!B93="","",'Employee Master'!G93) -> Angela | G93: 0 | H93: 0 | I93: =IF(A93="","",G93-H93) -> 0 | J93: =IF(A93="","",IF(H93=0,0,H93/(Settings!B6*12))) -> 0 | K93: 0 | L93: 3.5 | M93: 0 | N93: =IF(A93="","",IF(H93=0,0,M93/H93)) -> 0 | O93: 0 | P93: 0 | Q93: =IF(A93="","",IF(O93=0,0,1-P93/O93)) -> 0 | R93: 12
A94: =IF('Employee Master'!B94="","",'Employee Master'!B94) -> CAS-IH_1170 | B94: =IF('Employee Master'!B94="","",'Employee Master'!C94) -> Sakshi.M | C94: =IF('Employee Master'!B94="","",'Employee Master'!D94) -> Remote | D94: =IF('Employee Master'!B94="","",'Employee Master'!E94) -> Manager | E94: =IF('Employee Master'!B94="","",'Employee Master'!F94) -> FP&A | F94: =IF('Employee Master'!B94="","",'Employee Master'!G94) -> Prachi Guglani | G94: 44.8 | H94: 44.8 | I94: =IF(A94="","",G94-H94) -> 0 | J94: =IF(A94="","",IF(H94=0,0,H94/(Settings!B6*12))) -> 0.023333333 | K94: 3 | L94: 3.5 | M94: 0 | N94: =IF(A94="","",IF(H94=0,0,M94/H94)) -> 0 | O94: 0 | P94: 0 | Q94: =IF(A94="","",IF(O94=0,0,1-P94/O94)) -> 0 | R94: 12
A95: =IF('Employee Master'!B95="","",'Employee Master'!B95) -> CASCFO**** | B95: =IF('Employee Master'!B95="","",'Employee Master'!C95) -> Tracey.G | C95: =IF('Employee Master'!B95="","",'Employee Master'!D95) -> Remote | D95: =IF('Employee Master'!B95="","",'Employee Master'!E95) -> Coo | E95: =IF('Employee Master'!B95="","",'Employee Master'!F95) -> Accounting, Individual Tax, Business Tax, VA | F95: =IF('Employee Master'!B95="","",'Employee Master'!G95) -> -- | G95: 175.3 | H95: 175.3 | I95: =IF(A95="","",G95-H95) -> 0 | J95: =IF(A95="","",IF(H95=0,0,H95/(Settings!B6*12))) -> 0.091302083 | K95: 5 | L95: 3.5 | M95: 0 | N95: =IF(A95="","",IF(H95=0,0,M95/H95)) -> 0 | O95: 0 | P95: 0 | Q95: =IF(A95="","",IF(O95=0,0,1-P95/O95)) -> 0 | R95: 12
A96: =IF('Employee Master'!B96="","",'Employee Master'!B96) -> CAS-IH_1171 | B96: =IF('Employee Master'!B96="","",'Employee Master'!C96) -> Khushboo.S | C96: =IF('Employee Master'!B96="","",'Employee Master'!D96) -> In-house | D96: =IF('Employee Master'!B96="","",'Employee Master'!E96) -> Manager | E96: =IF('Employee Master'!B96="","",'Employee Master'!F96) -> Accounting | F96: =IF('Employee Master'!B96="","",'Employee Master'!G96) -> Jasleen.D | G96: 16 | H96: 16 | I96: =IF(A96="","",G96-H96) -> 0 | J96: =IF(A96="","",IF(H96=0,0,H96/(Settings!B6*12))) -> 0.0083333333 | K96: 1 | L96: 3.5 | M96: 0 | N96: =IF(A96="","",IF(H96=0,0,M96/H96)) -> 0 | O96: 0 | P96: 0 | Q96: =IF(A96="","",IF(O96=0,0,1-P96/O96)) -> 0 | R96: 12
A97: =IF('Employee Master'!B97="","",'Employee Master'!B97) -> CAS-RT_2402 | B97: =IF('Employee Master'!B97="","",'Employee Master'!C97) -> Prerna.G | C97: =IF('Employee Master'!B97="","",'Employee Master'!D97) -> Remote | D97: =IF('Employee Master'!B97="","",'Employee Master'!E97) -> Manager | E97: =IF('Employee Master'!B97="","",'Employee Master'!F97) -> Accounting | F97: =IF('Employee Master'!B97="","",'Employee Master'!G97) -> Ayushi | G97: 167 | H97: 167 | I97: =IF(A97="","",G97-H97) -> 0 | J97: =IF(A97="","",IF(H97=0,0,H97/(Settings!B6*12))) -> 0.086979167 | K97: 1 | L97: 3.5 | M97: 0 | N97: =IF(A97="","",IF(H97=0,0,M97/H97)) -> 0 | O97: 0 | P97: 0 | Q97: =IF(A97="","",IF(O97=0,0,1-P97/O97)) -> 0 | R97: 12
A98: =IF('Employee Master'!B98="","",'Employee Master'!B98) -> CASCFO-IH-007 | B98: =IF('Employee Master'!B98="","",'Employee Master'!C98) -> Monika.M | C98: =IF('Employee Master'!B98="","",'Employee Master'!D98) -> In-house | D98: =IF('Employee Master'!B98="","",'Employee Master'!E98) -> Manager | E98: =IF('Employee Master'!B98="","",'Employee Master'!F98) -> HR | F98: =IF('Employee Master'!B98="","",'Employee Master'!G98) -> Vinita Dagar | G98: 0 | H98: 0 | I98: =IF(A98="","",G98-H98) -> 0 | J98: =IF(A98="","",IF(H98=0,0,H98/(Settings!B6*12))) -> 0 | K98: 0 | L98: 3.5 | M98: 0 | N98: =IF(A98="","",IF(H98=0,0,M98/H98)) -> 0 | O98: 0 | P98: 0 | Q98: =IF(A98="","",IF(O98=0,0,1-P98/O98)) -> 0 | R98: 12
A99: =IF('Employee Master'!B99="","",'Employee Master'!B99) -> CAS-RT_2403 | B99: =IF('Employee Master'!B99="","",'Employee Master'!C99) -> Richa.A | C99: =IF('Employee Master'!B99="","",'Employee Master'!D99) -> Remote | D99: =IF('Employee Master'!B99="","",'Employee Master'!E99) -> Sr. Associate | E99: =IF('Employee Master'!B99="","",'Employee Master'!F99) -> Accounting | F99: =IF('Employee Master'!B99="","",'Employee Master'!G99) -> Ayushi | G99: 184.3 | H99: 184.3 | I99: =IF(A99="","",G99-H99) -> 0 | J99: =IF(A99="","",IF(H99=0,0,H99/(Settings!B6*12))) -> 0.095989583 | K99: 2 | L99: 3.5 | M99: 0 | N99: =IF(A99="","",IF(H99=0,0,M99/H99)) -> 0 | O99: 0 | P99: 0 | Q99: =IF(A99="","",IF(O99=0,0,1-P99/O99)) -> 0 | R99: 12
A100: =IF('Employee Master'!B100="","",'Employee Master'!B100) -> CASUS-IH_004 | B100: =IF('Employee Master'!B100="","",'Employee Master'!C100) -> brandon | C100: =IF('Employee Master'!B100="","",'Employee Master'!D100) -> Remote | D100: =IF('Employee Master'!B100="","",'Employee Master'!E100) -> Marketing | E100: =IF('Employee Master'!B100="","",'Employee Master'!F100) -> Marketing | F100: =IF('Employee Master'!B100="","",'Employee Master'!G100) -> Angela | G100: 173.8 | H100: 173.8 | I100: =IF(A100="","",G100-H100) -> 0 | J100: =IF(A100="","",IF(H100=0,0,H100/(Settings!B6*12))) -> 0.090520833 | K100: 6 | L100: 3.5 | M100: 0 | N100: =IF(A100="","",IF(H100=0,0,M100/H100)) -> 0 | O100: 0 | P100: 0 | Q100: =IF(A100="","",IF(O100=0,0,1-P100/O100)) -> 0 | R100: 12
...

Sheet ⑦ Controller-Firm Map
A1: CONTROLLER → CPA FIRM MAPPING (INPUT)
A2: Paste your controller-to-CPA-firm assignments here. One row = one controller managing one firm's service. Updates Controller Team Analysis automatically.
A3: Controller Name | B3: CPA Firm Name | C3: Service Type | D3: Seats | E3: Status | F3: Billing USD (Auto) | G3: Billing INR (Auto) | H3: Revenue/Seat (Auto)
A4: Nikita Shah | B4: AB CAPSTONE GROUP | C4: Accounting | D4: 1.5 | E4: ACTIVE | F4: =IFERROR(VLOOKUP(B4,'③ Billing Input'!B$4:F$103,4,FALSE()),0) -> 0 | G4: =F4*Settings!B8 -> 0 | H4: =IF(D4=0,0,F4/D4) -> 0
A5: Nikita Shah | B5: ACE CPA | C5: Accounting | D5: 2 | E5: ACTIVE | F5: =IFERROR(VLOOKUP(B5,'③ Billing Input'!B$4:F$103,4,FALSE()),0) -> 3400 | G5: =F5*Settings!B8 -> 289000 | H5: =IF(D5=0,0,F5/D5) -> 1700
A6: Nikita Shah | B6: ACT NOW FINANCIAL SERVICES, LLC | C6: Accounting | D6: 0.5 | E6: ACTIVE | F6: =IFERROR(VLOOKUP(B6,'③ Billing Input'!B$4:F$103,4,FALSE()),0) -> 0 | G6: =F6*Settings!B8 -> 0 | H6: =IF(D6=0,0,F6/D6) -> 0
A7: Nikita Shah | B7: ACTION ACCOUNTING | C7: Accounting | D7: 1 | E7: ACTIVE | F7: =IFERROR(VLOOKUP(B7,'③ Billing Input'!B$4:F$103,4,FALSE()),0) -> 1200 | G7: =F7*Settings!B8 -> 102000 | H7: =IF(D7=0,0,F7/D7) -> 1200
A8: Nikita Shah | B8: BEAM ACCOUNTING INC | C8: Accounting | D8: 0.25 | E8: ACTIVE | F8: =IFERROR(VLOOKUP(B8,'③ Billing Input'!B$4:F$103,4,FALSE()),0) -> 650 | G8: =F8*Settings!B8 -> 55250 | H8: =IF(D8=0,0,F8/D8) -> 2600
A9: Ayushi | B9: BORISTAX INC | C9: Accounting | D9: 3 | E9: ACTIVE | F9: =IFERROR(VLOOKUP(B9,'③ Billing Input'!B$4:F$103,4,FALSE()),0) -> 0 | G9: =F9*Settings!B8 -> 0 | H9: =IF(D9=0,0,F9/D9) -> 0
A10: Nikita Shah | B10: CENTURION TAX AND ACCOUNTING | C10: Accounting | D10: 0.25 | E10: ACTIVE | F10: =IFERROR(VLOOKUP(B10,'③ Billing Input'!B$4:F$103,4,FALSE()),0) -> 0 | G10: =F10*Settings!B8 -> 0 | H10: =IF(D10=0,0,F10/D10) -> 0
A11: Nikita Shah | B11: CHRIS WHALEN CPA, LLC | C11: Accounting | D11: 1 | E11: ACTIVE | F11: =IFERROR(VLOOKUP(B11,'③ Billing Input'!B$4:F$103,4,FALSE()),0) -> 1880 | G11: =F11*Settings!B8 -> 159800 | H11: =IF(D11=0,0,F11/D11) -> 1880
A12: Nikita Shah | B12: H J EDWARDS | C12: Accounting | D12: 0.5 | E12: ACTIVE | F12: =IFERROR(VLOOKUP(B12,'③ Billing Input'!B$4:F$103,4,FALSE()),0) -> 600 | G12: =F12*Settings!B8 -> 51000 | H12: =IF(D12=0,0,F12/D12) -> 1200
A13: Nikita Shah | B13: JOHNSON & ROBINSON LLC | C13: Accounting | D13: 0.5 | E13: ACTIVE | F13: =IFERROR(VLOOKUP(B13,'③ Billing Input'!B$4:F$103,4,FALSE()),0) -> 800 | G13: =F13*Settings!B8 -> 68000 | H13: =IF(D13=0,0,F13/D13) -> 1600
A14: Nikita Shah | B14: LAST MILE DELIVERY GROUP | C14: Accounting | D14: 0.5 | E14: ACTIVE | F14: =IFERROR(VLOOKUP(B14,'③ Billing Input'!B$4:F$103,4,FALSE()),0) -> 0 | G14: =F14*Settings!B8 -> 0 | H14: =IF(D14=0,0,F14/D14) -> 0
A15: Nikita Shah | B15: LEANCORP ACCOUNTING | C15: Accounting | D15: 0.5 | E15: ACTIVE | F15: =IFERROR(VLOOKUP(B15,'③ Billing Input'!B$4:F$103,4,FALSE()),0) -> 0 | G15: =F15*Settings!B8 -> 0 | H15: =IF(D15=0,0,F15/D15) -> 0
A16: Nikita Shah | B16: MARTIN D. EISENSTEIN, CPA | C16: Accounting | D16: 0.5 | E16: ACTIVE | F16: =IFERROR(VLOOKUP(B16,'③ Billing Input'!B$4:F$103,4,FALSE()),0) -> 0 | G16: =F16*Settings!B8 -> 0 | H16: =IF(D16=0,0,F16/D16) -> 0
A17: Nikita Shah | B17: MCFADDEN ACCOUNTING | C17: Accounting | D17: 1 | E17: ACTIVE | F17: =IFERROR(VLOOKUP(B17,'③ Billing Input'!B$4:F$103,4,FALSE()),0) -> 1000 | G17: =F17*Settings!B8 -> 85000 | H17: =IF(D17=0,0,F17/D17) -> 1000
A18: Nikita Shah | B18: PORCHEA & LOTT ACCOUNTING | C18: Accounting | D18: 0.5 | E18: ACTIVE | F18: =IFERROR(VLOOKUP(B18,'③ Billing Input'!B$4:F$103,4,FALSE()),0) -> 500 | G18: =F18*Settings!B8 -> 42500 | H18: =IF(D18=0,0,F18/D18) -> 1000
A19: Nikita Shah | B19: PW ADVISORS LLC | C19: Accounting | D19: 2 | E19: ACTIVE | F19: =IFERROR(VLOOKUP(B19,'③ Billing Input'!B$4:F$103,4,FALSE()),0) -> 3600 | G19: =F19*Settings!B8 -> 306000 | H19: =IF(D19=0,0,F19/D19) -> 1800
A20: Nikita Shah | B20: RATHEL'S ACCOUNTING SERVICE, INC | C20: Accounting | D20: 1 | E20: ACTIVE | F20: =IFERROR(VLOOKUP(B20,'③ Billing Input'!B$4:F$103,4,FALSE()),0) -> 0 | G20: =F20*Settings!B8 -> 0 | H20: =IF(D20=0,0,F20/D20) -> 0
A21: Nikita Shah | B21: ROSEN KUSLANSKY CPA PC | C21: Accounting | D21: 1 | E21: ACTIVE | F21: =IFERROR(VLOOKUP(B21,'③ Billing Input'!B$4:F$103,4,FALSE()),0) -> 1000 | G21: =F21*Settings!B8 -> 85000 | H21: =IF(D21=0,0,F21/D21) -> 1000
A22: Nikita Shah | B22: SFSG BILLING PROJECT | C22: Accounting | D22: 1.25 | E22: ACTIVE | F22: =IFERROR(VLOOKUP(B22,'③ Billing Input'!B$4:F$103,4,FALSE()),0) -> 0 | G22: =F22*Settings!B8 -> 0 | H22: =IF(D22=0,0,F22/D22) -> 0
A23: Jyoti | B23: SOUTH FLORIDA SECURITY GROUP | C23: Accounting | D23: 2 | E23: ACTIVE | F23: =IFERROR(VLOOKUP(B23,'③ Billing Input'!B$4:F$103,4,FALSE()),0) -> 2320 | G23: =F23*Settings!B8 -> 197200 | H23: =IF(D23=0,0,F23/D23) -> 1160
A24: Nikita Shah | B24: TAX GEEK LLC | C24: Accounting | D24: 1 | E24: ACTIVE | F24: =IFERROR(VLOOKUP(B24,'③ Billing Input'!B$4:F$103,4,FALSE()),0) -> 1800 | G24: =F24*Settings!B8 -> 153000 | H24: =IF(D24=0,0,F24/D24) -> 1800
A25: Nikita Shah | B25: THE PROFIT SCALE THRIVE | C25: Accounting | D25: 0.5 | E25: ACTIVE | F25: =IFERROR(VLOOKUP(B25,'③ Billing Input'!B$4:F$103,4,FALSE()),0) -> 600 | G25: =F25*Settings!B8 -> 51000 | H25: =IF(D25=0,0,F25/D25) -> 1200
A26: Nikita Shah | B26: THINKING MAPS, INC. | C26: Accounting | D26: 2 | E26: ACTIVE | F26: =IFERROR(VLOOKUP(B26,'③ Billing Input'!B$4:F$103,4,FALSE()),0) -> 2600 | G26: =F26*Settings!B8 -> 221000 | H26: =IF(D26=0,0,F26/D26) -> 1300
A27: Nikita Shah | B27: TREE OF LIFE FUNDING INC | C27: Accounting | D27: 1 | E27: ACTIVE | F27: =IFERROR(VLOOKUP(B27,'③ Billing Input'!B$4:F$103,4,FALSE()),0) -> 0 | G27: =F27*Settings!B8 -> 0 | H27: =IF(D27=0,0,F27/D27) -> 0
A28: Nikita Shah | B28: WE ARE QUADRANT | C28: Accounting | D28: 1.5 | E28: ACTIVE | F28: =IFERROR(VLOOKUP(B28,'③ Billing Input'!B$4:F$103,4,FALSE()),0) -> 0 | G28: =F28*Settings!B8 -> 0 | H28: =IF(D28=0,0,F28/D28) -> 0
A29: Nikita Shah | B29: WIGGS CPA TAX & ACCOUNTING | C29: Accounting | D29: 0.5 | E29: ACTIVE | F29: =IFERROR(VLOOKUP(B29,'③ Billing Input'!B$4:F$103,4,FALSE()),0) -> 600 | G29: =F29*Settings!B8 -> 51000 | H29: =IF(D29=0,0,F29/D29) -> 1200
A30: Nikita Shah | B30: XPERT BOOKKEEPING LLC | C30: Accounting | D30: 1 | E30: ACTIVE | F30: =IFERROR(VLOOKUP(B30,'③ Billing Input'!B$4:F$103,4,FALSE()),0) -> 1100 | G30: =F30*Settings!B8 -> 93500 | H30: =IF(D30=0,0,F30/D30) -> 1100
A31: Jasleen.D | B31: 4P TAXES LLC | C31: Accounting | D31: 1 | E31: ACTIVE | F31: =IFERROR(VLOOKUP(B31,'③ Billing Input'!B$4:F$103,4,FALSE()),0) -> 1200 | G31: =F31*Settings!B8 -> 102000 | H31: =IF(D31=0,0,F31/D31) -> 1200
A32: Jasleen.D | B32: ABACUS BUSINESS SOLUTIONS, LLC | C32: Accounting | D32: 4 | E32: ACTIVE | F32: =IFERROR(VLOOKUP(B32,'③ Billing Input'!B$4:F$103,4,FALSE()),0) -> 5800 | G32: =F32*Settings!B8 -> 493000 | H32: =IF(D32=0,0,F32/D32) -> 1450
A33: Jasleen.D | B33: ANCIENT CITY ACCOUNTING LLC | C33: Accounting | D33: 1 | E33: ACTIVE | F33: =IFERROR(VLOOKUP(B33,'③ Billing Input'!B$4:F$103,4,FALSE()),0) -> 1200 | G33: =F33*Settings!B8 -> 102000 | H33: =IF(D33=0,0,F33/D33) -> 1200
A34: Jasleen.D | B34: BRADLEY FINANCIAL SERVICES LLC | C34: Accounting | D34: 0.5 | E34: ACTIVE | F34: =IFERROR(VLOOKUP(B34,'③ Billing Input'!B$4:F$103,4,FALSE()),0) -> 700 | G34: =F34*Settings!B8 -> 59500 | H34: =IF(D34=0,0,F34/D34) -> 1400
A35: Jasleen.D | B35: BRIGHTSKIES BUSINESS SERVICES, LLC | C35: Accounting | D35: 2.5 | E35: ACTIVE | F35: =IFERROR(VLOOKUP(B35,'③ Billing Input'!B$4:F$103,4,FALSE()),0) -> 2600 | G35: =F35*Settings!B8 -> 221000 | H35: =IF(D35=0,0,F35/D35) -> 1040
A36: Jasleen.D | B36: BUSINESS NAVIGATORS LLC | C36: Accounting | D36: 1 | E36: ACTIVE | F36: =IFERROR(VLOOKUP(B36,'③ Billing Input'!B$4:F$103,4,FALSE()),0) -> 1000 | G36: =F36*Settings!B8 -> 85000 | H36: =IF(D36=0,0,F36/D36) -> 1000
A37: Jasleen.D | B37: CASCFO Advisory- United States | C37: Accounting | D37: 1 | E37: ACTIVE | F37: =IFERROR(VLOOKUP(B37,'③ Billing Input'!B$4:F$103,4,FALSE()),0) -> 0 | G37: =F37*Settings!B8 -> 0 | H37: =IF(D37=0,0,F37/D37) -> 0
A38: Jasleen.D | B38: DEDICATED BOOKS LLC | C38: Accounting | D38: 1 | E38: ACTIVE | F38: =IFERROR(VLOOKUP(B38,'③ Billing Input'!B$4:F$103,4,FALSE()),0) -> 1400 | G38: =F38*Settings!B8 -> 119000 | H38: =IF(D38=0,0,F38/D38) -> 1400
A39: Jasleen.D | B39: EVERMORE FINANCIAL SERVICES LLC | C39: Accounting | D39: 1.5 | E39: ACTIVE | F39: =IFERROR(VLOOKUP(B39,'③ Billing Input'!B$4:F$103,4,FALSE()),0) -> 2000 | G39: =F39*Settings!B8 -> 170000 | H39: =IF(D39=0,0,F39/D39) -> 1333.3333
A40: Jyoti | B40: FULL COMPLIANCE, LLC | C40: Accounting | D40: 2 | E40: ACTIVE | F40: =IFERROR(VLOOKUP(B40,'③ Billing Input'!B$4:F$103,4,FALSE()),0) -> 2600 | G40: =F40*Settings!B8 -> 221000 | H40: =IF(D40=0,0,F40/D40) -> 1300
A41: Jasleen.D | B41: HIA TAX | C41: Accounting | D41: 1 | E41: ACTIVE | F41: =IFERROR(VLOOKUP(B41,'③ Billing Input'!B$4:F$103,4,FALSE()),0) -> 1200 | G41: =F41*Settings!B8 -> 102000 | H41: =IF(D41=0,0,F41/D41) -> 1200
A42: Jasleen.D | B42: IAM ACCOUNTING LLC | C42: Accounting | D42: 3 | E42: ACTIVE | F42: =IFERROR(VLOOKUP(B42,'③ Billing Input'!B$4:F$103,4,FALSE()),0) -> 0 | G42: =F42*Settings!B8 -> 0 | H42: =IF(D42=0,0,F42/D42) -> 0
A43: Jasleen.D | B43: INVENT WEALTH, CPA | C43: Accounting | D43: 2 | E43: ACTIVE | F43: =IFERROR(VLOOKUP(B43,'③ Billing Input'!B$4:F$103,4,FALSE()),0) -> 2640 | G43: =F43*Settings!B8 -> 224400 | H43: =IF(D43=0,0,F43/D43) -> 1320
A44: Jasleen.D | B44: MAINSPRING SOLUTIONS | C44: Accounting | D44: 1 | E44: ACTIVE | F44: =IFERROR(VLOOKUP(B44,'③ Billing Input'!B$4:F$103,4,FALSE()),0) -> 1200 | G44: =F44*Settings!B8 -> 102000 | H44: =IF(D44=0,0,F44/D44) -> 1200
A45: Jasleen.D | B45: MATHESON & ASSOCIATES | C45: Accounting | D45: 1 | E45: ACTIVE | F45: =IFERROR(VLOOKUP(B45,'③ Billing Input'!B$4:F$103,4,FALSE()),0) -> 1200 | G45: =F45*Settings!B8 -> 102000 | H45: =IF(D45=0,0,F45/D45) -> 1200
A46: Jasleen.D | B46: NEWELL TAYLOR CPA | C46: Accounting | D46: 1 | E46: ACTIVE | F46: =IFERROR(VLOOKUP(B46,'③ Billing Input'!B$4:F$103,4,FALSE()),0) -> 1000 | G46: =F46*Settings!B8 -> 85000 | H46: =IF(D46=0,0,F46/D46) -> 1000
A47: Jasleen.D | B47: RRAW CPA LLP | C47: Accounting | D47: 0.25 | E47: ACTIVE | F47: =IFERROR(VLOOKUP(B47,'③ Billing Input'!B$4:F$103,4,FALSE()),0) -> 400 | G47: =F47*Settings!B8 -> 34000 | H47: =IF(D47=0,0,F47/D47) -> 1600
A48: Anshul.O | B48: WB MORROW | C48: Accounting | D48: 1 | E48: ACTIVE | F48: =IFERROR(VLOOKUP(B48,'③ Billing Input'!B$4:F$103,4,FALSE()),0) -> 1800 | G48: =F48*Settings!B8 -> 153000 | H48: =IF(D48=0,0,F48/D48) -> 1800
A49: Ayushi | B49: CLARK FINANCIALS | C49: Accounting | D49: 0.5 | E49: ACTIVE | F49: =IFERROR(VLOOKUP(B49,'③ Billing Input'!B$4:F$103,4,FALSE()),0) -> 700 | G49: =F49*Settings!B8 -> 59500 | H49: =IF(D49=0,0,F49/D49) -> 1400
A50: Ayushi | B50: DOR BUSINESS GROUP LLC | C50: Accounting | D50: 0.25 | E50: ACTIVE | F50: =IFERROR(VLOOKUP(B50,'③ Billing Input'!B$4:F$103,4,FALSE()),0) -> 350 | G50: =F50*Settings!B8 -> 29750 | H50: =IF(D50=0,0,F50/D50) -> 1400
A51: Ayushi | B51: HELLO ACCOUNTAX | C51: Accounting | D51: 0.5 | E51: ACTIVE | F51: =IFERROR(VLOOKUP(B51,'③ Billing Input'!B$4:F$103,4,FALSE()),0) -> 600 | G51: =F51*Settings!B8 -> 51000 | H51: =IF(D51=0,0,F51/D51) -> 1200
A52: Ayushi | B52: INNOVATIVE CONSULTING & SOLUTIONS, LLC | C52: Accounting | D52: 0.5 | E52: ACTIVE | F52: =IFERROR(VLOOKUP(B52,'③ Billing Input'!B$4:F$103,4,FALSE()),0) -> 450 | G52: =F52*Settings!B8 -> 38250 | H52: =IF(D52=0,0,F52/D52) -> 900
A53: Ayushi | B53: LIFETIME FUNDING, LLC | C53: Accounting | D53: 1.5 | E53: ACTIVE | F53: =IFERROR(VLOOKUP(B53,'③ Billing Input'!B$4:F$103,4,FALSE()),0) -> 1900 | G53: =F53*Settings!B8 -> 161500 | H53: =IF(D53=0,0,F53/D53) -> 1266.6667
A54: Ayushi | B54: MERAKI ACCOUNTING & TAX LLC | C54: Accounting | D54: 0.5 | E54: ACTIVE | F54: =IFERROR(VLOOKUP(B54,'③ Billing Input'!B$4:F$103,4,FALSE()),0) -> 600 | G54: =F54*Settings!B8 -> 51000 | H54: =IF(D54=0,0,F54/D54) -> 1200
A55: Ayushi | B55: NATIONAL TAX CENTERS, LLC | C55: Accounting | D55: 2 | E55: ACTIVE | F55: =IFERROR(VLOOKUP(B55,'③ Billing Input'!B$4:F$103,4,FALSE()),0) -> 4000 | G55: =F55*Settings!B8 -> 340000 | H55: =IF(D55=0,0,F55/D55) -> 2000
A56: Ayushi | B56: NEW AGE IRON WORKS, INC. | C56: Accounting | D56: 1 | E56: ACTIVE | F56: =IFERROR(VLOOKUP(B56,'③ Billing Input'!B$4:F$103,4,FALSE()),0) -> 1000 | G56: =F56*Settings!B8 -> 85000 | H56: =IF(D56=0,0,F56/D56) -> 1000
A57: Ayushi | B57: NUMBER NUTTZ CONSULTING | C57: Accounting | D57: 0.25 | E57: ACTIVE | F57: =IFERROR(VLOOKUP(B57,'③ Billing Input'!B$4:F$103,4,FALSE()),0) -> 450 | G57: =F57*Settings!B8 -> 38250 | H57: =IF(D57=0,0,F57/D57) -> 1800
A58: Ayushi | B58: RTW XXACT ENTERPRISES, LLC | C58: Accounting | D58: 1 | E58: ACTIVE | F58: =IFERROR(VLOOKUP(B58,'③ Billing Input'!B$4:F$103,4,FALSE()),0) -> 0 | G58: =F58*Settings!B8 -> 0 | H58: =IF(D58=0,0,F58/D58) -> 0
A59: Ayushi | B59: TRI SCAPES | C59: Accounting | D59: 2 | E59: ACTIVE | F59: =IFERROR(VLOOKUP(B59,'③ Billing Input'!B$4:F$103,4,FALSE()),0) -> 0 | G59: =F59*Settings!B8 -> 0 | H59: =IF(D59=0,0,F59/D59) -> 0
A60: Ayushi | B60: WE ARE QUADRANT | C60: Accounting | D60: 1 | E60: ACTIVE | F60: =IFERROR(VLOOKUP(B60,'③ Billing Input'!B$4:F$103,4,FALSE()),0) -> 0 | G60: =F60*Settings!B8 -> 0 | H60: =IF(D60=0,0,F60/D60) -> 0
A61: Ammie | B61: ACTION ACCOUNTING | C61: Individual Tax | D61: 0.35 | E61: ACTIVE | F61: =IFERROR(VLOOKUP(B61,'③ Billing Input'!B$4:F$103,4,FALSE()),0) -> 1200 | G61: =F61*Settings!B8 -> 102000 | H61: =IF(D61=0,0,F61/D61) -> 3428.5714
A62: Ammie | B62: CHRIS WHALEN CPA, LLC | C62: Individual Tax | D62: 1 | E62: ACTIVE | F62: =IFERROR(VLOOKUP(B62,'③ Billing Input'!B$4:F$103,4,FALSE()),0) -> 1880 | G62: =F62*Settings!B8 -> 159800 | H62: =IF(D62=0,0,F62/D62) -> 1880
A63: Ammie | B63: FULL COMPLIANCE, LLC | C63: Individual Tax | D63: 0.7 | E63: ACTIVE | F63: =IFERROR(VLOOKUP(B63,'③ Billing Input'!B$4:F$103,4,FALSE()),0) -> 2600 | G63: =F63*Settings!B8 -> 221000 | H63: =IF(D63=0,0,F63/D63) -> 3714.2857
A64: Ammie | B64: INVENT WEALTH, CPA | C64: Individual Tax | D64: 0.7 | E64: ACTIVE | F64: =IFERROR(VLOOKUP(B64,'③ Billing Input'!B$4:F$103,4,FALSE()),0) -> 2640 | G64: =F64*Settings!B8 -> 224400 | H64: =IF(D64=0,0,F64/D64) -> 3771.4286
A65: Ammie | B65: jmWILLIAMS, CPA, LLP | C65: Individual Tax | D65: 0.7 | E65: ACTIVE | F65: =IFERROR(VLOOKUP(B65,'③ Billing Input'!B$4:F$103,4,FALSE()),0) -> 0 | G65: =F65*Settings!B8 -> 0 | H65: =IF(D65=0,0,F65/D65) -> 0
A66: Ammie | B66: MARTIN D. EISENSTEIN, CPA | C66: Individual Tax | D66: 0.7 | E66: ACTIVE | F66: =IFERROR(VLOOKUP(B66,'③ Billing Input'!B$4:F$103,4,FALSE()),0) -> 0 | G66: =F66*Settings!B8 -> 0 | H66: =IF(D66=0,0,F66/D66) -> 0
A67: Ammie | B67: PROVISION ACCOUNTING SOLUTIONS | C67: Individual Tax | D67: 0.35 | E67: ACTIVE | F67: =IFERROR(VLOOKUP(B67,'③ Billing Input'!B$4:F$103,4,FALSE()),0) -> 250 | G67: =F67*Settings!B8 -> 21250 | H67: =IF(D67=0,0,F67/D67) -> 714.28571
A68: Ammie | B68: PW ADVISORS LLC | C68: Individual Tax | D68: 0.7 | E68: ACTIVE | F68: =IFERROR(VLOOKUP(B68,'③ Billing Input'!B$4:F$103,4,FALSE()),0) -> 3600 | G68: =F68*Settings!B8 -> 306000 | H68: =IF(D68=0,0,F68/D68) -> 5142.8571
A69: Ammie | B69: TAX GEEK LLC | C69: Individual Tax | D69: 0.35 | E69: ACTIVE | F69: =IFERROR(VLOOKUP(B69,'③ Billing Input'!B$4:F$103,4,FALSE()),0) -> 1800 | G69: =F69*Settings!B8 -> 153000 | H69: =IF(D69=0,0,F69/D69) -> 5142.8571
A70: Jyoti | B70: ACTION ACCOUNTING | C70: Business Tax | D70: 0.15 | E70: ACTIVE | F70: =IFERROR(VLOOKUP(B70,'③ Billing Input'!B$4:F$103,4,FALSE()),0) -> 1200 | G70: =F70*Settings!B8 -> 102000 | H70: =IF(D70=0,0,F70/D70) -> 8000
A71: Jyoti | B71: FULL COMPLIANCE, LLC | C71: Business Tax | D71: 0.3 | E71: ACTIVE | F71: =IFERROR(VLOOKUP(B71,'③ Billing Input'!B$4:F$103,4,FALSE()),0) -> 2600 | G71: =F71*Settings!B8 -> 221000 | H71: =IF(D71=0,0,F71/D71) -> 8666.6667
A72: Jyoti | B72: INVENT WEALTH, CPA | C72: Business Tax | D72: 0.3 | E72: ACTIVE | F72: =IFERROR(VLOOKUP(B72,'③ Billing Input'!B$4:F$103,4,FALSE()),0) -> 2640 | G72: =F72*Settings!B8 -> 224400 | H72: =IF(D72=0,0,F72/D72) -> 8800
A73: Jyoti | B73: jmWILLIAMS, CPA, LLP | C73: Business Tax | D73: 0.3 | E73: ACTIVE | F73: =IFERROR(VLOOKUP(B73,'③ Billing Input'!B$4:F$103,4,FALSE()),0) -> 0 | G73: =F73*Settings!B8 -> 0 | H73: =IF(D73=0,0,F73/D73) -> 0
A74: Jyoti | B74: MARTIN D. EISENSTEIN, CPA | C74: Business Tax | D74: 0.3 | E74: ACTIVE | F74: =IFERROR(VLOOKUP(B74,'③ Billing Input'!B$4:F$103,4,FALSE()),0) -> 0 | G74: =F74*Settings!B8 -> 0 | H74: =IF(D74=0,0,F74/D74) -> 0
A75: Jyoti | B75: PROVISION ACCOUNTING SOLUTIONS | C75: Business Tax | D75: 0.15 | E75: ACTIVE | F75: =IFERROR(VLOOKUP(B75,'③ Billing Input'!B$4:F$103,4,FALSE()),0) -> 250 | G75: =F75*Settings!B8 -> 21250 | H75: =IF(D75=0,0,F75/D75) -> 1666.6667
A76: Jyoti | B76: PW ADVISORS LLC | C76: Business Tax | D76: 0.3 | E76: ACTIVE | F76: =IFERROR(VLOOKUP(B76,'③ Billing Input'!B$4:F$103,4,FALSE()),0) -> 3600 | G76: =F76*Settings!B8 -> 306000 | H76: =IF(D76=0,0,F76/D76) -> 12000
A77: Jyoti | B77: TAX GEEK LLC | C77: Business Tax | D77: 0.15 | E77: ACTIVE | F77: =IFERROR(VLOOKUP(B77,'③ Billing Input'!B$4:F$103,4,FALSE()),0) -> 1800 | G77: =F77*Settings!B8 -> 153000 | H77: =IF(D77=0,0,F77/D77) -> 12000
A78: Jyoti | B78: 406 CONSULTING LLC | C78: Business Tax | D78: 0.6 | E78: ACTIVE | F78: =IFERROR(VLOOKUP(B78,'③ Billing Input'!B$4:F$103,4,FALSE()),0) -> 3600 | G78: =F78*Settings!B8 -> 306000 | H78: =IF(D78=0,0,F78/D78) -> 6000
A79: Ammie | B79: 406 CONSULTING LLC | C79: Individual Tax | D79: 1.4 | E79: ACTIVE | F79: =IFERROR(VLOOKUP(B79,'③ Billing Input'!B$4:F$103,4,FALSE()),0) -> 3600 | G79: =F79*Settings!B8 -> 306000 | H79: =IF(D79=0,0,F79/D79) -> 2571.4286
A80: Sachi Mazumdar | B80: AMI US HOLDING INC. | C80: FP&A | D80: 5 | E80: ACTIVE | F80: =IFERROR(VLOOKUP(B80,'③ Billing Input'!B$4:F$103,4,FALSE()),0) -> 0 | G80: =F80*Settings!B8 -> 0 | H80: =IF(D80=0,0,F80/D80) -> 0
A81: Vinita Dagar | B81: AMI US HOLDING INC. | C81: HR | D81: 1 | E81: ACTIVE | F81: =IFERROR(VLOOKUP(B81,'③ Billing Input'!B$4:F$103,4,FALSE()),0) -> 0 | G81: =F81*Settings!B8 -> 0 | H81: =IF(D81=0,0,F81/D81) -> 0
A82: Ayushi | B82: COHEN AND ASSOCIATES | C82: Accounting | D82: 0.5 | E82: ACTIVE | F82: =IFERROR(VLOOKUP(B82,'③ Billing Input'!B$4:F$103,4,FALSE()),0) -> 0 | G82: =F82*Settings!B8 -> 0 | H82: =IF(D82=0,0,F82/D82) -> 0
A83: Snehal Kothari | B83: Fleming Accounting Solutions | C83: Accounting | D83: 1 | E83: ACTIVE | F83: =IFERROR(VLOOKUP(B83,'③ Billing Input'!B$4:F$103,4,FALSE()),0) -> 3000 | G83: =F83*Settings!B8 -> 255000 | H83: =IF(D83=0,0,F83/D83) -> 3000
A84: Jyoti | B84: Fleming Accounting Solutions | C84: Business Tax | D84: 0.5 | E84: ACTIVE | F84: =IFERROR(VLOOKUP(B84,'③ Billing Input'!B$4:F$103,4,FALSE()),0) -> 3000 | G84: =F84*Settings!B8 -> 255000 | H84: =IF(D84=0,0,F84/D84) -> 6000
A85: Ammie | B85: Fleming Accounting Solutions | C85: Individual Tax | D85: 0.5 | E85: ACTIVE | F85: =IFERROR(VLOOKUP(B85,'③ Billing Input'!B$4:F$103,4,FALSE()),0) -> 3000 | G85: =F85*Settings!B8 -> 255000 | H85: =IF(D85=0,0,F85/D85) -> 6000
A86: Jyoti | B86: FULL COMPLIANCE, LLC | C86: VA | D86: 1 | E86: ACTIVE | F86: =IFERROR(VLOOKUP(B86,'③ Billing Input'!B$4:F$103,4,FALSE()),0) -> 2600 | G86: =F86*Settings!B8 -> 221000 | H86: =IF(D86=0,0,F86/D86) -> 2600
A87: Nikita Shah | B87: MARTIN D. EISENSTEIN, CPA | C87: VA | D87: 0.25 | E87: ACTIVE | F87: =IFERROR(VLOOKUP(B87,'③ Billing Input'!B$4:F$103,4,FALSE()),0) -> 0 | G87: =F87*Settings!B8 -> 0 | H87: =IF(D87=0,0,F87/D87) -> 0
A88: Jyoti | B88: MEJIA & ASSOCIATES, INC. | C88: Accounting | D88: 1 | E88: ACTIVE | F88: =IFERROR(VLOOKUP(B88,'③ Billing Input'!B$4:F$103,4,FALSE()),0) -> 1800 | G88: =F88*Settings!B8 -> 153000 | H88: =IF(D88=0,0,F88/D88) -> 1800
A89: Tithi Gandhi | B89: ONE KOSMOS, INC. | C89: FP&A | D89: 0.75 | E89: ACTIVE | F89: =IFERROR(VLOOKUP(B89,'③ Billing Input'!B$4:F$103,4,FALSE()),0) -> 8300 | G89: =F89*Settings!B8 -> 705500 | H89: =IF(D89=0,0,F89/D89) -> 11066.667
A90: Tithi Gandhi | B90: ONE KOSMOS, INC. | C90: FP&A | D90: 1 | E90: ACTIVE | F90: =IFERROR(VLOOKUP(B90,'③ Billing Input'!B$4:F$103,4,FALSE()),0) -> 8300 | G90: =F90*Settings!B8 -> 705500 | H90: =IF(D90=0,0,F90/D90) -> 8300
A91: Prachi Guglani | B91: TRI SCAPES | C91: FP&A | D91: 2 | E91: ACTIVE | F91: =IFERROR(VLOOKUP(B91,'③ Billing Input'!B$4:F$103,4,FALSE()),0) -> 0 | G91: =F91*Settings!B8 -> 0 | H91: =IF(D91=0,0,F91/D91) -> 0
F92: =IF(A92="","",IFERROR(VLOOKUP(B92,'③ Billing Input'!B$4:F$103,4,FALSE()),0)) | G92: =IF(A92="","",F92*Settings!B8) | H92: =IF(A92="","",IF(D92=0,0,F92/D92))
F93: =IF(A93="","",IFERROR(VLOOKUP(B93,'③ Billing Input'!B$4:F$103,4,FALSE()),0)) | G93: =IF(A93="","",F93*Settings!B8) | H93: =IF(A93="","",IF(D93=0,0,F93/D93))
F94: =IF(A94="","",IFERROR(VLOOKUP(B94,'③ Billing Input'!B$4:F$103,4,FALSE()),0)) | G94: =IF(A94="","",F94*Settings!B8) | H94: =IF(A94="","",IF(D94=0,0,F94/D94))
F95: =IF(A95="","",IFERROR(VLOOKUP(B95,'③ Billing Input'!B$4:F$103,4,FALSE()),0)) | G95: =IF(A95="","",F95*Settings!B8) | H95: =IF(A95="","",IF(D95=0,0,F95/D95))
F96: =IF(A96="","",IFERROR(VLOOKUP(B96,'③ Billing Input'!B$4:F$103,4,FALSE()),0)) | G96: =IF(A96="","",F96*Settings!B8) | H96: =IF(A96="","",IF(D96=0,0,F96/D96))
F97: =IF(A97="","",IFERROR(VLOOKUP(B97,'③ Billing Input'!B$4:F$103,4,FALSE()),0)) | G97: =IF(A97="","",F97*Settings!B8) | H97: =IF(A97="","",IF(D97=0,0,F97/D97))
F98: =IF(A98="","",IFERROR(VLOOKUP(B98,'③ Billing Input'!B$4:F$103,4,FALSE()),0)) | G98: =IF(A98="","",F98*Settings!B8) | H98: =IF(A98="","",IF(D98=0,0,F98/D98))
F99: =IF(A99="","",IFERROR(VLOOKUP(B99,'③ Billing Input'!B$4:F$103,4,FALSE()),0)) | G99: =IF(A99="","",F99*Settings!B8) | H99: =IF(A99="","",IF(D99=0,0,F99/D99))
F100: =IF(A100="","",IFERROR(VLOOKUP(B100,'③ Billing Input'!B$4:F$103,4,FALSE()),0)) | G100: =IF(A100="","",F100*Settings!B8) | H100: =IF(A100="","",IF(D100=0,0,F100/D100))
...

Sheet Employee Master
A1: EMPLOYEE MASTER — Auto-Generated from Timelog + Salary Inputs
A2: DO NOT EDIT — This sheet auto-updates when you change Timelog or Salary input sheets
A3: S.No | B3: Employee ID | C3: Employee Name | D3: Employment Type | E3: Designation | F3: Department | G3: Controller | H3: Reporting Manager | I3: Total Hours | J3: Billable Hours | K3: Standard Hours | L3: Utilization % | M3: Gross Pay (₹) | N3: Hourly Prof. Fee (₹) | O3: Effective Hourly Rate (₹) | P3: Cost/Billable Hr (₹) | Q3: Efficiency Score | R3: Status
A4: =IF('① Timelog Input'!B4="","",ROW()-3) -> 1 | B4: =IF('① Timelog Input'!B4="","",'① Timelog Input'!C4) -> CAS-IH_1070 | C4: =IF('① Timelog Input'!B4="","",'① Timelog Input'!B4) -> Ankit | D4: =IF('① Timelog Input'!B4="","",'① Timelog Input'!F4) -> In-house | E4: =IF('① Timelog Input'!B4="","",'① Timelog Input'!G4) -> Associate | F4: =IF('① Timelog Input'!B4="","",'① Timelog Input'!H4) -> Accounting | G4: =IF('① Timelog Input'!B4="","",'① Timelog Input'!E4) -> Jasleen.D | H4: =IF('① Timelog Input'!B4="","",'① Timelog Input'!D4) -> Jasleen.D | I4: =IF('① Timelog Input'!B4="","",IF(ISNUMBER('① Timelog Input'!I4),'① Timelog Input'!I4,0)) -> 113.42 | J4: =IF('① Timelog Input'!B4="","",IF(ISNUMBER('① Timelog Input'!J4),'① Timelog Input'!J4,0)) -> 113.42 | K4: =IF('① Timelog Input'!B4="","",Settings!B6) -> 160 | L4: =IF(OR('① Timelog Input'!B4="",K4=0),"",J4/K4) -> 0.708875 | M4: =IF('① Timelog Input'!B4="","",IFERROR(VLOOKUP(B4,'② Salary Input'!A:V,14,FALSE()),0)) -> 60000 | N4: =IF('① Timelog Input'!B4="","",IFERROR(VLOOKUP(B4,'② Salary Input'!A:V,10,FALSE()),0)) -> 0 | O4: =IF('① Timelog Input'!B4="","",IF(AND(D4="Remote",N4>0),N4,IF(K4=0,0,M4/K4))) -> 375 | P4: =IF(OR('① Timelog Input'!B4="",J4=0),"",M4/J4) -> 529.00723 | Q4: =IF('① Timelog Input'!B4="","",'① Timelog Input'!L4) -> 100% | R4: =IF('① Timelog Input'!B4="","",IF(NOT(ISNUMBER(L4)),"No Data",IF(L4>=Settings!B13,"HIGH",IF(L4>=Settings!B14,"MEDIUM","LOW")))) -> MEDIUM
A5: =IF('① Timelog Input'!B5="","",ROW()-3) -> 2 | B5: =IF('① Timelog Input'!B5="","",'① Timelog Input'!C5) -> CAS-IH_1092 | C5: =IF('① Timelog Input'!B5="","",'① Timelog Input'!B5) -> Astha.D | D5: =IF('① Timelog Input'!B5="","",'① Timelog Input'!F5) -> In-house | E5: =IF('① Timelog Input'!B5="","",'① Timelog Input'!G5) -> Associate | F5: =IF('① Timelog Input'!B5="","",'① Timelog Input'!H5) -> Accounting | G5: =IF('① Timelog Input'!B5="","",'① Timelog Input'!E5) -> Jasleen.D | H5: =IF('① Timelog Input'!B5="","",'① Timelog Input'!D5) -> Anshul Ohri | I5: =IF('① Timelog Input'!B5="","",IF(ISNUMBER('① Timelog Input'!I5),'① Timelog Input'!I5,0)) -> 156.75 | J5: =IF('① Timelog Input'!B5="","",IF(ISNUMBER('① Timelog Input'!J5),'① Timelog Input'!J5,0)) -> 156.75 | K5: =IF('① Timelog Input'!B5="","",Settings!B6) -> 160 | L5: =IF(OR('① Timelog Input'!B5="",K5=0),"",J5/K5) -> 0.9796875 | M5: =IF('① Timelog Input'!B5="","",IFERROR(VLOOKUP(B5,'② Salary Input'!A:V,14,FALSE()),0)) -> 45000 | N5: =IF('① Timelog Input'!B5="","",IFERROR(VLOOKUP(B5,'② Salary Input'!A:V,10,FALSE()),0)) -> 0 | O5: =IF('① Timelog Input'!B5="","",IF(AND(D5="Remote",N5>0),N5,IF(K5=0,0,M5/K5))) -> 281.25 | P5: =IF(OR('① Timelog Input'!B5="",J5=0),"",M5/J5) -> 287.08134 | Q5: =IF('① Timelog Input'!B5="","",'① Timelog Input'!L5) -> 100% | R5: =IF('① Timelog Input'!B5="","",IF(NOT(ISNUMBER(L5)),"No Data",IF(L5>=Settings!B13,"HIGH",IF(L5>=Settings!B14,"MEDIUM","LOW")))) -> HIGH
A6: =IF('① Timelog Input'!B6="","",ROW()-3) -> 3 | B6: =IF('① Timelog Input'!B6="","",'① Timelog Input'!C6) -> CAS-IH_1105 | C6: =IF('① Timelog Input'!B6="","",'① Timelog Input'!B6) -> Pragati.S | D6: =IF('① Timelog Input'!B6="","",'① Timelog Input'!F6) -> In-house | E6: =IF('① Timelog Input'!B6="","",'① Timelog Input'!G6) -> Asst. Team Lead | F6: =IF('① Timelog Input'!B6="","",'① Timelog Input'!H6) -> Accounting | G6: =IF('① Timelog Input'!B6="","",'① Timelog Input'!E6) -> Jasleen.D | H6: =IF('① Timelog Input'!B6="","",'① Timelog Input'!D6) -> Anshul Ohri | I6: =IF('① Timelog Input'!B6="","",IF(ISNUMBER('① Timelog Input'!I6),'① Timelog Input'!I6,0)) -> 125.58 | J6: =IF('① Timelog Input'!B6="","",IF(ISNUMBER('① Timelog Input'!J6),'① Timelog Input'!J6,0)) -> 125.58 | K6: =IF('① Timelog Input'!B6="","",Settings!B6) -> 160 | L6: =IF(OR('① Timelog Input'!B6="",K6=0),"",J6/K6) -> 0.784875 | M6: =IF('① Timelog Input'!B6="","",IFERROR(VLOOKUP(B6,'② Salary Input'!A:V,14,FALSE()),0)) -> 65000 | N6: =IF('① Timelog Input'!B6="","",IFERROR(VLOOKUP(B6,'② Salary Input'!A:V,10,FALSE()),0)) -> 0 | O6: =IF('① Timelog Input'!B6="","",IF(AND(D6="Remote",N6>0),N6,IF(K6=0,0,M6/K6))) -> 406.25 | P6: =IF(OR('① Timelog Input'!B6="",J6=0),"",M6/J6) -> 517.59834 | Q6: =IF('① Timelog Input'!B6="","",'① Timelog Input'!L6) -> 100% | R6: =IF('① Timelog Input'!B6="","",IF(NOT(ISNUMBER(L6)),"No Data",IF(L6>=Settings!B13,"HIGH",IF(L6>=Settings!B14,"MEDIUM","LOW")))) -> MEDIUM
A7: =IF('① Timelog Input'!B7="","",ROW()-3) -> 4 | B7: =IF('① Timelog Input'!B7="","",'① Timelog Input'!C7) -> CAS-IH_1109 | C7: =IF('① Timelog Input'!B7="","",'① Timelog Input'!B7) -> Anshul.O | D7: =IF('① Timelog Input'!B7="","",'① Timelog Input'!F7) -> In-house | E7: =IF('① Timelog Input'!B7="","",'① Timelog Input'!G7) -> Team Lead | F7: =IF('① Timelog Input'!B7="","",'① Timelog Input'!H7) -> Accounting | G7: =IF('① Timelog Input'!B7="","",'① Timelog Input'!E7) -> Jasleen.D | H7: =IF('① Timelog Input'!B7="","",'① Timelog Input'!D7) -> Jasleen.D | I7: =IF('① Timelog Input'!B7="","",IF(ISNUMBER('① Timelog Input'!I7),'① Timelog Input'!I7,0)) -> 157.42 | J7: =IF('① Timelog Input'!B7="","",IF(ISNUMBER('① Timelog Input'!J7),'① Timelog Input'!J7,0)) -> 157.42 | K7: =IF('① Timelog Input'!B7="","",Settings!B6) -> 160 | L7: =IF(OR('① Timelog Input'!B7="",K7=0),"",J7/K7) -> 0.983875 | M7: =IF('① Timelog Input'!B7="","",IFERROR(VLOOKUP(B7,'② Salary Input'!A:V,14,FALSE()),0)) -> 84000 | N7: =IF('① Timelog Input'!B7="","",IFERROR(VLOOKUP(B7,'② Salary Input'!A:V,10,FALSE()),0)) -> 0 | O7: =IF('① Timelog Input'!B7="","",IF(AND(D7="Remote",N7>0),N7,IF(K7=0,0,M7/K7))) -> 525 | P7: =IF(OR('① Timelog Input'!B7="",J7=0),"",M7/J7) -> 533.60437 | Q7: =IF('① Timelog Input'!B7="","",'① Timelog Input'!L7) -> 100% | R7: =IF('① Timelog Input'!B7="","",IF(NOT(ISNUMBER(L7)),"No Data",IF(L7>=Settings!B13,"HIGH",IF(L7>=Settings!B14,"MEDIUM","LOW")))) -> HIGH
A8: =IF('① Timelog Input'!B8="","",ROW()-3) -> 5 | B8: =IF('① Timelog Input'!B8="","",'① Timelog Input'!C8) -> CAS-IH_1122 | C8: =IF('① Timelog Input'!B8="","",'① Timelog Input'!B8) -> Shefali.B | D8: =IF('① Timelog Input'!B8="","",'① Timelog Input'!F8) -> In-house | E8: =IF('① Timelog Input'!B8="","",'① Timelog Input'!G8) -> Associate | F8: =IF('① Timelog Input'!B8="","",'① Timelog Input'!H8) -> Accounting | G8: =IF('① Timelog Input'!B8="","",'① Timelog Input'!E8) -> Jasleen.D | H8: =IF('① Timelog Input'!B8="","",'① Timelog Input'!D8) -> Anshul Ohri | I8: =IF('① Timelog Input'!B8="","",IF(ISNUMBER('① Timelog Input'!I8),'① Timelog Input'!I8,0)) -> 147.41 | J8: =IF('① Timelog Input'!B8="","",IF(ISNUMBER('① Timelog Input'!J8),'① Timelog Input'!J8,0)) -> 147.41 | K8: =IF('① Timelog Input'!B8="","",Settings!B6) -> 160 | L8: =IF(OR('① Timelog Input'!B8="",K8=0),"",J8/K8) -> 0.9213125 | M8: =IF('① Timelog Input'!B8="","",IFERROR(VLOOKUP(B8,'② Salary Input'!A:V,14,FALSE()),0)) -> 45000 | N8: =IF('① Timelog Input'!B8="","",IFERROR(VLOOKUP(B8,'② Salary Input'!A:V,10,FALSE()),0)) -> 0 | O8: =IF('① Timelog Input'!B8="","",IF(AND(D8="Remote",N8>0),N8,IF(K8=0,0,M8/K8))) -> 281.25 | P8: =IF(OR('① Timelog Input'!B8="",J8=0),"",M8/J8) -> 305.27101 | Q8: =IF('① Timelog Input'!B8="","",'① Timelog Input'!L8) -> 100% | R8: =IF('① Timelog Input'!B8="","",IF(NOT(ISNUMBER(L8)),"No Data",IF(L8>=Settings!B13,"HIGH",IF(L8>=Settings!B14,"MEDIUM","LOW")))) -> HIGH
A9: =IF('① Timelog Input'!B9="","",ROW()-3) -> 6 | B9: =IF('① Timelog Input'!B9="","",'① Timelog Input'!C9) -> CAS-IH_1149 | C9: =IF('① Timelog Input'!B9="","",'① Timelog Input'!B9) -> Sandesh.H | D9: =IF('① Timelog Input'!B9="","",'① Timelog Input'!F9) -> In-house | E9: =IF('① Timelog Input'!B9="","",'① Timelog Input'!G9) -> Associate | F9: =IF('① Timelog Input'!B9="","",'① Timelog Input'!H9) -> Accounting | G9: =IF('① Timelog Input'!B9="","",'① Timelog Input'!E9) -> Jasleen.D | H9: =IF('① Timelog Input'!B9="","",'① Timelog Input'!D9) -> Anshul Ohri | I9: =IF('① Timelog Input'!B9="","",IF(ISNUMBER('① Timelog Input'!I9),'① Timelog Input'!I9,0)) -> 166 | J9: =IF('① Timelog Input'!B9="","",IF(ISNUMBER('① Timelog Input'!J9),'① Timelog Input'!J9,0)) -> 166 | K9: =IF('① Timelog Input'!B9="","",Settings!B6) -> 160 | L9: =IF(OR('① Timelog Input'!B9="",K9=0),"",J9/K9) -> 1.0375 | M9: =IF('① Timelog Input'!B9="","",IFERROR(VLOOKUP(B9,'② Salary Input'!A:V,14,FALSE()),0)) -> 40000 | N9: =IF('① Timelog Input'!B9="","",IFERROR(VLOOKUP(B9,'② Salary Input'!A:V,10,FALSE()),0)) -> 0 | O9: =IF('① Timelog Input'!B9="","",IF(AND(D9="Remote",N9>0),N9,IF(K9=0,0,M9/K9))) -> 250 | P9: =IF(OR('① Timelog Input'!B9="",J9=0),"",M9/J9) -> 240.96386 | Q9: =IF('① Timelog Input'!B9="","",'① Timelog Input'!L9) -> 100% | R9: =IF('① Timelog Input'!B9="","",IF(NOT(ISNUMBER(L9)),"No Data",IF(L9>=Settings!B13,"HIGH",IF(L9>=Settings!B14,"MEDIUM","LOW")))) -> HIGH
A10: =IF('① Timelog Input'!B10="","",ROW()-3) -> 7 | B10: =IF('① Timelog Input'!B10="","",'① Timelog Input'!C10) -> CAS-IH_1162 | C10: =IF('① Timelog Input'!B10="","",'① Timelog Input'!B10) -> Robin.S | D10: =IF('① Timelog Input'!B10="","",'① Timelog Input'!F10) -> Remote | E10: =IF('① Timelog Input'!B10="","",'① Timelog Input'!G10) -> Associate | F10: =IF('① Timelog Input'!B10="","",'① Timelog Input'!H10) -> Accounting | G10: =IF('① Timelog Input'!B10="","",'① Timelog Input'!E10) -> Jasleen.D | H10: =IF('① Timelog Input'!B10="","",'① Timelog Input'!D10) -> Anshul Ohri | I10: =IF('① Timelog Input'!B10="","",IF(ISNUMBER('① Timelog Input'!I10),'① Timelog Input'!I10,0)) -> 141.24 | J10: =IF('① Timelog Input'!B10="","",IF(ISNUMBER('① Timelog Input'!J10),'① Timelog Input'!J10,0)) -> 141.24 | K10: =IF('① Timelog Input'!B10="","",Settings!B6) -> 160 | L10: =IF(OR('① Timelog Input'!B10="",K10=0),"",J10/K10) -> 0.88275 | M10: =IF('① Timelog Input'!B10="","",IFERROR(VLOOKUP(B10,'② Salary Input'!A:V,14,FALSE()),0)) -> 40000 | N10: =IF('① Timelog Input'!B10="","",IFERROR(VLOOKUP(B10,'② Salary Input'!A:V,10,FALSE()),0)) -> 0 | O10: =IF('① Timelog Input'!B10="","",IF(AND(D10="Remote",N10>0),N10,IF(K10=0,0,M10/K10))) -> 250 | P10: =IF(OR('① Timelog Input'!B10="",J10=0),"",M10/J10) -> 283.20589 | Q10: =IF('① Timelog Input'!B10="","",'① Timelog Input'!L10) -> 100% | R10: =IF('① Timelog Input'!B10="","",IF(NOT(ISNUMBER(L10)),"No Data",IF(L10>=Settings!B13,"HIGH",IF(L10>=Settings!B14,"MEDIUM","LOW")))) -> HIGH
A11: =IF('① Timelog Input'!B11="","",ROW()-3) -> 8 | B11: =IF('① Timelog Input'!B11="","",'① Timelog Input'!C11) -> CAS-RR_2371 | C11: =IF('① Timelog Input'!B11="","",'① Timelog Input'!B11) -> Vijet.B | D11: =IF('① Timelog Input'!B11="","",'① Timelog Input'!F11) -> Remote | E11: =IF('① Timelog Input'!B11="","",'① Timelog Input'!G11) -> Associate | F11: =IF('① Timelog Input'!B11="","",'① Timelog Input'!H11) -> Accounting | G11: =IF('① Timelog Input'!B11="","",'① Timelog Input'!E11) -> Jasleen.D | H11: =IF('① Timelog Input'!B11="","",'① Timelog Input'!D11) -> Anshul Ohri | I11: =IF('① Timelog Input'!B11="","",IF(ISNUMBER('① Timelog Input'!I11),'① Timelog Input'!I11,0)) -> 157.75 | J11: =IF('① Timelog Input'!B11="","",IF(ISNUMBER('① Timelog Input'!J11),'① Timelog Input'!J11,0)) -> 157.75 | K11: =IF('① Timelog Input'!B11="","",Settings!B6) -> 160 | L11: =IF(OR('① Timelog Input'!B11="",K11=0),"",J11/K11) -> 0.9859375 | M11: =IF('① Timelog Input'!B11="","",IFERROR(VLOOKUP(B11,'② Salary Input'!A:V,14,FALSE()),0)) -> 32000 | N11: =IF('① Timelog Input'!B11="","",IFERROR(VLOOKUP(B11,'② Salary Input'!A:V,10,FALSE()),0)) -> 0 | O11: =IF('① Timelog Input'!B11="","",IF(AND(D11="Remote",N11>0),N11,IF(K11=0,0,M11/K11))) -> 200 | P11: =IF(OR('① Timelog Input'!B11="",J11=0),"",M11/J11) -> 202.85261 | Q11: =IF('① Timelog Input'!B11="","",'① Timelog Input'!L11) -> 100% | R11: =IF('① Timelog Input'!B11="","",IF(NOT(ISNUMBER(L11)),"No Data",IF(L11>=Settings!B13,"HIGH",IF(L11>=Settings!B14,"MEDIUM","LOW")))) -> HIGH
A12: =IF('① Timelog Input'!B12="","",ROW()-3) -> 9 | B12: =IF('① Timelog Input'!B12="","",'① Timelog Input'!C12) -> CAS-IH_1169 | C12: =IF('① Timelog Input'!B12="","",'① Timelog Input'!B12) -> Somya.B | D12: =IF('① Timelog Input'!B12="","",'① Timelog Input'!F12) -> Retainer | E12: =IF('① Timelog Input'!B12="","",'① Timelog Input'!G12) -> Sr. Associate | F12: =IF('① Timelog Input'!B12="","",'① Timelog Input'!H12) -> Accounting | G12: =IF('① Timelog Input'!B12="","",'① Timelog Input'!E12) -> Jasleen.D | H12: =IF('① Timelog Input'!B12="","",'① Timelog Input'!D12) -> Anshul Ohri | I12: =IF('① Timelog Input'!B12="","",IF(ISNUMBER('① Timelog Input'!I12),'① Timelog Input'!I12,0)) -> 146.75 | J12: =IF('① Timelog Input'!B12="","",IF(ISNUMBER('① Timelog Input'!J12),'① Timelog Input'!J12,0)) -> 146.75 | K12: =IF('① Timelog Input'!B12="","",Settings!B6) -> 160 | L12: =IF(OR('① Timelog Input'!B12="",K12=0),"",J12/K12) -> 0.9171875 | M12: =IF('① Timelog Input'!B12="","",IFERROR(VLOOKUP(B12,'② Salary Input'!A:V,14,FALSE()),0)) -> 50000 | N12: =IF('① Timelog Input'!B12="","",IFERROR(VLOOKUP(B12,'② Salary Input'!A:V,10,FALSE()),0)) -> 0 | O12: =IF('① Timelog Input'!B12="","",IF(AND(D12="Remote",N12>0),N12,IF(K12=0,0,M12/K12))) -> 312.5 | P12: =IF(OR('① Timelog Input'!B12="",J12=0),"",M12/J12) -> 340.7155 | Q12: =IF('① Timelog Input'!B12="","",'① Timelog Input'!L12) -> 100% | R12: =IF('① Timelog Input'!B12="","",IF(NOT(ISNUMBER(L12)),"No Data",IF(L12>=Settings!B13,"HIGH",IF(L12>=Settings!B14,"MEDIUM","LOW")))) -> HIGH
A13: =IF('① Timelog Input'!B13="","",ROW()-3) -> 10 | B13: =IF('① Timelog Input'!B13="","",'① Timelog Input'!C13) -> CAS-IH_1069 | C13: =IF('① Timelog Input'!B13="","",'① Timelog Input'!B13) -> Jasleen.D | D13: =IF('① Timelog Input'!B13="","",'① Timelog Input'!F13) -> In-house | E13: =IF('① Timelog Input'!B13="","",'① Timelog Input'!G13) -> Controller | F13: =IF('① Timelog Input'!B13="","",'① Timelog Input'!H13) -> Accounting | G13: =IF('① Timelog Input'!B13="","",'① Timelog Input'!E13) -> -- | H13: =IF('① Timelog Input'!B13="","",'① Timelog Input'!D13) -> Andrew Jindal | I13: =IF('① Timelog Input'!B13="","",IF(ISNUMBER('① Timelog Input'!I13),'① Timelog Input'!I13,0)) -> 107 | J13: =IF('① Timelog Input'!B13="","",IF(ISNUMBER('① Timelog Input'!J13),'① Timelog Input'!J13,0)) -> 107 | K13: =IF('① Timelog Input'!B13="","",Settings!B6) -> 160 | L13: =IF(OR('① Timelog Input'!B13="",K13=0),"",J13/K13) -> 0.66875 | M13: =IF('① Timelog Input'!B13="","",IFERROR(VLOOKUP(B13,'② Salary Input'!A:V,14,FALSE()),0)) -> 245000 | N13: =IF('① Timelog Input'!B13="","",IFERROR(VLOOKUP(B13,'② Salary Input'!A:V,10,FALSE()),0)) -> 0 | O13: =IF('① Timelog Input'!B13="","",IF(AND(D13="Remote",N13>0),N13,IF(K13=0,0,M13/K13))) -> 1531.25 | P13: =IF(OR('① Timelog Input'!B13="",J13=0),"",M13/J13) -> 2289.7196 | Q13: =IF('① Timelog Input'!B13="","",'① Timelog Input'!L13) -> 100% | R13: =IF('① Timelog Input'!B13="","",IF(NOT(ISNUMBER(L13)),"No Data",IF(L13>=Settings!B13,"HIGH",IF(L13>=Settings!B14,"MEDIUM","LOW")))) -> MEDIUM
A14: =IF('① Timelog Input'!B14="","",ROW()-3) -> 11 | B14: =IF('① Timelog Input'!B14="","",'① Timelog Input'!C14) -> CAS-IH_1037 | C14: =IF('① Timelog Input'!B14="","",'① Timelog Input'!B14) -> Jyoti | D14: =IF('① Timelog Input'!B14="","",'① Timelog Input'!F14) -> In-house | E14: =IF('① Timelog Input'!B14="","",'① Timelog Input'!G14) -> Controller | F14: =IF('① Timelog Input'!B14="","",'① Timelog Input'!H14) -> Accounting, Business Tax, VA | G14: =IF('① Timelog Input'!B14="","",'① Timelog Input'!E14) -> -- | H14: =IF('① Timelog Input'!B14="","",'① Timelog Input'!D14) -> Andrew Jindal | I14: =IF('① Timelog Input'!B14="","",IF(ISNUMBER('① Timelog Input'!I14),'① Timelog Input'!I14,0)) -> 151.9 | J14: =IF('① Timelog Input'!B14="","",IF(ISNUMBER('① Timelog Input'!J14),'① Timelog Input'!J14,0)) -> 151.9 | K14: =IF('① Timelog Input'!B14="","",Settings!B6) -> 160 | L14: =IF(OR('① Timelog Input'!B14="",K14=0),"",J14/K14) -> 0.949375 | M14: =IF('① Timelog Input'!B14="","",IFERROR(VLOOKUP(B14,'② Salary Input'!A:V,14,FALSE()),0)) -> 0 | N14: =IF('① Timelog Input'!B14="","",IFERROR(VLOOKUP(B14,'② Salary Input'!A:V,10,FALSE()),0)) -> 0 | O14: =IF('① Timelog Input'!B14="","",IF(AND(D14="Remote",N14>0),N14,IF(K14=0,0,M14/K14))) -> 0 | P14: =IF(OR('① Timelog Input'!B14="",J14=0),"",M14/J14) -> 0 | Q14: =IF('① Timelog Input'!B14="","",'① Timelog Input'!L14) -> 100% | R14: =IF('① Timelog Input'!B14="","",IF(NOT(ISNUMBER(L14)),"No Data",IF(L14>=Settings!B13,"HIGH",IF(L14>=Settings!B14,"MEDIUM","LOW")))) -> HIGH
A15: =IF('① Timelog Input'!B15="","",ROW()-3) -> 12 | B15: =IF('① Timelog Input'!B15="","",'① Timelog Input'!C15) -> CAS-IH_1018 | C15: =IF('① Timelog Input'!B15="","",'① Timelog Input'!B15) -> Vini | D15: =IF('① Timelog Input'!B15="","",'① Timelog Input'!F15) -> In-house | E15: =IF('① Timelog Input'!B15="","",'① Timelog Input'!G15) -> Controller | F15: =IF('① Timelog Input'!B15="","",'① Timelog Input'!H15) -> HR | G15: =IF('① Timelog Input'!B15="","",'① Timelog Input'!E15) -> -- | H15: =IF('① Timelog Input'!B15="","",'① Timelog Input'!D15) -> Andrew Jindal | I15: =IF('① Timelog Input'!B15="","",IF(ISNUMBER('① Timelog Input'!I15),'① Timelog Input'!I15,0)) -> 10.42 | J15: =IF('① Timelog Input'!B15="","",IF(ISNUMBER('① Timelog Input'!J15),'① Timelog Input'!J15,0)) -> 10.42 | K15: =IF('① Timelog Input'!B15="","",Settings!B6) -> 160 | L15: =IF(OR('① Timelog Input'!B15="",K15=0),"",J15/K15) -> 0.065125 | M15: =IF('① Timelog Input'!B15="","",IFERROR(VLOOKUP(B15,'② Salary Input'!A:V,14,FALSE()),0)) -> 175000 | N15: =IF('① Timelog Input'!B15="","",IFERROR(VLOOKUP(B15,'② Salary Input'!A:V,10,FALSE()),0)) -> 0 | O15: =IF('① Timelog Input'!B15="","",IF(AND(D15="Remote",N15>0),N15,IF(K15=0,0,M15/K15))) -> 1093.75 | P15: =IF(OR('① Timelog Input'!B15="",J15=0),"",M15/J15) -> 16794.626 | Q15: =IF('① Timelog Input'!B15="","",'① Timelog Input'!L15) -> 100% | R15: =IF('① Timelog Input'!B15="","",IF(NOT(ISNUMBER(L15)),"No Data",IF(L15>=Settings!B13,"HIGH",IF(L15>=Settings!B14,"MEDIUM","LOW")))) -> LOW
A16: =IF('① Timelog Input'!B16="","",ROW()-3) -> 13 | B16: =IF('① Timelog Input'!B16="","",'① Timelog Input'!C16) -> CAS-IH_1049 | C16: =IF('① Timelog Input'!B16="","",'① Timelog Input'!B16) -> Asmita | D16: =IF('① Timelog Input'!B16="","",'① Timelog Input'!F16) -> In-house | E16: =IF('① Timelog Input'!B16="","",'① Timelog Input'!G16) -> Sr. Associate | F16: =IF('① Timelog Input'!B16="","",'① Timelog Input'!H16) -> Accounting, Business Tax | G16: =IF('① Timelog Input'!B16="","",'① Timelog Input'!E16) -> Jyoti | H16: =IF('① Timelog Input'!B16="","",'① Timelog Input'!D16) -> Jyoti | I16: =IF('① Timelog Input'!B16="","",IF(ISNUMBER('① Timelog Input'!I16),'① Timelog Input'!I16,0)) -> 115.67 | J16: =IF('① Timelog Input'!B16="","",IF(ISNUMBER('① Timelog Input'!J16),'① Timelog Input'!J16,0)) -> 115.67 | K16: =IF('① Timelog Input'!B16="","",Settings!B6) -> 160 | L16: =IF(OR('① Timelog Input'!B16="",K16=0),"",J16/K16) -> 0.7229375 | M16: =IF('① Timelog Input'!B16="","",IFERROR(VLOOKUP(B16,'② Salary Input'!A:V,14,FALSE()),0)) -> 62500 | N16: =IF('① Timelog Input'!B16="","",IFERROR(VLOOKUP(B16,'② Salary Input'!A:V,10,FALSE()),0)) -> 0 | O16: =IF('① Timelog Input'!B16="","",IF(AND(D16="Remote",N16>0),N16,IF(K16=0,0,M16/K16))) -> 390.625 | P16: =IF(OR('① Timelog Input'!B16="",J16=0),"",M16/J16) -> 540.33025 | Q16: =IF('① Timelog Input'!B16="","",'① Timelog Input'!L16) -> 100% | R16: =IF('① Timelog Input'!B16="","",IF(NOT(ISNUMBER(L16)),"No Data",IF(L16>=Settings!B13,"HIGH",IF(L16>=Settings!B14,"MEDIUM","LOW")))) -> MEDIUM
A17: =IF('① Timelog Input'!B17="","",ROW()-3) -> 14 | B17: =IF('① Timelog Input'!B17="","",'① Timelog Input'!C17) -> CAS-IH_1041 | C17: =IF('① Timelog Input'!B17="","",'① Timelog Input'!B17) -> Nikita | D17: =IF('① Timelog Input'!B17="","",'① Timelog Input'!F17) -> In-house | E17: =IF('① Timelog Input'!B17="","",'① Timelog Input'!G17) -> Controller | F17: =IF('① Timelog Input'!B17="","",'① Timelog Input'!H17) -> Accounting, Business Tax, VA, L&D | G17: =IF('① Timelog Input'!B17="","",'① Timelog Input'!E17) -> -- | H17: =IF('① Timelog Input'!B17="","",'① Timelog Input'!D17) -> Andrew Jindal | I17: =IF('① Timelog Input'!B17="","",IF(ISNUMBER('① Timelog Input'!I17),'① Timelog Input'!I17,0)) -> 101 | J17: =IF('① Timelog Input'!B17="","",IF(ISNUMBER('① Timelog Input'!J17),'① Timelog Input'!J17,0)) -> 101 | K17: =IF('① Timelog Input'!B17="","",Settings!B6) -> 160 | L17: =IF(OR('① Timelog Input'!B17="",K17=0),"",J17/K17) -> 0.63125 | M17: =IF('① Timelog Input'!B17="","",IFERROR(VLOOKUP(B17,'② Salary Input'!A:V,14,FALSE()),0)) -> 280000 | N17: =IF('① Timelog Input'!B17="","",IFERROR(VLOOKUP(B17,'② Salary Input'!A:V,10,FALSE()),0)) -> 0 | O17: =IF('① Timelog Input'!B17="","",IF(AND(D17="Remote",N17>0),N17,IF(K17=0,0,M17/K17))) -> 1750 | P17: =IF(OR('① Timelog Input'!B17="",J17=0),"",M17/J17) -> 2772.2772 | Q17: =IF('① Timelog Input'!B17="","",'① Timelog Input'!L17) -> 100% | R17: =IF('① Timelog Input'!B17="","",IF(NOT(ISNUMBER(L17)),"No Data",IF(L17>=Settings!B13,"HIGH",IF(L17>=Settings!B14,"MEDIUM","LOW")))) -> LOW
